Workbook

Sheet Time Table
G1: =sumif($F$26:$F$40,F1,$B$26:$B$40) -> 0
F2: {=UNIQUE(F26:F40)} -> health | G2: =sumif($F$26:$F$40,F2,$B$26:$B$40) -> 10.5
F3: fitness | G3: =sumif($F$26:$F$40,F3,$B$26:$B$40) -> 1.5
F4: hygene | G4: =sumif($F$26:$F$40,F4,$B$26:$B$40) -> 1.5
A5: =sum(A8:A936) -> 0 | B5: =sum(B8:B936) -> 26 | F5: wealth | G5: =sumif($F$26:$F$40,F5,$B$26:$B$40) -> 11
F6: rest | G6: =sumif($F$26:$F$40,F6,$B$26:$B$40) -> 1.5
G7: =sumif($F$26:$F$40,F7,$B$26:$B$40) -> 0
R8: =SUM(R10:R936) -> 3.5 | Z8: Available Time / Week | AA8: =7*24 -> 168
A9: Monthly Income | B9: Weekly Income | C9: Column 1 | D9: Column 2 | E9: Monday | F9: Column 12 | G9: Column 13 | H9: Tuesday | I9: Wednesday | J9: Thursday | K9: Friday | L9: Saturday | M9: Sunday | R9: HRS | S9: COUNT | AA9: =sum(J8:J936) -> 0 | AN9: =sum(AN10:AN18) -> 13787
C10: 0.20833333 | D10: 0.25 | E10: wakeup and pranayama | H10: wakeup and pranayama | I10: wakeup and pranayama | J10: wakeup and pranayama | K10: wakeup and pranayama | L10: wakeup and pranayama | M10: wakeup and pranayama | R10: =S10/2 -> 0 | S10: =COUNTIF(Table2[[Monday]:[Sunday]],T10) -> 0 | T10: BRUSH & BATH | Y10: Daily | Z10: Repeats/Week | AA10: Weekly | AN10: 5
C11: 0.25 | D11: 0.29166667 | E11: walking | H11: walking | I11: walking | J11: walking | K11: walking | L11: walking | M11: walking | R11: =S11/2 -> 0 | S11: =COUNTIF(Table2[[Monday]:[Sunday]],T11) -> 0 | T11: TRIP TO STADIUM | V11: 0.22916667 | W11: 0.33333333 | X11: Badminton, Brush, Bath, Temple, Breakfast | Y11: 2.5 | Z11: 7 | AA11: =Y11*Z11 -> 17.5 | AN11: 801
C12: 0.29166667 | D12: 0.3125 | E12: brush and bath | H12: brush and bath | I12: brush and bath | J12: brush and bath | K12: brush and bath | L12: brush and bath | M12: brush and bath | R12: =S12/2 -> 0 | S12: =COUNTIF(Table2[[Monday]:[Sunday]],T12) -> 0 | T12: BADMINTON | V12: 0.33333333 | W12: 0.41666667 | X12: Freelancing - Ishika | Y12: 2 | Z12: 5 | AA12: =Y12*Z12 -> 10 | AN12: 1588
C13: 0.3125 | D13: 0.39583333 | E13: ishika freelance support | H13: ishika freelance support | I13: ishika freelance support | J13: ishika freelance support | K13: ishika freelance support | R13: =S13/2 -> 0 | S13: =COUNTIF(Table2[[Monday]:[Sunday]],T13) -> 0 | T13: TRIP TO TEMPLE | V13: 0.41666667 | W13: 0.625 | X13: Trading - Akshay | Y13: 3 | Z13: 5 | AA13: =Y13*Z13 -> 15 | AN13: 1612
C14: 0.39583333 | D14: 0.4375 | E14: suryanamaskar and breakfast with medicine | H14: suryanamaskar and breakfast with medicine | I14: suryanamaskar and breakfast with medicine | J14: suryanamaskar and breakfast with medicine | K14: suryanamaskar and breakfast with medicine | L14: suryanamaskar and breakfast with medicine | M14: suryanamaskar and breakfast with medicine | R14: =S14/2 -> 0 | S14: =COUNTIF(Table2[[Monday]:[Sunday]],T14) -> 0 | T14: BREAKFAST | V14: 0.41666667 | W14: 0.625 | X14: Youtube - Intellect Reef | Y14: 3 | Z14: 1 | AA14: =Y14*Z14 -> 3 | AN14: 18
C15: 0.4375 | D15: 0.5625 | E15: office work 3 hrs | H15: office work 3 hrs | I15: office work 3 hrs | J15: office work 3 hrs | K15: office work 3 hrs | R15: =S15/2 -> 0 | S15: =COUNTIF(Table2[[Monday]:[Sunday]],T15) -> 0 | T15: FREELANCING - ISHIKA | V15: 0.41666667 | W15: 0.625 | X15: Youtube - Coding Reef | Y15: 3 | Z15: 1 | AA15: =Y15*Z15 -> 3 | AN15: 1712
C16: 0.5625 | D16: 0.60416667 | E16: suryanamaskar and lunch | H16: suryanamaskar and lunch | I16: suryanamaskar and lunch | J16: suryanamaskar and lunch | K16: suryanamaskar and lunch | L16: suryanamaskar and lunch | M16: suryanamaskar and lunch | R16: =S16/2 -> 0 | S16: =COUNTIF(Table2[[Monday]:[Sunday]],T16) -> 0 | T16: OFFICE | V16: 0.41666667 | W16: 0.625 | X16: Book Publishing | Y16: 4 | Z16: 1 | AA16: =Y16*Z16 -> 4 | AN16: 1674
C17: 0.60416667 | D17: 0.72916667 | E17: office work 3 hrs | H17: office work 3 hrs | I17: office work 3 hrs | J17: office work 3 hrs | K17: office work 3 hrs | R17: =S17/2 -> 0 | S17: =COUNTIF(Table2[[Monday]:[Sunday]],T17) -> 0 | T17: TRADING - AKSHAY | V17: 0.625 | W17: 0.70833333 | X17: Sleep | Y17: 2 | Z17: 7 | AA17: =Y17*Z17 -> 14 | AN17: 3372
C18: 0.72916667 | D18: 0.77083333 | E18: suryanamaskar and dinner with medicine | H18: suryanamaskar and dinner with medicine | I18: suryanamaskar and dinner with medicine | J18: suryanamaskar and dinner with medicine | K18: suryanamaskar and dinner with medicine | L18: suryanamaskar and dinner with medicine | M18: suryanamaskar and dinner with medicine | R18: =S18/2 -> 3.5 | S18: =COUNTIF(Table2[[Monday]:[Sunday]],T18) -> 7 | T18: SLEEP | V18: 0.70833333 | W18: 0.77083333 | X18: Freelancing - Soujanya | Y18: 1.5 | Z18: 5 | AA18: =Y18*Z18 -> 7.5 | AN18: 3005
C19: 0.77083333 | D19: 0.79166667 | E19: walking | H19: walking | I19: walking | J19: walking | K19: walking | L19: walking | M19: walking | R19: =S19/2 -> 0 | S19: =COUNTIF(Table2[[Monday]:[Sunday]],T19) -> 0 | T19: FREELANCING - SOUJANYA | V19: 0.77083333 | W19: 0 | X19: Job Apptware Solutiona | Y19: 5.5 | Z19: 5 | AA19: =Y19*Z19 -> 27.5
C20: 0.79166667 | D20: 0.85416667 | E20: mits soujanya freelance support | H20: mits soujanya freelance support | I20: mits soujanya freelance support | J20: mits soujanya freelance support | K20: mits soujanya freelance support | R20: =S20/2 -> 0 | S20: =COUNTIF(Table2[[Monday]:[Sunday]],T20) -> 0 | T20: YOUTUBE - INTELLECT REEF | V20: 0 | W20: 0.20833333 | X20: Sleep | Y20: 5 | Z20: 7 | AA20: =Y20*Z20 -> 35
C21: 0.85416667 | D21: 0.9375 | E21: office work 2 hrs | H21: office work 2 hrs | I21: office work 2 hrs | J21: office work 2 hrs | K21: office work 2 hrs | R21: =S21/2 -> 0 | S21: =COUNTIF(Table2[[Monday]:[Sunday]],T21) -> 0 | T21: YOUTUBE - CODING REEF | X21: App Development | Y21: 8 | Z21: 1 | AA21: =Y21*Z21 -> 8
C22: 0.9375 | D22: 0.95833333 | E22: evening rituals and sleep | H22: evening rituals and sleep | I22: evening rituals and sleep | J22: evening rituals and sleep | K22: evening rituals and sleep | L22: evening rituals and sleep | M22: evening rituals and sleep | R22: =S22/2 -> 0 | S22: =COUNTIF(Table2[[Monday]:[Sunday]],T22) -> 0 | T22: App Development | X22: Professional Development | Y22: 8 | Z22: 1 | AA22: =Y22*Z22 -> 8
R23: =S23/2 -> 0 | S23: =COUNTIF(Table2[[Monday]:[Sunday]],T23) -> 0 | T23: LAUNDARY
R24: =S24/2 -> 0 | S24: =COUNTIF(Table2[[Monday]:[Sunday]],T24) -> 0 | T24: Professional Development
R25: =S25/2 -> 0 | S25: =COUNTIF(Table2[[Monday]:[Sunday]],T25) -> 0 | T25: Book Publishing
B26: 1 | C26: 0.20833333 | D26: 0.25 | E26: wakeup and pranayama | F26: health | H26: wakeup and pranayama | I26: wakeup and pranayama | J26: wakeup and pranayama | K26: wakeup and pranayama | L26: wakeup and pranayama | M26: wakeup and pranayama
B27: 1 | C27: 0.25 | D27: 0.29166667 | E27: walking | F27: fitness | H27: walking | I27: walking | J27: walking | K27: walking | L27: walking | M27: walking
B28: 1.5 | C28: 0.29166667 | D28: 0.3125 | E28: brush and bath | F28: hygene | H28: brush and bath | I28: brush and bath | J28: brush and bath | K28: brush and bath | L28: brush and bath | M28: brush and bath
B29: 2 | C29: 0.3125 | D29: 0.39583333 | E29: ishika freelance support 2 hrs office | F29: wealth | H29: ishika freelance support 2 hrs office | I29: ishika freelance support 2 hrs office | J29: ishika freelance support 2 hrs office | K29: ishika freelance support 2 hrs office
B30: 1 | C30: 0.39583333 | D30: 0.4375 | E30: suryanamaskar and breakfast with medicine | F30: health | H30: suryanamaskar and breakfast with medicine | I30: suryanamaskar and breakfast with medicine | J30: suryanamaskar and breakfast with medicine | K30: suryanamaskar and breakfast with medicine | L30: suryanamaskar and breakfast with medicine | M30: suryanamaskar and breakfast with medicine
B31: 3 | C31: 0.4375 | D31: 0.5625 | E31: office work 3 hrs | F31: wealth | H31: office work 3 hrs | I31: office work 3 hrs | J31: office work 3 hrs | K31: office work 3 hrs
B32: 1 | C32: 0.5625 | D32: 0.60416667 | E32: suryanamaskar and lunch | F32: health | H32: suryanamaskar and lunch | I32: suryanamaskar and lunch | J32: suryanamaskar and lunch | K32: suryanamaskar and lunch | L32: suryanamaskar and lunch | M32: suryanamaskar and lunch
B33: 2 | C33: 0.60416667 | D33: 0.6875 | E33: office work 2 hrs | F33: wealth | H33: office work 2 hrs | I33: office work 2 hrs | J33: office work 2 hrs | K33: office work 2 hrs
B34: 1.5 | C34: 0.6875 | D34: 0.70833333 | E34: rest | F34: rest | H34: rest | I34: rest | J34: rest | K34: rest | L34: rest | M34: rest
B35: 1.5 | C35: 0.70833333 | D35: 0.77083333 | E35: mits soujanya freelance support 1.5 hrs office | F35: wealth | H35: mits soujanya freelance support 1.5 hrs office | I35: mits soujanya freelance support 1.5 hrs office | J35: mits soujanya freelance support 1.5 hrs office | K35: mits soujanya freelance support 1.5 hrs office
B36: 1 | C36: 0.77083333 | D36: 0.8125 | E36: suryanamaskar and dinner | F36: health | H36: suryanamaskar and dinner | I36: suryanamaskar and dinner | J36: suryanamaskar and dinner | K36: suryanamaskar and dinner | L36: suryanamaskar and dinner | M36: suryanamaskar and dinner
B37: 0.5 | C37: 0.8125 | D37: 0.83333333 | E37: walking | F37: fitness | H37: walking | I37: walking | J37: walking | K37: walking | L37: walking | M37: walking
B38: 2.5 | C38: 0.83333333 | D38: 0.9375 | E38: office work 2.5 hrs | F38: wealth | H38: office work 2.5 hrs | I38: office work 2.5 hrs | J38: office work 2.5 hrs | K38: office work 2.5 hrs
B39: 0.5 | C39: 0.9375 | D39: 0.95833333 | E39: evening rituals and sleep | F39: health | H39: evening rituals and sleep | I39: evening rituals and sleep | J39: evening rituals and sleep | K39: evening rituals and sleep | L39: evening rituals and sleep | M39: evening rituals and sleep
B40: 6 | C40: 0.95833333 | D40: 0.20833333 | E40: sleep | F40: health | H40: sleep | I40: sleep | J40: sleep | K40: sleep | L40: sleep | M40: sleep

Sheet Copy of Time Table
A5: =sum(A8:A935) -> 0 | B5: =sum(B8:B935) -> 0
P8: =SUM(P10:P935) -> 165 | X8: Available Time / Week | Y8: =7*24 -> 168
A9: Monthly Income | B9: Weekly Income | C9: Column 1 | D9: Column 2 | E9: Monday | F9: Tuesday | G9: Wednesday | H9: Thursday | I9: Friday | J9: Saturday | K9: Sunday | P9: HRS | Q9: COUNT | Y9: =sum(H8:H935) -> 0 | AL9: =sum(AL10:AL18) -> 13787
C10: 1.2083333 | D10: 1.2291667 | E10: BRUSH & BATH | F10: BRUSH & BATH | G10: BRUSH & BATH | H10: BRUSH & BATH | I10: BRUSH & BATH | J10: BRUSH & BATH | K10: BRUSH & BATH | P10: =Q10/2 -> 3.5 | Q10: =COUNTIF(Table2_2[[Monday]:[Sunday]],R10) -> 7 | R10: BRUSH & BATH | W10: Daily | X10: Repeats/Week | Y10: Weekly | AL10: 5
C11: 1.2291667 | D11: 1.25 | E11: TRIP TO STADIUM | F11: TRIP TO STADIUM | G11: TRIP TO STADIUM | H11: TRIP TO STADIUM | I11: TRIP TO STADIUM | J11: TRIP TO STADIUM | K11: TRIP TO STADIUM | P11: =Q11/2 -> 3.5 | Q11: =COUNTIF(Table2_2[[Monday]:[Sunday]],R11) -> 7 | R11: TRIP TO STADIUM | T11: 0.22916667 | U11: 0.33333333 | V11: Badminton, Brush, Bath, Temple, Breakfast | W11: 2.5 | X11: 7 | Y11: =W11*X11 -> 17.5 | AL11: 801
C12: 0.25 | D12: 0.27083333 | E12: BADMINTON | F12: BADMINTON | G12: BADMINTON | H12: BADMINTON | I12: BADMINTON | J12: BADMINTON | K12: BADMINTON | P12: =Q12/2 -> 7 | Q12: =COUNTIF(Table2_2[[Monday]:[Sunday]],R12) -> 14 | R12: BADMINTON | T12: 0.33333333 | U12: 0.41666667 | V12: Freelancing - Ishika | W12: 2 | X12: 5 | Y12: =W12*X12 -> 10 | AL12: 1588
C13: 0.27083333 | D13: 0.29166667 | E13: BADMINTON | F13: BADMINTON | G13: BADMINTON | H13: BADMINTON | I13: BADMINTON | J13: BADMINTON | K13: BADMINTON | P13: =Q13/2 -> 3.5 | Q13: =COUNTIF(Table2_2[[Monday]:[Sunday]],R13) -> 7 | R13: TRIP TO TEMPLE | T13: 0.41666667 | U13: 0.625 | V13: Trading - Akshay | W13: 3 | X13: 5 | Y13: =W13*X13 -> 15 | AL13: 1612
C14: 0.29166667 | D14: 0.3125 | E14: TRIP TO TEMPLE | F14: TRIP TO TEMPLE | G14: TRIP TO TEMPLE | H14: TRIP TO TEMPLE | I14: TRIP TO TEMPLE | J14: TRIP TO TEMPLE | K14: TRIP TO TEMPLE | P14: =Q14/2 -> 3.5 | Q14: =COUNTIF(Table2_2[[Monday]:[Sunday]],R14) -> 7 | R14: BREAKFAST | T14: 0.41666667 | U14: 0.625 | V14: Youtube - Intellect Reef | W14: 3 | X14: 1 | Y14: =W14*X14 -> 3 | AL14: 18
C15: 0.3125 | D15: 0.33333333 | E15: BREAKFAST | F15: BREAKFAST | G15: BREAKFAST | H15: BREAKFAST | I15: BREAKFAST | J15: BREAKFAST | K15: BREAKFAST | P15: =Q15/2 -> 10 | Q15: =COUNTIF(Table2_2[[Monday]:[Sunday]],R15) -> 20 | R15: FREELANCING - ISHIKA | T15: 0.41666667 | U15: 0.625 | V15: Youtube - Coding Reef | W15: 3 | X15: 1 | Y15: =W15*X15 -> 3 | AL15: 1712
C16: 0.33333333 | D16: 0.35416667 | E16: FREELANCING - ISHIKA | F16: FREELANCING - ISHIKA | G16: FREELANCING - ISHIKA | H16: FREELANCING - ISHIKA | I16: FREELANCING - ISHIKA | J16: YOUTUBE - INTELLECT REEF | K16: YOUTUBE - CODING REEF | P16: =Q16/2 -> 40 | Q16: =COUNTIF(Table2_2[[Monday]:[Sunday]],R16) -> 80 | R16: OFFICE | T16: 0.41666667 | U16: 0.625 | V16: Book Publishing | W16: 4 | X16: 1 | Y16: =W16*X16 -> 4 | AL16: 1674
C17: 0.35416667 | D17: 0.375 | E17: FREELANCING - ISHIKA | F17: FREELANCING - ISHIKA | G17: FREELANCING - ISHIKA | H17: FREELANCING - ISHIKA | I17: FREELANCING - ISHIKA | J17: YOUTUBE - INTELLECT REEF | K17: YOUTUBE - CODING REEF | P17: =Q17/2 -> 17.5 | Q17: =COUNTIF(Table2_2[[Monday]:[Sunday]],R17) -> 35 | R17: TRADING - AKSHAY | T17: 0.625 | U17: 0.70833333 | V17: Sleep | W17: 2 | X17: 7 | Y17: =W17*X17 -> 14 | AL17: 3372
C18: 0.375 | D18: 0.39583333 | E18: FREELANCING - ISHIKA | F18: FREELANCING - ISHIKA | G18: FREELANCING - ISHIKA | H18: FREELANCING - ISHIKA | I18: FREELANCING - ISHIKA | J18: YOUTUBE - INTELLECT REEF | K18: YOUTUBE - CODING REEF | P18: =Q18/2 -> 42 | Q18: =COUNTIF(Table2_2[[Monday]:[Sunday]],R18) -> 84 | R18: SLEEP | T18: 0.70833333 | U18: 0.77083333 | V18: Freelancing - Soujanya | W18: 1.5 | X18: 5 | Y18: =W18*X18 -> 7.5 | AL18: 3005
C19: 0.39583333 | D19: 0.41666667 | E19: FREELANCING - ISHIKA | F19: FREELANCING - ISHIKA | G19: FREELANCING - ISHIKA | H19: FREELANCING - ISHIKA | I19: FREELANCING - ISHIKA | J19: YOUTUBE - INTELLECT REEF | K19: YOUTUBE - CODING REEF | P19: =Q19/2 -> 7.5 | Q19: =COUNTIF(Table2_2[[Monday]:[Sunday]],R19) -> 15 | R19: FREELANCING - SOUJANYA | T19: 0.77083333 | U19: 0 | V19: Job Apptware Solutiona | W19: 5.5 | X19: 5 | Y19: =W19*X19 -> 27.5
C20: 0.41666667 | D20: 0.4375 | E20: OFFICE | F20: OFFICE | G20: OFFICE | H20: OFFICE | I20: OFFICE | J20: LAUNDARY | K20: LAUNDARY | P20: =Q20/2 -> 3 | Q20: =COUNTIF(Table2_2[[Monday]:[Sunday]],R20) -> 6 | R20: YOUTUBE - INTELLECT REEF | T20: 0 | U20: 0.20833333 | V20: Sleep | W20: 5 | X20: 7 | Y20: =W20*X20 -> 35
C21: 0.4375 | D21: 0.45833333 | E21: TRADING - AKSHAY | F21: TRADING - AKSHAY | G21: TRADING - AKSHAY | H21: TRADING - AKSHAY | I21: TRADING - AKSHAY | J21: YOUTUBE - INTELLECT REEF | K21: YOUTUBE - CODING REEF | P21: =Q21/2 -> 4 | Q21: =COUNTIF(Table2_2[[Monday]:[Sunday]],R21) -> 8 | R21: YOUTUBE - CODING REEF | V21: App Development | W21: 8 | X21: 1 | Y21: =W21*X21 -> 8
C22: 0.45833333 | D22: 0.47916667 | E22: TRADING - AKSHAY | F22: TRADING - AKSHAY | G22: TRADING - AKSHAY | H22: TRADING - AKSHAY | I22: TRADING - AKSHAY | J22: YOUTUBE - INTELLECT REEF | K22: YOUTUBE - CODING REEF | P22: =Q22/2 -> 5 | Q22: =COUNTIF(Table2_2[[Monday]:[Sunday]],R22) -> 10 | R22: App Development | V22: Professional Development | W22: 8 | X22: 1 | Y22: =W22*X22 -> 8
C23: 0.47916667 | D23: 0.5 | E23: TRADING - AKSHAY | F23: TRADING - AKSHAY | G23: TRADING - AKSHAY | H23: TRADING - AKSHAY | I23: TRADING - AKSHAY | J23: App Development | K23: YOUTUBE - CODING REEF | P23: =Q23/2 -> 3 | Q23: =COUNTIF(Table2_2[[Monday]:[Sunday]],R23) -> 6 | R23: LAUNDARY
C24: 0.5 | D24: 0.52083333 | E24: TRADING - AKSHAY | F24: TRADING - AKSHAY | G24: TRADING - AKSHAY | H24: TRADING - AKSHAY | I24: TRADING - AKSHAY | J24: App Development | K24: YOUTUBE - CODING REEF | P24: =Q24/2 -> 6 | Q24: =COUNTIF(Table2_2[[Monday]:[Sunday]],R24) -> 12 | R24: Professional Development
C25: 0.52083333 | D25: 0.54166667 | E25: OFFICE | F25: OFFICE | G25: OFFICE | H25: OFFICE | I25: OFFICE | J25: LAUNDARY | K25: LAUNDARY | P25: =Q25/2 -> 6 | Q25: =COUNTIF(Table2_2[[Monday]:[Sunday]],R25) -> 12 | R25: Book Publishing
C26: 0.54166667 | D26: 0.5625 | E26: OFFICE | F26: OFFICE | G26: OFFICE | H26: OFFICE | I26: OFFICE | J26: App Development | K26: App Development
C27: 0.5625 | D27: 0.58333333 | E27: TRADING - AKSHAY | F27: TRADING - AKSHAY | G27: TRADING - AKSHAY | H27: TRADING - AKSHAY | I27: TRADING - AKSHAY | J27: App Development | K27: App Development
C28: 0.58333333 | D28: 0.60416667 | E28: TRADING - AKSHAY | F28: TRADING - AKSHAY | G28: TRADING - AKSHAY | H28: TRADING - AKSHAY | I28: TRADING - AKSHAY | J28: App Development | K28: App Development
C29: 0.60416667 | D29: 0.625 | E29: TRADING - AKSHAY | F29: TRADING - AKSHAY | G29: TRADING - AKSHAY | H29: TRADING - AKSHAY | I29: TRADING - AKSHAY | J29: App Development | K29: App Development
C30: 0.625 | D30: 0.64583333 | E30: SLEEP | F30: SLEEP | G30: SLEEP | H30: SLEEP | I30: SLEEP | J30: SLEEP | K30: SLEEP
C31: 0.64583333 | D31: 0.66666667 | E31: SLEEP | F31: SLEEP | G31: SLEEP | H31: SLEEP | I31: SLEEP | J31: SLEEP | K31: SLEEP
C32: 0.66666667 | D32: 0.6875 | E32: SLEEP | F32: SLEEP | G32: SLEEP | H32: SLEEP | I32: SLEEP | J32: SLEEP | K32: SLEEP
C33: 0.6875 | D33: 0.70833333 | E33: SLEEP | F33: SLEEP | G33: SLEEP | H33: SLEEP | I33: SLEEP | J33: SLEEP | K33: SLEEP
C34: 0.70833333 | D34: 0.72916667 | E34: FREELANCING - SOUJANYA | F34: FREELANCING - SOUJANYA | G34: FREELANCING - SOUJANYA | H34: FREELANCING - SOUJANYA | I34: FREELANCING - SOUJANYA | J34: Professional Development | K34: Professional Development
C35: 0.72916667 | D35: 0.75 | E35: FREELANCING - SOUJANYA | F35: FREELANCING - SOUJANYA | G35: FREELANCING - SOUJANYA | H35: FREELANCING - SOUJANYA | I35: FREELANCING - SOUJANYA | J35: Professional Development | K35: Professional Development
C36: 0.75 | D36: 0.77083333 | E36: FREELANCING - SOUJANYA | F36: FREELANCING - SOUJANYA | G36: FREELANCING - SOUJANYA | H36: FREELANCING - SOUJANYA | I36: FREELANCING - SOUJANYA | J36: Professional Development | K36: Professional Development
C37: 0.77083333 | D37: 0.79166667 | E37: OFFICE | F37: OFFICE | G37: OFFICE | H37: OFFICE | I37: OFFICE | J37: Professional Development | K37: Professional Development
C38: 0.79166667 | D38: 0.8125 | E38: OFFICE | F38: OFFICE | G38: OFFICE | H38: OFFICE | I38: OFFICE
C39: 0.8125 | D39: 0.83333333 | E39: OFFICE | F39: OFFICE | G39: OFFICE | H39: OFFICE | I39: OFFICE | J39: Professional Development | K39: Professional Development
C40: 0.83333333 | D40: 0.85416667 | E40: OFFICE | F40: OFFICE | G40: OFFICE | H40: OFFICE | I40: OFFICE | J40: Professional Development | K40: Professional Development
C41: 0.85416667 | D41: 0.875 | E41: OFFICE | F41: OFFICE | G41: OFFICE | H41: OFFICE | I41: OFFICE
C42: 0.875 | D42: 0.89583333 | E42: OFFICE | F42: OFFICE | G42: OFFICE | H42: OFFICE | I42: OFFICE | J42: Book Publishing | K42: Book Publishing
C43: 0.89583333 | D43: 0.91666667 | E43: OFFICE | F43: OFFICE | G43: OFFICE | H43: OFFICE | I43: OFFICE | J43: Book Publishing | K43: Book Publishing
C44: 0.91666667 | D44: 0.9375 | E44: OFFICE | F44: OFFICE | G44: OFFICE | H44: OFFICE | I44: OFFICE | J44: Book Publishing | K44: Book Publishing
C45: 0.9375 | D45: 0.95833333 | E45: OFFICE | F45: OFFICE | G45: OFFICE | H45: OFFICE | I45: OFFICE | J45: Book Publishing | K45: Book Publishing
C46: 0.95833333 | D46: 0.97916667 | E46: OFFICE | F46: OFFICE | G46: OFFICE | H46: OFFICE | I46: OFFICE | J46: Book Publishing | K46: Book Publishing
C47: 0.97916667 | D47: 1 | E47: OFFICE | F47: OFFICE | G47: OFFICE | H47: OFFICE | I47: OFFICE | J47: Book Publishing | K47: Book Publishing
C48: 1 | D48: 1.0208333 | E48: OFFICE | F48: OFFICE | G48: OFFICE | H48: OFFICE | I48: OFFICE
C49: 1.0208333 | D49: 1.0416667 | E49: OFFICE | F49: OFFICE | G49: OFFICE | H49: OFFICE | I49: OFFICE | J49: LAUNDARY | K49: LAUNDARY
C50: 1.0416667 | D50: 1.0625 | E50: SLEEP | F50: SLEEP | G50: SLEEP | H50: SLEEP | I50: SLEEP | J50: SLEEP | K50: SLEEP
C51: 1.0625 | D51: 1.0833333 | E51: SLEEP | F51: SLEEP | G51: SLEEP | H51: SLEEP | I51: SLEEP | J51: SLEEP | K51: SLEEP
C52: 1.0833333 | D52: 1.1041667 | E52: SLEEP | F52: SLEEP | G52: SLEEP | H52: SLEEP | I52: SLEEP | J52: SLEEP | K52: SLEEP
C53: 1.1041667 | D53: 1.125 | E53: SLEEP | F53: SLEEP | G53: SLEEP | H53: SLEEP | I53: SLEEP | J53: SLEEP | K53: SLEEP
C54: 1.125 | D54: 1.1458333 | E54: SLEEP | F54: SLEEP | G54: SLEEP | H54: SLEEP | I54: SLEEP | J54: SLEEP | K54: SLEEP
C55: 1.1458333 | D55: 1.1666667 | E55: SLEEP | F55: SLEEP | G55: SLEEP | H55: SLEEP | I55: SLEEP | J55: SLEEP | K55: SLEEP
C56: 1.1666667 | D56: 1.1875 | E56: SLEEP | F56: SLEEP | G56: SLEEP | H56: SLEEP | I56: SLEEP | J56: SLEEP | K56: SLEEP
C57: 1.1875 | D57: 1.2083333 | E57: SLEEP | F57: SLEEP | G57: SLEEP | H57: SLEEP | I57: SLEEP | J57: SLEEP | K57: SLEEP

Sheet Planned Expenses
A1: 44927 | F1: Balance | G1: Investment | H1: Investment | I1: Expense
D2: Pending | G2: Paid | H2: Paid | I2: Paid
A3: Fixed Factor | B3: 1000 | F3: Due Date | G3: 44580 | H3: 44583 | I3: 44928
A4: 17263.21 | D4: 0 | I4: Axis 2009
A5: Remaining | D5: Savings | E5: 45032 | F5: Balance | G5: Mutual Funds | H5: Mutual Funds | I5: CC Bill
A6: 3647.26 | D6: 0 | E6: ICICI 3945 | F6: 3647.26
A7: 10000.62 | D7: 0 | E7: Axis 0370 | F7: 10000.62 | G7: 500 | H7: 3000 | I7: 4526.4
A8: 500.98 | D8: 0 | E8: Axis 7503 | F8: 500.98
A9: 513.57 | D9: 0 | E9: HSBC 9006 | F9: 513.57
A10: 2100 | D10: 0 | E10: Paytm 4366 | F10: 2100
A11: 500.78 | D11: 0 | E11: SBI 5825 | F11: 500.78
A12: 0 | D12: 0 | E12: Paytm Wallet | F12: 0
A13: 0 | D13: 0 | E13: Phonepe Wallet | F13: 0
A15: 44958 | F15: Balance | G15: Investment | H15: Investment | I15: Expense
D16: Pending | G16: Paid | H16: Paid | I16: Paid
A17: Fixed Factor | B17: 1000 | F17: Due Date | G17: 44945 | H17: 44950 | I17: 44928
A18: 3552.81 | D18: 0 | I18: Axis 2009
A19: Remaining | D19: Savings | E19: 45032 | F19: Balance | G19: Mutual Funds | H19: Mutual Funds | I19: CC Bill
A20: 210.47 | D20: 0 | E20: ICICI 3945 | F20: 210.47
A21: 1018.5 | D21: 0 | E21: Axis 0370 | F21: 1018.5 | G21: 500 | H21: 3000 | I21: 1642.56
A22: 52.98 | D22: 0 | E22: Axis 7503 | F22: 52.98
A23: 1024.57 | D23: 0 | E23: HSBC 9006 | F23: 1024.57
A24: 83 | D24: 0 | E24: Paytm 4366 | F24: 83
A25: 9.28 | D25: 0 | E25: SBI 5825 | F25: 9.28
A26: 154.01 | D26: 0 | E26: Paytm Wallet | F26: 154.01
A27: 1000 | D27: 0 | E27: Phonepe Wallet | F27: 1000
A29: 44986 | F29: Balance | G29: Investment | H29: Investment | I29: Expense
D30: Pending | E30: 128596.81 | G30: Paid | H30: Paid | I30: Paid
A31: Fixed Factor | B31: 1000 | F31: Due Date | G31: 45004 | H31: 45007 | I31: 44928
A32: 4283.83 | B32: 18000 | D32: 0 | E32: 44986 | F32: 30734.83 | I32: Axis 2009
A33: Remaining | B33: Fixed Balance | D33: Savings | E33: 45032 | F33: Balance | G33: Mutual Funds | H33: Mutual Funds | I33: CC Bill
A34: 169.15 | B34: 3000 | D34: 0 | E34: ICICI 3945 | F34: 3213.15
A35: 561.48 | B35: 3000 | D35: 0 | E35: Axis 0370 | F35: 11968.48 | G35: 500 | H35: 3000 | I35: 0
A36: 72.91 | B36: 3000 | D36: 0 | E36: Axis 7503 | F36: 3072.91
A37: 1109.75 | B37: 3000 | D37: 0 | E37: HSBC 9006 | F37: 4109.75
A38: 100 | B38: 3000 | D38: 0 | E38: Paytm 4366 | F38: 3100
A39: 17.28 | B39: 3000 | D39: 0 | E39: SBI 5825 | F39: 3017.28
A40: 963.83 | B40: 0 | D40: 0 | E40: Paytm Wallet | F40: 963.83
A41: 1108.8 | B41: 0 | D41: 0 | E41: Phonepe Wallet | F41: 1108.8
A42: 180.63 | B42: 0 | D42: 0 | E42: Splitwise | F42: 180.63
A44: 45017 | F44: Balance | G44: Expense | H44: Expense | I44: Expense
D45: Pending | E45: =Projections!C14 -> 116633.17 | G45: Paid | H45: Paid | I45: Paid
A46: Fixed Factor | B46: 1000 | E46: 820 | F46: Due Date | G46: 44936 | H46: 45015
A47: =#REF!-sum(D47)-B47 -> #REF! | B47: =sum(B49:B57) -> 24000 | D47: =sum(D49:D57) -> 0 | E47: =if(today()>#REF!,0,E46*(#REF!-#REF!+1)) -> #REF! | F47: =sum(F49:F57) -> 33134.91 | G47: ICICI 7018 | H47: ICICI 3002 | I47: Miyapur
A48: Remaining | B48: Fixed Balance | D48: Savings | E48: =today() -> 45969 | F48: Balance | G48: CC Bill | H48: CC Bill | I48: Maintenance
A49: =#REF!-sum(D49)-B49 -> #REF! | B49: =B34+B46 -> 4000 | D49: =sumifs($F49:$L49,$F$44:$L$44,D$19,$F$45:$L$45,"Pending") -> 0 | E49: ICICI 3945 | F49: 4100.15 | G49: 12637.63 | H49: 1494.51
A50: =#REF!-sum(D50)-B50 -> #REF! | B50: =B35+B46 -> 4000 | D50: =sumifs($F50:$L50,$F$44:$L$44,D$19,$F$45:$L$45,"Pending") -> 0 | E50: Axis 0370 | F50: =4100.48 -> 4100.48
A51: =#REF!-sum(D51)-B51 -> #REF! | B51: =B36+B46 -> 4000 | D51: =sumifs($F51:$L51,$F$44:$L$44,D$19,$F$45:$L$45,"Pending") -> 0 | E51: Axis 7503 | F51: 4096.48
A52: =#REF!-sum(D52)-B52 -> #REF! | B52: =B37+B46 -> 4000 | D52: =sumifs($F52:$L52,$F$44:$L$44,D$19,$F$45:$L$45,"Pending") -> 0 | E52: HSBC 9006 | F52: 11366.57
A53: =#REF!-sum(D53)-B53 -> #REF! | B53: =B38+B46 -> 4000 | D53: =sumifs($F53:$L53,$F$44:$L$44,D$19,$F$45:$L$45,"Pending") -> 0 | E53: Paytm 4366 | F53: 3965.15 | I53: 800
A54: =#REF!-sum(D54)-B54 -> #REF! | B54: =B39+B46 -> 4000 | D54: =sumifs($F54:$L54,$F$44:$L$44,D$19,$F$45:$L$45,"Pending") -> 0 | E54: SBI 5825 | F54: 4100.28
A55: =#REF!-sum(D55)-B55 -> #REF! | B55: 0 | D55: =sumifs($F55:$L55,$F$44:$L$44,D$19,$F$45:$L$45,"Pending") -> 0 | E55: Paytm Wallet | F55: 21.8
A56: =#REF!-sum(D56)-B56 -> #REF! | B56: 0 | D56: =sumifs($F56:$L56,$F$44:$L$44,D$19,$F$45:$L$45,"Pending") -> 0 | E56: Phonepe Wallet | F56: 1384
A57: =#REF!-sum(D57)-B57 -> #REF! | B57: 0 | D57: =sumifs($F57:$L57,$F$44:$L$44,D$19,$F$45:$L$45,"Pending") -> 0 | E57: Splitwise | F57: 0
A59: 45047 | F59: Balance | G59: Expense | H59: Expense | I59: Expense
D60: Pending | E60: =Projections!D14 -> 154155.89 | G60: Paid | H60: Paid | I60: Paid
A61: Fixed Factor | B61: 1000 | E61: 820 | F61: Due Date | G61: 44936 | H61: 44925
A62: =#REF!-sum(D62)-B62 -> #REF! | B62: =sum(B64:B73) -> 30000 | D62: =sum(D64:D73) -> 0 | E62: =if(today()>#REF!,0,E61*(#REF!-#REF!+1)) -> #REF! | F62: =sum(F64:F73) -> 27146.53 | G62: ICICI 7018 | H62: ICICI 3002 | I62: Miyapur
A63: Remaining | B63: Fixed Balance | D63: Savings | E63: =today() -> 45969 | F63: Balance | G63: CC Bill | H63: CC Bill | I63: Maintenance
A64: =#REF!-sum(D64)-B64 -> #REF! | B64: =B49+B61 -> 5000 | D64: =sumifs($F64:$M64,$F59:$M59,D63,$F60:$M60,"Pending") -> 0 | E64: ICICI 3945 | F64: 995.77 | G64: 818 | H64: 8900.76
A65: =#REF!-sum(D65)-B65 -> #REF! | B65: =B50+B61 -> 5000 | D65: =sumifs($F65:$M65,$F59:$M59,D63,$F60:$M60,"Pending") -> 0 | E65: Axis 0370 | F65: =6545.48-173-500-272 -> 5600.48
A66: =#REF!-sum(D66)-B66 -> #REF! | B66: =B51+B61 -> 5000 | D66: =sumifs($F66:$M66,$F59:$M59,D63,$F60:$M60,"Pending") -> 0 | E66: Axis 7503 | F66: 5470.48
A67: =#REF!-sum(D67)-B67 -> #REF! | B67: =B52+B61 -> 5000 | D67: =sumifs($F67:$M67,$F59:$M59,D63,$F60:$M60,"Pending") -> 0 | E67: HSBC 9006 | F67: 3387.5
A68: =#REF!-sum(D68)-B68 -> #REF! | B68: =B53+B61 -> 5000 | D68: =sumifs($F68:$M68,$F59:$M59,D63,$F60:$M60,"Pending") -> 0 | E68: Paytm 4366 | F68: 3641.15 | I68: 800
A69: =#REF!-sum(D69)-B69 -> #REF! | B69: =B54+B61 -> 5000 | D69: =sumifs($F69:$M69,$F59:$M59,D63,$F60:$M60,"Pending") -> 0 | E69: SBI 5825 | F69: 5600.28
A70: =#REF!-sum(D70)-B70 -> #REF! | B70: 0 | D70: =sumifs($F70:$M70,$F59:$M59,D63,$F60:$M60,"Pending") -> 0 | E70: Paytm Wallet | F70: 1064.47
A71: =#REF!-sum(D71)-B71 -> #REF! | B71: 0 | D71: =sumifs($F71:$M71,$F59:$M59,D63,$F60:$M60,"Pending") -> 0 | E71: Phonepe Wallet | F71: 618
A72: =#REF!-sum(D72)-B72 -> #REF! | B72: 0 | D72: =sumifs($F72:$M72,$F59:$M59,D63,$F60:$M60,"Pending") -> 0 | E72: Splitwise | F72: 208.4
A73: =#REF!-sum(D73)-B73 -> #REF! | B73: 0 | D73: =sumifs($F73:$M73,$F59:$M59,D63,$F60:$M60,"Pending") -> 0 | E73: Cash | F73: 560
A75: 45078 | E75: =Projections!E14 -> 160132 | F75: Balance | G75: Expense | H75: Expense | I75: Expense
D76: Pending | E76: 1000 | G76: Paid | H76: Paid | I76: Paid
A77: Fixed Factor | B77: 0 | E77: =if(today()>#REF!,0,E76*(#REF!-#REF!+1)) -> #REF! | F77: Due Date | G77: 11th | H77: 30th
A78: =#REF!-sum(D78)-B78 -> #REF! | B78: =sum(B80:B88) -> 0 | D78: =sum(D80:D88) -> 0 | F78: =sum(F80:F88) -> 2509.93 | G78: ICICI 7018 | H78: ICICI 3002 | I78: Miyapur
A79: Remaining | B79: Fixed Balance | D79: Savings | E79: =today() -> 45969 | F79: Balance | G79: CC Bill | H79: CC Bill | I79: Maintenance
A80: =#REF!-sum(D80)-B80 -> #REF! | B80: =B77 -> 0 | D80: =sumifs($F80:$M80,$F75:$M75,D79,$F76:$M76,"Pending") -> 0 | E80: ICICI 3945 | F80: 16.18 | G80: 11028.49 | H80: 7820.98
A81: =#REF!-sum(D81)-B81 -> #REF! | B81: =B77 -> 0 | D81: =sumifs($F81:$M81,$F75:$M75,D79,$F76:$M76,"Pending") -> 0 | E81: Axis 0370 | F81: 100.91
A82: =#REF!-sum(D82)-B82 -> #REF! | B82: =B77 -> 0 | D82: =sumifs($F82:$M82,$F75:$M75,D79,$F76:$M76,"Pending") -> 0 | E82: Axis 7503 | F82: 98.48
A83: =#REF!-sum(D83)-B83 -> #REF! | B83: =B77 -> 0 | D83: =sumifs($F83:$M83,$F75:$M75,D79,$F76:$M76,"Pending") -> 0 | E83: HSBC 9006 | F83: 593.92
A84: =#REF!-sum(D84)-B84 -> #REF! | B84: =B77 -> 0 | D84: =sumifs($F84:$M84,$F75:$M75,D79,$F76:$M76,"Pending") -> 0 | E84: Paytm 4366 | F84: 627.54 | I84: 800
A85: =#REF!-sum(D85)-B85 -> #REF! | B85: =B77 -> 0 | D85: =sumifs($F85:$M85,$F75:$M75,D79,$F76:$M76,"Pending") -> 0 | E85: SBI 5825 | F85: 126.28
A86: =#REF!-sum(D86)-B86 -> #REF! | B86: 0 | D86: =sumifs($F86:$M86,$F75:$M75,D79,$F76:$M76,"Pending") -> 0 | E86: Paytm Wallet | F86: 12
A87: =#REF!-sum(D87)-B87 -> #REF! | B87: 0 | D87: =sumifs($F87:$M87,$F75:$M75,D79,$F76:$M76,"Pending") -> 0 | E87: Phonepe Wallet | F87: 232
A88: =#REF!-sum(D88)-B88 -> #REF! | B88: 0 | D88: =sumifs($F88:$M88,$F75:$M75,D79,$F76:$M76,"Pending") -> 0 | E88: Splitwise | F88: 702.62
A90: 45108 | F90: Balance | G90: Expense | H90: Expense | I90: Expense
B91: =Projections!F8 -> 129632 | D91: Pending | E91: =Projections!F14 -> 130132 | G91: Paid | H91: Paid | I91: Paid
A92: Fixed Factor | B92: =round(B91/12/6,0) -> 1800 | E92: 1000 | F92: Due Date | G92: 45108 | H92: 44925
A93: =#REF!-sum(D93)-B93 -> #REF! | B93: =sum(B95:B103) -> 10800 | D93: =sum(D95:D103) -> 0 | E93: =if(today()>#REF!,0,E92*(#REF!-#REF!+1)) -> #REF! | F93: =sum(F95:F103) -> 25729.8 | G93: ICICI 7018 | H93: ICICI 3002 | I93: Miyapur
A94: Remaining | B94: Fixed Balance | D94: Savings | E94: =today() -> 45969 | F94: Balance | G94: CC Bill | H94: CC Bill | I94: Maintenance
A95: =#REF!-sum(D95)-B95 -> #REF! | B95: =B80+B92 -> 1800 | D95: =sumifs($F95:$M95,$F90:$M90,D94,$F91:$M91,"Pending") -> 0 | E95: ICICI 3945 | F95: 5209.05 | G95: =19994.1 -> 19994.1 | H95: 8520
A96: =#REF!-sum(D96)-B96 -> #REF! | B96: =B81+B92 -> 1800 | D96: =sumifs($F96:$M96,$F90:$M90,D94,$F91:$M91,"Pending") -> 0 | E96: Axis 0370 | F96: =3500.24-126 -> 3374.24
A97: =#REF!-sum(D97)-B97 -> #REF! | B97: =B82+B92 -> 1800 | D97: =sumifs($F97:$M97,$F90:$M90,D94,$F91:$M91,"Pending") -> 0 | E97: Axis 7503 | F97: =3000.54+249+251 -> 3500.54
A98: =#REF!-sum(D98)-B98 -> #REF! | B98: =B83+B92 -> 1800 | D98: =sumifs($F98:$M98,$F90:$M90,D94,$F91:$M91,"Pending") -> 0 | E98: HSBC 9006 | F98: 2356.47
A99: =#REF!-sum(D99)-B99 -> #REF! | B99: =B84+B92 -> 1800 | D99: =sumifs($F99:$M99,$F90:$M90,D94,$F91:$M91,"Pending") -> 0 | E99: Paytm 4366 | F99: 4194.5 | I99: 800
A100: =#REF!-sum(D100)-B100 -> #REF! | B100: =B85+B92 -> 1800 | D100: =sumifs($F100:$M100,$F90:$M90,D94,$F91:$M91,"Pending") -> 0 | E100: SBI 5825 | F100: =3000+500 -> 3500
A101: =#REF!-sum(D101)-B101 -> #REF! | B101: 0 | D101: =sumifs($F101:$M101,$F90:$M90,D94,$F91:$M91,"Pending") -> 0 | E101: Paytm Wallet | F101: 2251
A102: =#REF!-sum(D102)-B102 -> #REF! | B102: 0 | D102: =sumifs($F102:$M102,$F90:$M90,D94,$F91:$M91,"Pending") -> 0 | E102: Phonepe Wallet | F102: 1344
A103: =#REF!-sum(D103)-B103 -> #REF! | B103: 0 | D103: =sumifs($F103:$M103,$F90:$M90,D94,$F91:$M91,"Pending") -> 0 | E103: Splitwise | F103: 0
A105: =Projections!G1 -> 45139 | F105: Balance | G105: Expense | H105: Expense | I105: Expense
B106: =Projections!G8 -> 129632 | D106: Pending | E106: =Projections!G14 -> 141932 | G106: Paid | H106: Paid | I106: Paid
A107: Fixed Factor | B107: 0 | E107: =round(B106*20%*12/365,0) -> 852 | F107: Due Date | G107: 45151 | H107: 45151 | I107: PhonePe
...

Sheet Trading
K3: Partnership Start | M3: 45812
K4: Ratio | L4: =L$6/$G$6% -> 92 | M4: =M$6/$G$6% -> 8
L5: Aditya | M5: Laxmi Narayana
G6: =sum(L6:AH6) -> 250000 | K6: Investment | L6: 230000 | M6: 20000
K7: P&L Balance | L7: =round(L6+B9,0) -> 242012 | M7: =round(M6+C9,0) -> 20631
B9: =sum(B11:B1003) -> 12011.843 | C9: =sum(C11:C1003) -> 631.36728
A10: Commission | B10: =L10 -> Aditya | C10: =M10 -> Laxmi Narayana | D10: Date | E10: Trade | F10: Investment | G10: Traded | H10: P&L | I10: Charges | J10: Brokerage | K10: Net Realised Profit | L10: =L5 -> Aditya | M10: =M5 -> Laxmi Narayana
A11: =if(H11>0,M11*10%,0) -> 0 | B11: 3047.08 | C11: 0 | D11: 45811 | E11: Jindal Stainless Cochin Shipyard | H11: 3273.4 | I11: 146.32 | J11: 80 | K11: 3047.08 | L11: 3047.08 | M11: 0 | P11: 45811 | Q11: 4 | R11: 3273.4 | S11: 3047.08 | T11: 146.32
A12: 23.67312 | B12: 2746.0819 | C12: 213.05808 | D12: 45812 | E12: Inventurus Knowledge Solutions | F12: 238560 | G12: 47616.766 | H12: 3091.3 | I12: 92.16 | J12: 40 | K12: 2959.15 | L12: 2722.4088 | M12: 236.7312 | P12: 45812 | Q12: 2 | R12: 3091.3 | S12: 2959.15 | T12: 92.16
A13: 0 | B13: -584.9728 | C13: -50.8672 | D13: 45813 | E13: PB FinTech | F13: 187800 | G13: 37485.03 | H13: -521.6 | I13: 74.24 | J13: 40 | K13: -635.84 | L13: -584.9728 | M13: -50.8672 | P13: 45813 | Q13: 2 | R13: -521.6 | S13: -635.84 | T13: 74.24
A14: 63.46624 | B14: 7362.0838 | C14: 571.19616 | D14: 45814 | E14: Godrej Properties Macrotek Developers | H14: 8195 | I14: 181.72 | J14: 80 | K14: 7933.28 | L14: 7298.6176 | M14: 634.6624 | P14: 45814 | Q14: 4 | R14: 8195 | S14: 7933.28 | T14: 181.72
A15: 17.114 | B15: 1985.224 | C15: 154.026 | D15: 45817 | E15: Muthoot Finance | H15: 2276.4 | I15: 97.15 | J15: 40 | K15: 2139.25 | L15: 1968.11 | M15: 171.14 | P15: 45817 | Q15: 2 | R15: 2276.4 | S15: 2139.25 | T15: ₹ 97.15
A16: =if(H16>0,M16*10%,0) -> 6.7064 | B16: =L16+A16 -> 777.9424 | C16: =M16-A16 -> 60.3576 | D16: 45820 | H16: 1250.98 | K16: 838.3 | L16: =$K16*L$4/100 -> 771.236 | M16: =$K16*M$4/100 -> 67.064 | P16: 45820 | Q16: 6 | R16: 1250.98 | S16: 838.3 | T16: ₹ 292.68
A17: =if(H17>0,M17*10%,0) -> 25.36336 | B17: =L17+A17 -> 2942.1498 | C17: =M17-A17 -> 228.27024 | D17: 45832 | H17: 3691.37 | K17: 3170.42 | L17: =$K17*L$4/100 -> 2916.7864 | M17: =$K17*M$4/100 -> 253.6336 | P17: 45832 | Q17: 8 | R17: 3691.37 | S17: 3170.42 | T17: ₹ 360.95
A18: =if(H18>0,M18*10%,0) -> 0 | B18: =L18+A18 -> -6263.7464 | C18: =M18-A18 -> -544.6736 | D18: 45835 | H18: -6280.08 | K18: -6808.42 | L18: =$K18*L$4/100 -> -6263.7464 | M18: =$K18*M$4/100 -> -544.6736 | P18: 45835 | Q18: 8 | R18: -6280.08 | S18: -6808.42 | T18: ₹ 368.34
A19: =if(H19>0,M19*10%,0) -> 0 | B19: =L19+A19 -> 0 | C19: =M19-A19 -> 0 | K19: 0 | L19: =$K19*L$4/100 -> 0 | M19: =$K19*M$4/100 -> 0
A20: =if(H20>0,M20*10%,0) -> 0 | B20: =L20+A20 -> 0 | C20: =M20-A20 -> 0 | K20: 0 | L20: =$K20*L$4/100 -> 0 | M20: =$K20*M$4/100 -> 0
A21: =if(H21>0,M21*10%,0) -> 0 | B21: =L21+A21 -> 0 | C21: =M21-A21 -> 0 | K21: 0 | L21: =$K21*L$4/100 -> 0 | M21: =$K21*M$4/100 -> 0
A22: =if(H22>0,M22*10%,0) -> 0 | B22: =L22+A22 -> 0 | C22: =M22-A22 -> 0 | K22: 0 | L22: =$K22*L$4/100 -> 0 | M22: =$K22*M$4/100 -> 0
A23: =if(H23>0,M23*10%,0) -> 0 | B23: =L23+A23 -> 0 | C23: =M23-A23 -> 0 | K23: 0 | L23: =$K23*L$4/100 -> 0 | M23: =$K23*M$4/100 -> 0
A24: =if(H24>0,M24*10%,0) -> 0 | B24: =L24+A24 -> 0 | C24: =M24-A24 -> 0 | K24: 0 | L24: =$K24*L$4/100 -> 0 | M24: =$K24*M$4/100 -> 0
A25: =if(H25>0,M25*10%,0) -> 0 | B25: =L25+A25 -> 0 | C25: =M25-A25 -> 0 | K25: 0 | L25: =$K25*L$4/100 -> 0 | M25: =$K25*M$4/100 -> 0
A26: =if(H26>0,M26*10%,0) -> 0 | B26: =L26+A26 -> 0 | C26: =M26-A26 -> 0 | K26: 0 | L26: =$K26*L$4/100 -> 0 | M26: =$K26*M$4/100 -> 0
A27: =if(H27>0,M27*10%,0) -> 0 | B27: =L27+A27 -> 0 | C27: =M27-A27 -> 0 | K27: 0 | L27: =$K27*L$4/100 -> 0 | M27: =$K27*M$4/100 -> 0
A28: =if(H28>0,M28*10%,0) -> 0 | B28: =L28+A28 -> 0 | C28: =M28-A28 -> 0 | K28: 0 | L28: =$K28*L$4/100 -> 0 | M28: =$K28*M$4/100 -> 0
A29: =if(H29>0,M29*10%,0) -> 0 | B29: =L29+A29 -> 0 | C29: =M29-A29 -> 0 | K29: 0 | L29: =$K29*L$4/100 -> 0 | M29: =$K29*M$4/100 -> 0
A30: =if(H30>0,M30*10%,0) -> 0 | B30: =L30+A30 -> 0 | C30: =M30-A30 -> 0 | K30: 0 | L30: =$K30*L$4/100 -> 0 | M30: =$K30*M$4/100 -> 0
... A1003: =if(H1003>0,M1003*10%,0) -> 0 | B1003: =L1003+A1003 -> 0 | C1003: =M1003-A1003 -> 0 | K1003: 0 | L1003: =$K1003*L$4/100 -> 0 | M1003: =$K1003*M$4/100 -> 0

Sheet CC Outstanding
V3: Without Car | W3: =W6-W10 -> 67146 | Z3: =Z6-Z10 -> 1895446.1
B4: Credit Card Details | C4: 45809 | F4: =sum(F6:F9) -> 562037.76 | O4: =sum(O6:O1000) -> 16359
D5: Total Credit Limit | E5: Available Credit Limit | F5: Credit Card Outstanding | O5: MF | U5: =145649 -> 145649 | V5: Income
C6: ICICI 3002 | D6: 790000 | E6: 651214.46 | F6: =D6-E6 -> 138785.54 | O6: 6895 | U6: =sum(W6:AP6) -> 2912722 | V6: Loans | W6: =sum(W8:W1000) -> 79916 | X6: =sum(X8:X1000) -> 69000 | Z6: =sum(Z8:Z1000) -> 2763806
C7: ICICI 7018 ICICI 3003 ICICI 20010 | D7: 660000 | E7: 367662.93 | F7: =D7-E7 -> 292337.07 | O7: 6781 | AE7: 4003 | AF7: 3002 | AG7: 7018 | AH7: 7221
C8: ICICI 4003 | D8: 790000 | E8: 745719.62 | F8: =D8-E8 -> 44280.38 | O8: 33 | V8: Money View | W8: 9290 | Z8: =AA8*AD8 -> 399470 | AA8: 9290 | AB8: 48 | AC8: 5 | AD8: =AB8-AC8 -> 43
C9: AXIS 2009 AXIS 7221 | D9: 118000 | E9: 31365.23 | F9: =D9-E9 -> 86634.77 | O9: 1821 | V9: Bajaj | W9: 15577 | Z9: =AA9*AD9 -> 560772 | AA9: 15577 | AB9: 60 | AC9: 24 | AD9: =AB9-AC9 -> 36
O10: 829 | V10: Car | W10: 12770 | Z10: =AA10*AD10 -> 868360 | AA10: 12770 | AB10: =12*7 -> 84 | AC10: 16 | AD10: =AB10-AC10 -> 68
B11: Credit Card Details | C11: 45778 | F11: =sum(F13:F16) -> 606851.1 | L11: =sum(L13:L17) -> 842 | V11: ICICI CC | W11: 32319 | Z11: =sum(AE11:AH11) -> 659716.4 | AE11: =790000-714397.54 -> 75602.46 | AF11: =790000-668627.03 -> 121372.97 | AG11: =790660-327919.03 -> 462740.97
D12: Total Credit Limit | E12: Available Credit Limit | F12: Credit Card Outstanding | L12: Per Day | V12: Axis CC | W12: 6988 | Z12: =sum(AE12:AH12) -> 95487.65 | AH12: =118000-22512.35 -> 95487.65
C13: ICICI 3002 | D13: 790000 | E13: 636907.68 | F13: =D13-E13 -> 153092.32 | K13: Soujanya | L13: =floor(850*3/7,1) -> 364 | V13: Axis Personal Loan | W13: 2972 | Z13: =AA13*AD13 -> 180000 | AA13: 3000 | AB13: 60 | AC13: 0 | AD13: =AB13-AC13 -> 60
C14: ICICI 7018 ICICI 3003 ICICI 20010 | D14: 660000 | E14: 343967.47 | F14: =D14-E14 -> 316032.53 | K14: Hafiz | L14: =floor(670*5/7,1) -> 478
C15: ICICI 4003 | D15: 790000 | E15: 743257.35 | F15: =D15-E15 -> 46742.65 | V15: STR Residency | X15: 5000
C16: AXIS 2009 AXIS 7221 | D16: 118000 | E16: 27016.4 | F16: =D16-E16 -> 90983.6 | V16: Responsibilities | X16: 55000
V17: Utility | X17: 5000
V18: Savings | X18: 2000
V19: Investments | X19: 2000
V48: Add Income Transaction
V49: Add Expense Transaction
V50: Update Balance Transaction | W50: sometimes, expense transaction may be missed, so need update balance
V51: Set EMIs | W51: for credit card, loans etc.
V52: Update Credit Card Bills
V53: Reminder for interest payments

Sheet EMI Sheet
A1: Card | B1: Merchant Name | C1: Original Amount | D1: Tenure | E1: EMI Amt With Interest | F1: Pending EMI | G1: EMI Creation Date | H1: End Date | I1: Status Of EMI Transaction | J1: Balance | K1: Rank | L1: Total Loan | M1: EMI Interest | N1: Rank
A2: ICICI 7018 | B2: PLCC | C2: 260000 | D2: 24 | E2: 12605.29 | F2: 17 | G2: 45363 | H2: 46092 | I2: Active | J2: =F2*E2 -> 214289.93 | K2: =rank(J2,J$2:J$20) -> 1 | L2: =E2*D2 -> 302526.96 | M2: =(L2-J2)/D2 -> 3676.5429 | N2: =rank(M2,M$2:M$20) -> 1 | R2: 783 | S2: done
A3: ICICI 7018 | B3: Merchant EMI | C3: 118800 | D3: 24 | E3: 5477.63 | F3: 12 | G3: 13-06-2024 | H3: 13-05-2026 | I3: Active | J3: =F3*E3 -> 65731.56 | K3: =rank(J3,J$2:J$20) -> 2 | L3: =E3*D3 -> 131463.12 | M3: =(L3-J3)/D3 -> 2738.815 | N3: =rank(M3,M$2:M$20) -> 2 | R3: 792
A4: ICICI 3002 | B4: IND*AMAZON PGSI | C4: 86908 | D4: 24 | E4: 4254.87 | F4: 14 | G4: 45391 | H4: 46120 | I4: Active | J4: =F4*E4 -> 59568.18 | K4: =rank(J4,J$2:J$20) -> 3 | L4: =E4*D4 -> 102116.88 | M4: =(L4-J4)/D4 -> 1772.8625 | N4: =rank(M4,M$2:M$20) -> 3 | R4: 1547 | S4: done
A5: ICICI 4003 | B5: Merchant EMI | C5: 45499.42 | D5: 24 | E5: 2129.09 | F5: 21 | G5: 45780 | H5: 46509 | I5: Active | J5: =F5*E5 -> 44710.89 | K5: =rank(J5,J$2:J$20) -> 4 | L5: =E5*D5 -> 51098.16 | M5: =(L5-J5)/D5 -> 266.13625 | N5: =rank(M5,M$2:M$20) -> 7 | R5: 1682
A6: ICICI 3002 | B6: IND*AMAZON PGSI | C6: 40242.76 | D6: 9 | E6: 4774.58 | F6: 7 | G6: 30-04-2025 | H6: 30-12-2025 | I6: Active | J6: =F6*E6 -> 33422.06 | K6: =rank(J6,J$2:J$20) -> 5 | L6: =E6*D6 -> 42971.22 | M6: =(L6-J6)/D6 -> 1061.0178 | N6: =rank(M6,M$2:M$20) -> 4 | R6: 3474
A7: ICICI 7018 | B7: APPLE INDIA PRIVATE LI | C7: 22823 | D7: 6 | E7: 3983.19 | F7: 5 | G7: 45813 | H7: 45818 | I7: Active | J7: =F7*E7 -> 19915.95 | K7: =rank(J7,J$2:J$20) -> 6 | L7: =E7*D7 -> 23899.14 | M7: =(L7-J7)/D7 -> 663.865 | N7: =rank(M7,M$2:M$20) -> 5 | R7: 1742 | S7: done
A8: ICICI 3002 | B8: IND*AMAZON PGSI | C8: 20653.26 | D8: 24 | E8: 1011.15 | F8: 16 | G8: 29-10-2024 | H8: 29-09-2026 | I8: Active | J8: =F8*E8 -> 16178.4 | K8: =rank(J8,J$2:J$20) -> 7 | L8: =E8*D8 -> 24267.6 | M8: =(L8-J8)/D8 -> 337.05 | N8: =rank(M8,M$2:M$20) -> 6 | R8: 3221 | S8: done
A9: ICICI 3002 | B9: IND*AMAZON PGSI | C9: 13999 | D9: 24 | E9: 685.37 | F9: 15 | G9: 45574 | H9: 46303 | I9: Active | J9: =F9*E9 -> 10280.55 | K9: =rank(J9,J$2:J$20) -> 8 | L9: =E9*D9 -> 16448.88 | M9: =(L9-J9)/D9 -> 257.01375 | N9: =rank(M9,M$2:M$20) -> 8 | R9: 3179
A10: ICICI 3002 | B10: IND*AMAZON | C10: 9822 | D10: 24 | E10: 490.36 | F10: 18 | G10: 45455 | H10: 46184 | I10: Active | J10: =F10*E10 -> 8826.48 | K10: =rank(J10,J$2:J$20) -> 9 | L10: =E10*D10 -> 11768.64 | M10: =(L10-J10)/D10 -> 122.59 | N10: =rank(M10,M$2:M$20) -> 10
A11: ICICI 7018 | B11: BALAJI XTENSION | C11: 7880 | D11: 24 | E11: 393.4 | F11: 17 | G11: 45334 | H11: 46064 | I11: Active | J11: =F11*E11 -> 6687.8 | K11: =rank(J11,J$2:J$20) -> 11 | L11: =E11*D11 -> 9441.6 | M11: =(L11-J11)/D11 -> 114.74167 | N11: =rank(M11,M$2:M$20) -> 12
A12: ICICI 3002 | B12: IND*AMAZON PGSI | C12: 7299 | D12: 24 | E12: 357.35 | F12: 21 | G12: 18-03-2025 | H12: 18-02-2027 | I12: Active | J12: =F12*E12 -> 7504.35 | K12: =rank(J12,J$2:J$20) -> 10 | L12: =E12*D12 -> 8576.4 | M12: =(L12-J12)/D12 -> 44.66875 | N12: =rank(M12,M$2:M$20) -> 17
A13: ICICI 7018 | B13: CENTRO | C13: 6897.4 | D13: 24 | E13: 344.35 | F13: 7 | G13: 24-01-2024 | H13: 24-12-2025 | I13: Active | J13: =F13*E13 -> 2410.45 | K13: =rank(J13,J$2:J$20) -> 16 | L13: =E13*D13 -> 8264.4 | M13: =(L13-J13)/D13 -> 243.91458 | N13: =rank(M13,M$2:M$20) -> 9
A14: ICICI 3002 | B14: IBRAHIM BROS EXTENSION | C14: 5800 | D14: 24 | E14: 289.56 | F14: 18 | G14: 20-12-2024 | H14: 20-11-2026 | I14: Active | J14: =F14*E14 -> 5212.08 | K14: =rank(J14,J$2:J$20) -> 12 | L14: =E14*D14 -> 6949.44 | M14: =(L14-J14)/D14 -> 72.39 | N14: =rank(M14,M$2:M$20) -> 14
A15: ICICI 4003 | B15: UPI-776178736984-JS WINES | C15: 5010 | D15: 24 | E15: 250.12 | F15: 17 | G15: 45334 | H15: 46064 | I15: Active | J15: =F15*E15 -> 4252.04 | K15: =rank(J15,J$2:J$20) -> 13 | L15: =E15*D15 -> 6002.88 | M15: =(L15-J15)/D15 -> 72.951667 | N15: =rank(M15,M$2:M$20) -> 13
A16: ICICI 3002 | B16: IND*AMAZON PGSI | C16: 4008.96 | D16: 6 | E16: 699.67 | F16: 5 | G16: 45874 | H16: 45879 | I16: Active | J16: =F16*E16 -> 3498.35 | K16: =rank(J16,J$2:J$20) -> 14 | L16: =E16*D16 -> 4198.02 | M16: =(L16-J16)/D16 -> 116.61167 | N16: =rank(M16,M$2:M$20) -> 11
A17: ICICI 3002 | B17: MANISHA GULATI | C17: 3799 | D17: 24 | E17: 189.66 | F17: 18 | G17: 20-12-2024 | H17: 20-11-2026 | I17: Active | J17: =F17*E17 -> 3413.88 | K17: =rank(J17,J$2:J$20) -> 15 | L17: =E17*D17 -> 4551.84 | M17: =(L17-J17)/D17 -> 47.415 | N17: =rank(M17,M$2:M$20) -> 15
A18: ICICI 3002 | B18: IND*AMAZON PGSI | C18: 2877.75 | D18: 24 | E18: 140.89 | F18: 16 | G18: 15-10-2024 | H18: 15-09-2026 | I18: Active | J18: =F18*E18 -> 2254.24 | K18: =rank(J18,J$2:J$20) -> 18 | L18: =E18*D18 -> 3381.36 | M18: =(L18-J18)/D18 -> 46.963333 | N18: =rank(M18,M$2:M$20) -> 16
A19: ICICI 3002 | B19: VOYLLA 11 | C19: 2524 | D19: 24 | E19: 126.01 | F19: 18 | G19: 20-12-2024 | H19: 20-11-2026 | I19: Active | J19: =F19*E19 -> 2268.18 | K19: =rank(J19,J$2:J$20) -> 17 | L19: =E19*D19 -> 3024.24 | M19: =(L19-J19)/D19 -> 31.5025 | N19: =rank(M19,M$2:M$20) -> 19
A20: ICICI 3002 | B20: IND*AMAZON PGSI | C20: 1527 | D20: 6 | E20: 266.5 | F20: 5 | G20: 30-05-2025 | H20: 30-10-2025 | I20: Active | J20: =F20*E20 -> 1332.5 | K20: =rank(J20,J$2:J$20) -> 19 | L20: =E20*D20 -> 1599 | M20: =(L20-J20)/D20 -> 44.416667 | N20: =rank(M20,M$2:M$20) -> 18

Sheet Bills - CC EMIs
D1: =sum(J1:AH1) -> 0 | I1: Subject | J1: ICICI 7018 | K1: ICICI 7018 | L1: ICICI 7018 | M1: ICICI 3002 | N1: ICICI 4003 | O1: ICICI 3002 | P1: ICICI 7018 | Q1: ICICI 3002 | R1: ICICI 3002 | S1: ICICI 3002 | T1: ICICI 7018 | U1: ICICI 3002 | V1: ICICI 7018 | W1: ICICI 3002 | X1: ICICI 4003 | Y1: ICICI 3002 | Z1: ICICI 3002 | AA1: ICICI 3002 | AB1: ICICI 3002 | AC1: ICICI 3002
B2: 4173.59 | G2: SR 1015104860 | I2: Merchant Name | J2: PLCC | K2: Merchant EMI | L2: Personal loan | M2: IND*AMAZON PGSI | N2: Merchant EMI | O2: IND*AMAZON PGSI | P2: APPLE INDIA PRIVATE LI | Q2: IND*AMAZON PGSI | R2: IND*AMAZON PGSI | S2: IND*AMAZON | T2: BALAJI XTENSION | U2: IND*AMAZON PGSI | V2: CENTRO | W2: IBRAHIM BROS EXTENSION | X2: UPI-776178736984-JS WINES | Y2: IND*AMAZON PGSI | Z2: MANISHA GULATI | AA2: IND*AMAZON PGSI | AB2: VOYLLA 11 | AC2: IND*AMAZON PGSI
B3: 271.28 | I3: Original Amount | J3: 260000 | K3: 118800 | L3: 100000 | M3: 86908 | N3: 45499.42 | O3: 40242.76 | P3: 22823 | Q3: 20653.26 | R3: 13999 | S3: 9822 | T3: 7880 | U3: 7299 | V3: 6897.4 | W3: 5800 | X3: 5010 | Y3: 4008.96 | Z3: 3799 | AA3: 2877.75 | AB3: 2524 | AC3: 1527 | AD3: 2675.38 | AE3: 5280 | AF3: 2869.14 | AG3: 2825.61 | AH3: 2811.74 | AI3: 2719.11 | AJ3: 2681.27 | AK3: 2560.79 | AL3: 3093 | AM3: 3663.54 | AN3: 2991 | AO3: 2816.99 | AP3: 2323.72 | AQ3: 2470 | AR3: 2591.94 | AS3: 1505 | AT3: 12961 | AU3: 2274 | AV3: 4720 | AW3: 2710 | AX3: 2235.79 | AY3: 2300 | AZ3: 2508.5 | BA3: 2332 | BB3: 2804.57 | BC3: 2568.89 | BD3: 10496 | BE3: 7405 | BF3: 3815
B4: 145822.76 | I4: Tenure | J4: 24 | K4: 24 | L4: 24 | M4: 24 | N4: 24 | O4: 9 | P4: 6 | Q4: 24 | R4: 24 | S4: 24 | T4: 24 | U4: 24 | V4: 24 | W4: 24 | X4: 24 | Y4: 6 | Z4: 24 | AA4: 24 | AB4: 24 | AC4: 6 | AD4: 12 | AE4: 12 | AF4: 12 | AG4: 12 | AH4: 12 | AI4: 12 | AJ4: 12 | AK4: 12 | AL4: 12 | AM4: 12 | AN4: 12 | AO4: 12 | AP4: 12 | AQ4: 12 | AR4: 12 | AS4: 12 | AT4: 12 | AU4: 12 | AV4: 24 | AW4: 24 | AX4: 24 | AY4: 24 | AZ4: 24 | BA4: 24 | BB4: 24 | BC4: 24 | BD4: 24 | BE4: 24 | BF4: 24
I5: EMI Amt With Interest | J5: 12605.29 | K5: 5477.63 | L5: 5477.63 | M5: 4254.87 | N5: 2129.09 | O5: 4774.58 | P5: 3983.19 | Q5: 1011.15 | R5: 685.37 | S5: 490.36 | T5: 393.4 | U5: 357.35 | V5: 344.35 | W5: 289.56 | X5: 250.12 | Y5: 699.67 | Z5: 189.66 | AA5: 140.89 | AB5: 126.01 | AC5: 266.5 | AD5: 248.75 | AE5: 490.91 | AF5: 266.76 | AG5: 262.71 | AH5: 261.42 | AI5: 252.81 | AJ5: 249.29 | AK5: 238.09 | AL5: 287.57 | AM5: 340.62 | AN5: 278.09 | AO5: 261.91 | AP5: 216.37 | AQ5: 229.99 | AR5: 241.35 | AS5: 140.14 | AT5: 1206.85 | AU5: 211.74 | AV5: 235.64 | AW5: 135.29 | AX5: 111.62 | AY5: 114.83 | AZ5: 125.23 | BA5: 116.42 | BB5: 140.02 | BC5: 128.25 | BD5: 524 | BE5: 369.69 | BF5: 190.46
I6: Pending EMI | J6: 17 | K6: 12 | L6: 12 | M6: 14 | N6: 21 | O6: 7 | P6: 5 | Q6: 16 | R6: 15 | S6: 18 | T6: 17 | U6: 21 | V6: 7 | W6: 18 | X6: 17 | Y6: 5 | Z6: 18 | AA6: 16 | AB6: 18 | AC6: 5 | AD6: 4 | AE6: 4 | AF6: 4 | AG6: 4 | AH6: 4 | AI6: 4 | AJ6: 4 | AK6: 5 | AL6: 6 | AM6: 6 | AN6: 6 | AO6: 6 | AP6: 7 | AQ6: 7 | AR6: 7 | AS6: 7 | AT6: 7 | AU6: 7 | AV6: 20 | AW6: 20 | AX6: 20 | AY6: 21 | AZ6: 21 | BA6: 21 | BB6: 21 | BC6: 22 | BD6: 22 | BE6: 24 | BF6: 24
I7: 1st EMI | J7: 45363 | K7: 13-06-2024 | L7: 13-06-2024 | M7: 45391 | N7: 45780 | O7: 30-04-2025 | P7: 45813 | Q7: 29-10-2024 | R7: 45574 | S7: 45455 | T7: 45334 | U7: 18-03-2025 | V7: 24-01-2024 | W7: 20-12-2024 | X7: 45334 | Y7: 45874 | Z7: 20-12-2024 | AA7: 15-10-2024 | AB7: 20-12-2024 | AC7: 30-05-2025 | AD7: 45565 | AE7: 45565 | AF7: 45565 | AG7: 45565 | AH7: 45565 | AI7: 45565 | AJ7: 45565 | AK7: 45593 | AL7: 45629 | AM7: 45632 | AN7: 45632 | AO7: 45632 | AP7: 45647 | AQ7: 45647 | AR7: 45658 | AS7: 45670 | AT7: 45670 | AU7: 45677 | AV7: 45701 | AW7: 45708 | AX7: 45708 | AY7: 45718 | AZ7: 45718 | BA7: 45732 | BB7: 45732 | BC7: 45754 | BD7: 45754 | BE7: 45802 | BF7: 45802
B8: 45383 | I8: Last EMI | J8: 46092 | K8: 13-05-2026 | L8: 13-05-2026 | M8: 46120 | N8: 46509 | O8: 30-12-2025 | P8: 45818 | Q8: 29-09-2026 | R8: 46303 | S8: 46184 | T8: 46064 | U8: 18-02-2027 | V8: 24-12-2025 | W8: 20-11-2026 | X8: 46064 | Y8: 45879 | Z8: 20-11-2026 | AA8: 15-09-2026 | AB8: 20-11-2026 | AC8: 30-10-2025 | AD8: =edate(AD7,AD4) -> 45930 | AE8: =edate(AE7,AE4) -> 45930 | AF8: =edate(AF7,AF4) -> 45930 | AG8: =edate(AG7,AG4) -> 45930 | AH8: =edate(AH7,AH4) -> 45930 | AI8: =edate(AI7,AI4) -> 45930 | AJ8: =edate(AJ7,AJ4) -> 45930 | AK8: =edate(AK7,AK4) -> 45958 | ... BF8: =edate(BF7,BF4) -> 46532
I9: Status Of EMI Transaction | J9: Active | K9: Active | L9: Active | M9: Active | N9: Active | O9: Active | P9: Active | Q9: Active | R9: Active | S9: Active | T9: Active | U9: Active | V9: Active | W9: Active | X9: Active | Y9: Active | Z9: Active | AA9: Active | AB9: Active | AC9: Active
I10: Status Of EMI Transaction
I11: Monthly Interest
B12: 224954 | G12: Start of Today | H12: =DATE(YEAR(today()),MONTH(TODAY()),1) -> 45962 | I12: Remaining Amount
I13: Remaining EMIs
I14: Today
I15: Principal
I16: Interest
I17: GST 18%
E18: =sum(E20:E117) -> 60187.91 | F18: =sum(F20:F117) -> 372547.12 | G18: =sum(G20:G117) -> 96524.51 | H18: =sum(H20:H117) -> 1783.9 | I18: Total EMI
A19: Remaining Loan Amount | B19: Total EMIs | C19: CC EMIs | D19: =sumif(I20:I117,"Future",B20:B117) -> 498306 | E19: ICICI CC 4003 | F19: ICICI CC 7018 | G19: ICICI CC 3002 | H19: AXIS 7221 | I19: Card | J19: ICICI CC 7018 | K19: ICICI CC 7018 | L19: ICICI CC 7018 | M19: ICICI CC 3002 | N19: ICICI CC 4003 | O19: ICICI CC 3002 | P19: ICICI CC 7018 | Q19: ICICI CC 3002 | R19: ICICI CC 3002 | S19: ICICI CC 3002 | T19: ICICI CC 7018 | U19: ICICI CC 3002 | V19: ICICI CC 7018 | W19: ICICI CC 3002 | X19: ICICI CC 4003 | Y19: ICICI CC 3002 | Z19: ICICI CC 3002 | AA19: ICICI CC 3002 | AB19: ICICI CC 3002 | AC19: ICICI CC 3002 | AD19: AXIS 7221 | AE19: AXIS 7221 | AF19: AXIS 7221 | AG19: AXIS 7221 | AH19: AXIS 7221 | AI19: AXIS 7221 | AJ19: AXIS 7221 | AK19: AXIS 7221 | AL19: AXIS 7221 | AM19: AXIS 7221 | AN19: AXIS 7221 | AO19: AXIS 7221 | AP19: AXIS 7221 | AQ19: AXIS 7221 | AR19: AXIS 7221 | AS19: AXIS 7221 | AT19: AXIS 7221 | AU19: AXIS 7221 | AV19: AXIS 7221 | AW19: AXIS 7221 | AX19: AXIS 7221 | AY19: AXIS 7221 | AZ19: AXIS 7221 | BA19: AXIS 7221 | BB19: AXIS 7221 | BC19: AXIS 7221 | BD19: AXIS 7221 | BE19: AXIS 7221 | BF19: AXIS 7221
A20: =ceiling(sum(J20:BF117)-sum(J20:BF20),1) -> 989504 | B20: =ceiling(sum(J20:BF20),1) -> 0 | C20: =sum(E20:H20) -> 0 | D20: 44805 | E20: =sumif($J$19:BF19,E$19,$J20:BF20) -> 0 | F20: =sumif($J$19:BG19,F$19,$J20:BG20) -> 0 | G20: =sumif($J$19:BH19,G$19,$J20:BH20) -> 0 | H20: =sumif($J$19:BI19,H$19,$J20:BI20) -> 0 | I20: =if(D20=DATE(year(today()),month(today()),1),"Current",if(D20>DATE(year(today()),month(today()),1), "Future","Past")) -> Past | AE20: =if(and($D20>AE$7,$D20<AE$8),AE$5,0) -> 0 | AF20: =if(and($D20>AF$7,$D20<AF$8),AF$5,0) -> 0 | AG20: =if(and($D20>AG$7,$D20<AG$8),AG$5,0) -> 0 | AH20: =if(and($D20>AH$7,$D20<AH$8),AH$5,0) -> 0 | AI20: =if(and($D20>AI$7,$D20<AI$8),AI$5,0) -> 0 | AJ20: =if(and($D20>AJ$7,$D20<AJ$8),AJ$5,0) -> 0 | AK20: =if(and($D20>AK$7,$D20<AK$8),AK$5,0) -> 0 | AL20: =if(and($D20>AL$7,$D20<AL$8),AL$5,0) -> 0 | ... BF20: =if(and($D20>BF$7,$D20<BF$8),BF$5,0) -> 0
A21: =ceiling(sum(J21:BF118)-sum(J21:BF21),1) -> 989504 | B21: =ceiling(sum(J21:BF21),1) -> 0 | C21: =sum(E21:H21) -> 0 | D21: 44835 | E21: =sumif($J$19:BF20,E$19,$J21:BF21) -> 0 | F21: =sumif($J$19:BG20,F$19,$J21:BG21) -> 0 | G21: =sumif($J$19:BH20,G$19,$J21:BH21) -> 0 | H21: =sumif($J$19:BI20,H$19,$J21:BI21) -> 0 | I21: =if(D21=DATE(year(today()),month(today()),1),"Current",if(D21>DATE(year(today()),month(today()),1), "Future","Past")) -> Past | AE21: =if(and($D21>AE$7,$D21<AE$8),AE$5,0) -> 0 | AF21: =if(and($D21>AF$7,$D21<AF$8),AF$5,0) -> 0 | AG21: =if(and($D21>AG$7,$D21<AG$8),AG$5,0) -> 0 | AH21: =if(and($D21>AH$7,$D21<AH$8),AH$5,0) -> 0 | AI21: =if(and($D21>AI$7,$D21<AI$8),AI$5,0) -> 0 | AJ21: =if(and($D21>AJ$7,$D21<AJ$8),AJ$5,0) -> 0 | AK21: =if(and($D21>AK$7,$D21<AK$8),AK$5,0) -> 0 | AL21: =if(and($D21>AL$7,$D21<AL$8),AL$5,0) -> 0 | ... BF21: =if(and($D21>BF$7,$D21<BF$8),BF$5,0) -> 0
A22: =ceiling(sum(J22:BF119)-sum(J22:BF22),1) -> 989504 | B22: =ceiling(sum(J22:BF22),1) -> 0 | C22: =sum(E22:H22) -> 0 | D22: 44866 | E22: =sumif($J$19:BF21,E$19,$J22:BF22) -> 0 | F22: =sumif($J$19:BG21,F$19,$J22:BG22) -> 0 | G22: =sumif($J$19:BH21,G$19,$J22:BH22) -> 0 | H22: =sumif($J$19:BI21,H$19,$J22:BI22) -> 0 | I22: =if(D22=DATE(year(today()),month(today()),1),"Current",if(D22>DATE(year(today()),month(today()),1), "Future","Past")) -> Past | AE22: =if(and($D22>AE$7,$D22<AE$8),AE$5,0) -> 0 | AF22: =if(and($D22>AF$7,$D22<AF$8),AF$5,0) -> 0 | AG22: =if(and($D22>AG$7,$D22<AG$8),AG$5,0) -> 0 | AH22: =if(and($D22>AH$7,$D22<AH$8),AH$5,0) -> 0 | AI22: =if(and($D22>AI$7,$D22<AI$8),AI$5,0) -> 0 | AJ22: =if(and($D22>AJ$7,$D22<AJ$8),AJ$5,0) -> 0 | AK22: =if(and($D22>AK$7,$D22<AK$8),AK$5,0) -> 0 | AL22: =if(and($D22>AL$7,$D22<AL$8),AL$5,0) -> 0 | ... BF22: =if(and($D22>BF$7,$D22<BF$8),BF$5,0) -> 0
A23: =ceiling(sum(J23:BF120)-sum(J23:BF23),1) -> 989504 | B23: =ceiling(sum(J23:BF23),1) -> 0 | C23: =sum(E23:H23) -> 0 | D23: 44896 | E23: =sumif($J$19:BF22,E$19,$J23:BF23) -> 0 | F23: =sumif($J$19:BG22,F$19,$J23:BG23) -> 0 | G23: =sumif($J$19:BH22,G$19,$J23:BH23) -> 0 | H23: =sumif($J$19:BI22,H$19,$J23:BI23) -> 0 | I23: =if(D23=DATE(year(today()),month(today()),1),"Current",if(D23>DATE(year(today()),month(today()),1), "Future","Past")) -> Past | AE23: =if(and($D23>AE$7,$D23<AE$8),AE$5,0) -> 0 | AF23: =if(and($D23>AF$7,$D23<AF$8),AF$5,0) -> 0 | AG23: =if(and($D23>AG$7,$D23<AG$8),AG$5,0) -> 0 | AH23: =if(and($D23>AH$7,$D23<AH$8),AH$5,0) -> 0 | AI23: =if(and($D23>AI$7,$D23<AI$8),AI$5,0) -> 0 | AJ23: =if(and($D23>AJ$7,$D23<AJ$8),AJ$5,0) -> 0 | AK23: =if(and($D23>AK$7,$D23<AK$8),AK$5,0) -> 0 | AL23: =if(and($D23>AL$7,$D23<AL$8),AL$5,0) -> 0 | ... BF23: =if(and($D23>BF$7,$D23<BF$8),BF$5,0) -> 0
A24: =ceiling(sum(J24:BF121)-sum(J24:BF24),1) -> 989504 | B24: =ceiling(sum(J24:BF24),1) -> 0 | C24: =sum(E24:H24) -> 0 | D24: 44927 | E24: =sumif($J$19:BF23,E$19,$J24:BF24) -> 0 | F24: =sumif($J$19:BG23,F$19,$J24:BG24) -> 0 | G24: =sumif($J$19:BH23,G$19,$J24:BH24) -> 0 | H24: =sumif($J$19:BI23,H$19,$J24:BI24) -> 0 | I24: =if(D24=DATE(year(today()),month(today()),1),"Current",if(D24>DATE(year(today()),month(today()),1), "Future","Past")) -> Past | AE24: =if(and($D24>AE$7,$D24<AE$8),AE$5,0) -> 0 | AF24: =if(and($D24>AF$7,$D24<AF$8),AF$5,0) -> 0 | AG24: =if(and($D24>AG$7,$D24<AG$8),AG$5,0) -> 0 | AH24: =if(and($D24>AH$7,$D24<AH$8),AH$5,0) -> 0 | AI24: =if(and($D24>AI$7,$D24<AI$8),AI$5,0) -> 0 | AJ24: =if(and($D24>AJ$7,$D24<AJ$8),AJ$5,0) -> 0 | AK24: =if(and($D24>AK$7,$D24<AK$8),AK$5,0) -> 0 | AL24: =if(and($D24>AL$7,$D24<AL$8),AL$5,0) -> 0 | ... BF24: =if(and($D24>BF$7,$D24<BF$8),BF$5,0) -> 0
A25: =ceiling(sum(J25:BF122)-sum(J25:BF25),1) -> 989504 | B25: =ceiling(sum(J25:BF25),1) -> 0 | C25: =sum(E25:H25) -> 0 | D25: 44958 | E25: =sumif($J$19:BF24,E$19,$J25:BF25) -> 0 | F25: =sumif($J$19:BG24,F$19,$J25:BG25) -> 0 | G25: =sumif($J$19:BH24,G$19,$J25:BH25) -> 0 | H25: =sumif($J$19:BI24,H$19,$J25:BI25) -> 0 | I25: =if(D25=DATE(year(today()),month(today()),1),"Current",if(D25>DATE(year(today()),month(today()),1), "Future","Past")) -> Past | AE25: =if(and($D25>AE$7,$D25<AE$8),AE$5,0) -> 0 | AF25: =if(and($D25>AF$7,$D25<AF$8),AF$5,0) -> 0 | AG25: =if(and($D25>AG$7,$D25<AG$8),AG$5,0) -> 0 | AH25: =if(and($D25>AH$7,$D25<AH$8),AH$5,0) -> 0 | AI25: =if(and($D25>AI$7,$D25<AI$8),AI$5,0) -> 0 | AJ25: =if(and($D25>AJ$7,$D25<AJ$8),AJ$5,0) -> 0 | AK25: =if(and($D25>AK$7,$D25<AK$8),AK$5,0) -> 0 | AL25: =if(and($D25>AL$7,$D25<AL$8),AL$5,0) -> 0 | ... BF25: =if(and($D25>BF$7,$D25<BF$8),BF$5,0) -> 0
A26: =ceiling(sum(J26:BF123)-sum(J26:BF26),1) -> 989504 | B26: =ceiling(sum(J26:BF26),1) -> 0 | C26: =sum(E26:H26) -> 0 | D26: 44986 | E26: =sumif($J$19:BF25,E$19,$J26:BF26) -> 0 | F26: =sumif($J$19:BG25,F$19,$J26:BG26) -> 0 | G26: =sumif($J$19:BH25,G$19,$J26:BH26) -> 0 | H26: =sumif($J$19:BI25,H$19,$J26:BI26) -> 0 | I26: =if(D26=DATE(year(today()),month(today()),1),"Current",if(D26>DATE(year(today()),month(today()),1), "Future","Past")) -> Past | AE26: =if(and($D26>AE$7,$D26<AE$8),AE$5,0) -> 0 | AF26: =if(and($D26>AF$7,$D26<AF$8),AF$5,0) -> 0 | AG26: =if(and($D26>AG$7,$D26<AG$8),AG$5,0) -> 0 | AH26: =if(and($D26>AH$7,$D26<AH$8),AH$5,0) -> 0 | AI26: =if(and($D26>AI$7,$D26<AI$8),AI$5,0) -> 0 | AJ26: =if(and($D26>AJ$7,$D26<AJ$8),AJ$5,0) -> 0 | AK26: =if(and($D26>AK$7,$D26<AK$8),AK$5,0) -> 0 | AL26: =if(and($D26>AL$7,$D26<AL$8),AL$5,0) -> 0 | ... BF26: =if(and($D26>BF$7,$D26<BF$8),BF$5,0) -> 0
A27: =ceiling(sum(J27:BF124)-sum(J27:BF27),1) -> 989504 | B27: =ceiling(sum(J27:BF27),1) -> 0 | C27: =sum(E27:H27) -> 0 | D27: 45017 | E27: =sumif($J$19:BF26,E$19,$J27:BF27) -> 0 | F27: =sumif($J$19:BG26,F$19,$J27:BG27) -> 0 | G27: =sumif($J$19:BH26,G$19,$J27:BH27) -> 0 | H27: =sumif($J$19:BI26,H$19,$J27:BI27) -> 0 | I27: =if(D27=DATE(year(today()),month(today()),1),"Current",if(D27>DATE(year(today()),month(today()),1), "Future","Past")) -> Past | AE27: =if(and($D27>AE$7,$D27<AE$8),AE$5,0) -> 0 | AF27: =if(and($D27>AF$7,$D27<AF$8),AF$5,0) -> 0 | AG27: =if(and($D27>AG$7,$D27<AG$8),AG$5,0) -> 0 | AH27: =if(and($D27>AH$7,$D27<AH$8),AH$5,0) -> 0 | AI27: =if(and($D27>AI$7,$D27<AI$8),AI$5,0) -> 0 | AJ27: =if(and($D27>AJ$7,$D27<AJ$8),AJ$5,0) -> 0 | AK27: =if(and($D27>AK$7,$D27<AK$8),AK$5,0) -> 0 | AL27: =if(and($D27>AL$7,$D27<AL$8),AL$5,0) -> 0 | ... BF27: =if(and($D27>BF$7,$D27<BF$8),BF$5,0) -> 0
A28: =ceiling(sum(J28:BF125)-sum(J28:BF28),1) -> 989504 | B28: =ceiling(sum(J28:BF28),1) -> 0 | C28: =sum(E28:H28) -> 0 | D28: 45047 | E28: =sumif($J$19:BF27,E$19,$J28:BF28) -> 0 | F28: =sumif($J$19:BG27,F$19,$J28:BG28) -> 0 | G28: =sumif($J$19:BH27,G$19,$J28:BH28) -> 0 | H28: =sumif($J$19:BI27,H$19,$J28:BI28) -> 0 | I28: =if(D28=DATE(year(today()),month(today()),1),"Current",if(D28>DATE(year(today()),month(today()),1), "Future","Past")) -> Past | AE28: =if(and($D28>AE$7,$D28<AE$8),AE$5,0) -> 0 | AF28: =if(and($D28>AF$7,$D28<AF$8),AF$5,0) -> 0 | AG28: =if(and($D28>AG$7,$D28<AG$8),AG$5,0) -> 0 | AH28: =if(and($D28>AH$7,$D28<AH$8),AH$5,0) -> 0 | AI28: =if(and($D28>AI$7,$D28<AI$8),AI$5,0) -> 0 | AJ28: =if(and($D28>AJ$7,$D28<AJ$8),AJ$5,0) -> 0 | AK28: =if(and($D28>AK$7,$D28<AK$8),AK$5,0) -> 0 | AL28: =if(and($D28>AL$7,$D28<AL$8),AL$5,0) -> 0 | ... BF28: =if(and($D28>BF$7,$D28<BF$8),BF$5,0) -> 0
A29: =ceiling(sum(J29:BF126)-sum(J29:BF29),1) -> 989504 | B29: =ceiling(sum(J29:BF29),1) -> 0 | C29: =sum(E29:H29) -> 0 | D29: 45078 | E29: =sumif($J$19:BF28,E$19,$J29:BF29) -> 0 | F29: =sumif($J$19:BG28,F$19,$J29:BG29) -> 0 | G29: =sumif($J$19:BH28,G$19,$J29:BH29) -> 0 | H29: =sumif($J$19:BI28,H$19,$J29:BI29) -> 0 | I29: =if(D29=DATE(year(today()),month(today()),1),"Current",if(D29>DATE(year(today()),month(today()),1), "Future","Past")) -> Past | AE29: =if(and($D29>AE$7,$D29<AE$8),AE$5,0) -> 0 | AF29: =if(and($D29>AF$7,$D29<AF$8),AF$5,0) -> 0 | AG29: =if(and($D29>AG$7,$D29<AG$8),AG$5,0) -> 0 | AH29: =if(and($D29>AH$7,$D29<AH$8),AH$5,0) -> 0 | AI29: =if(and($D29>AI$7,$D29<AI$8),AI$5,0) -> 0 | AJ29: =if(and($D29>AJ$7,$D29<AJ$8),AJ$5,0) -> 0 | AK29: =if(and($D29>AK$7,$D29<AK$8),AK$5,0) -> 0 | AL29: =if(and($D29>AL$7,$D29<AL$8),AL$5,0) -> 0 | ... BF29: =if(and($D29>BF$7,$D29<BF$8),BF$5,0) -> 0
A30: =ceiling(sum(J30:BF127)-sum(J30:BF30),1) -> 989504 | B30: =ceiling(sum(J30:BF30),1) -> 0 | C30: =sum(E30:H30) -> 0 | D30: 45108 | E30: =sumif($J$19:BF29,E$19,$J30:BF30) -> 0 | F30: =sumif($J$19:BG29,F$19,$J30:BG30) -> 0 | G30: =sumif($J$19:BH29,G$19,$J30:BH30) -> 0 | H30: =sumif($J$19:BI29,H$19,$J30:BI30) -> 0 | I30: =if(D30=DATE(year(today()),month(today()),1),"Current",if(D30>DATE(year(today()),month(today()),1), "Future","Past")) -> Past | AE30: =if(and($D30>AE$7,$D30<AE$8),AE$5,0) -> 0 | AF30: =if(and($D30>AF$7,$D30<AF$8),AF$5,0) -> 0 | AG30: =if(and($D30>AG$7,$D30<AG$8),AG$5,0) -> 0 | AH30: =if(and($D30>AH$7,$D30<AH$8),AH$5,0) -> 0 | AI30: =if(and($D30>AI$7,$D30<AI$8),AI$5,0) -> 0 | AJ30: =if(and($D30>AJ$7,$D30<AJ$8),AJ$5,0) -> 0 | AK30: =if(and($D30>AK$7,$D30<AK$8),AK$5,0) -> 0 | AL30: =if(and($D30>AL$7,$D30<AL$8),AL$5,0) -> 0 | ... BF30: =if(and($D30>BF$7,$D30<BF$8),BF$5,0) -> 0
A31: =ceiling(sum(J31:BF128)-sum(J31:BF31),1) -> 989504 | B31: =ceiling(sum(J31:BF31),1) -> 0 | C31: =sum(E31:H31) -> 0 | D31: 45139 | E31: =sumif($J$19:BF30,E$19,$J31:BF31) -> 0 | F31: =sumif($J$19:BG30,F$19,$J31:BG31) -> 0 | G31: =sumif($J$19:BH30,G$19,$J31:BH31) -> 0 | H31: =sumif($J$19:BI30,H$19,$J31:BI31) -> 0 | I31: =if(D31=DATE(year(today()),month(today()),1),"Current",if(D31>DATE(year(today()),month(today()),1), "Future","Past")) -> Past | AE31: =if(and($D31>AE$7,$D31<AE$8),AE$5,0) -> 0 | AF31: =if(and($D31>AF$7,$D31<AF$8),AF$5,0) -> 0 | AG31: =if(and($D31>AG$7,$D31<AG$8),AG$5,0) -> 0 | AH31: =if(and($D31>AH$7,$D31<AH$8),AH$5,0) -> 0 | AI31: =if(and($D31>AI$7,$D31<AI$8),AI$5,0) -> 0 | AJ31: =if(and($D31>AJ$7,$D31<AJ$8),AJ$5,0) -> 0 | AK31: =if(and($D31>AK$7,$D31<AK$8),AK$5,0) -> 0 | AL31: =if(and($D31>AL$7,$D31<AL$8),AL$5,0) -> 0 | ... BF31: =if(and($D31>BF$7,$D31<BF$8),BF$5,0) -> 0
... A36: =ceiling(sum(J36:BF133)-sum(J36:BF36),1) -> 989504 | B36: =ceiling(sum(J36:BF36),1) -> 0 | C36: =sum(E36:H36) -> 0 | D36: 45292 | E36: =sumif($J$19:BF35,E$19,$J36:BF36) -> 0 | F36: =sumif($J$19:BG35,F$19,$J36:BG36) -> 0 | G36: =sumif($J$19:BH35,G$19,$J36:BH36) -> 0 | H36: =sumif($J$19:BI35,H$19,$J36:BI36) -> 0 | I36: =if(D36=DATE(year(today()),month(today()),1),"Current",if(D36>DATE(year(today()),month(today()),1), "Future","Past")) -> Past | AE36: =if(and($D36>AE$7,$D36<AE$8),AE$5,0) -> 0 | AF36: =if(and($D36>AF$7,$D36<AF$8),AF$5,0) -> 0 | AG36: =if(and($D36>AG$7,$D36<AG$8),AG$5,0) -> 0 | AH36: =if(and($D36>AH$7,$D36<AH$8),AH$5,0) -> 0 | AI36: =if(and($D36>AI$7,$D36<AI$8),AI$5,0) -> 0 | AJ36: =if(and($D36>AJ$7,$D36<AJ$8),AJ$5,0) -> 0 | AK36: =if(and($D36>AK$7,$D36<AK$8),AK$5,0) -> 0 | AL36: =if(and($D36>AL$7,$D36<AL$8),AL$5,0) -> 0 | ... BF36: =if(and($D36>BF$7,$D36<BF$8),BF$5,0) -> 0
A37: =ceiling(sum(J37:BF134)-sum(J37:BF37),1) -> 989159 | B37: =ceiling(sum(J37:BF37),1) -> 345 | C37: =sum(E37:H37) -> 344.35 | D37: 45323 | E37: =sumif($J$19:BF36,E$19,$J37:BF37) -> 0 | F37: =sumif($J$19:BG36,F$19,$J37:BG37) -> 344.35 | G37: =sumif($J$19:BH36,G$19,$J37:BH37) -> 0 | H37: =sumif($J$19:BI36,H$19,$J37:BI37) -> 0 | I37: =if(D37=DATE(year(today()),month(today()),1),"Current",if(D37>DATE(year(today()),month(today()),1), "Future","Past")) -> Past | V37: =V$5 -> 344.35 | AE37: =if(and($D37>AE$7,$D37<AE$8),AE$5,0) -> 0 | AF37: =if(and($D37>AF$7,$D37<AF$8),AF$5,0) -> 0 | AG37: =if(and($D37>AG$7,$D37<AG$8),AG$5,0) -> 0 | AH37: =if(and($D37>AH$7,$D37<AH$8),AH$5,0) -> 0 | AI37: =if(and($D37>AI$7,$D37<AI$8),AI$5,0) -> 0 | AJ37: =if(and($D37>AJ$7,$D37<AJ$8),AJ$5,0) -> 0 | AK37: =if(and($D37>AK$7,$D37<AK$8),AK$5,0) -> 0 | AL37: =if(and($D37>AL$7,$D37<AL$8),AL$5,0) -> 0 | ... BF37: =if(and($D37>BF$7,$D37<BF$8),BF$5,0) -> 0
A38: =ceiling(sum(J38:BF135)-sum(J38:BF38),1) -> 988815 | B38: =ceiling(sum(J38:BF38),1) -> 345 | C38: =sum(E38:H38) -> 344.35 | D38: 45352 | E38: =sumif($J$19:BF37,E$19,$J38:BF38) -> 0 | F38: =sumif($J$19:BG37,F$19,$J38:BG38) -> 344.35 | G38: =sumif($J$19:BH37,G$19,$J38:BH38) -> 0 | H38: =sumif($J$19:BI37,H$19,$J38:BI38) -> 0 | I38: =if(D38=DATE(year(today()),month(today()),1),"Current",if(D38>DATE(year(today()),month(today()),1), "Future","Past")) -> Past | V38: =V$5 -> 344.35 | AE38: =if(and($D38>AE$7,$D38<AE$8),AE$5,0) -> 0 | AF38: =if(and($D38>AF$7,$D38<AF$8),AF$5,0) -> 0 | AG38: =if(and($D38>AG$7,$D38<AG$8),AG$5,0) -> 0 | AH38: =if(and($D38>AH$7,$D38<AH$8),AH$5,0) -> 0 | AI38: =if(and($D38>AI$7,$D38<AI$8),AI$5,0) -> 0 | AJ38: =if(and($D38>AJ$7,$D38<AJ$8),AJ$5,0) -> 0 | AK38: =if(and($D38>AK$7,$D38<AK$8),AK$5,0) -> 0 | AL38: =if(and($D38>AL$7,$D38<AL$8),AL$5,0) -> 0 | ... BF38: =if(and($D38>BF$7,$D38<BF$8),BF$5,0) -> 0
A39: =ceiling(sum(J39:BF136)-sum(J39:BF39),1) -> 988470 | B39: =ceiling(sum(J39:BF39),1) -> 345 | C39: =sum(E39:H39) -> 344.35 | D39: 45383 | E39: =sumif($J$19:BF38,E$19,$J39:BF39) -> 0 | F39: =sumif($J$19:BG38,F$19,$J39:BG39) -> 344.35 | G39: =sumif($J$19:BH38,G$19,$J39:BH39) -> 0 | H39: =sumif($J$19:BI38,H$19,$J39:BI39) -> 0 | I39: =if(D39=DATE(year(today()),month(today()),1),"Current",if(D39>DATE(year(today()),month(today()),1), "Future","Past")) -> Past | V39: =V$5 -> 344.35 | AE39: =if(and($D39>AE$7,$D39<AE$8),AE$5,0) -> 0 | AF39: =if(and($D39>AF$7,$D39<AF$8),AF$5,0) -> 0 | AG39: =if(and($D39>AG$7,$D39<AG$8),AG$5,0) -> 0 | AH39: =if(and($D39>AH$7,$D39<AH$8),AH$5,0) -> 0 | AI39: =if(and($D39>AI$7,$D39<AI$8),AI$5,0) -> 0 | AJ39: =if(and($D39>AJ$7,$D39<AJ$8),AJ$5,0) -> 0 | AK39: =if(and($D39>AK$7,$D39<AK$8),AK$5,0) -> 0 | AL39: =if(and($D39>AL$7,$D39<AL$8),AL$5,0) -> 0 | ... BF39: =if(and($D39>BF$7,$D39<BF$8),BF$5,0) -> 0
A40: =ceiling(sum(J40:BF137)-sum(J40:BF40),1) -> 988126 | B40: =ceiling(sum(J40:BF40),1) -> 345 | C40: =sum(E40:H40) -> 344.35 | D40: 45413 | E40: =sumif($J$19:BF39,E$19,$J40:BF40) -> 0 | F40: =sumif($J$19:BG39,F$19,$J40:BG40) -> 344.35 | G40: =sumif($J$19:BH39,G$19,$J40:BH40) -> 0 | H40: =sumif($J$19:BI39,H$19,$J40:BI40) -> 0 | I40: =if(D40=DATE(year(today()),month(today()),1),"Current",if(D40>DATE(year(today()),month(today()),1), "Future","Past")) -> Past | V40: =V$5 -> 344.35 | AE40: =if(and($D40>AE$7,$D40<AE$8),AE$5,0) -> 0 | AF40: =if(and($D40>AF$7,$D40<AF$8),AF$5,0) -> 0 | AG40: =if(and($D40>AG$7,$D40<AG$8),AG$5,0) -> 0 | AH40: =if(and($D40>AH$7,$D40<AH$8),AH$5,0) -> 0 | AI40: =if(and($D40>AI$7,$D40<AI$8),AI$5,0) -> 0 | AJ40: =if(and($D40>AJ$7,$D40<AJ$8),AJ$5,0) -> 0 | AK40: =if(and($D40>AK$7,$D40<AK$8),AK$5,0) -> 0 | AL40: =if(and($D40>AL$7,$D40<AL$8),AL$5,0) -> 0 | ... BF40: =if(and($D40>BF$7,$D40<BF$8),BF$5,0) -> 0
A41: =ceiling(sum(J41:BF138)-sum(J41:BF41),1) -> 987782 | B41: =ceiling(sum(J41:BF41),1) -> 345 | C41: =sum(E41:H41) -> 344.35 | D41: 45444 | E41: =sumif($J$19:BF40,E$19,$J41:BF41) -> 0 | F41: =sumif($J$19:BG40,F$19,$J41:BG41) -> 344.35 | G41: =sumif($J$19:BH40,G$19,$J41:BH41) -> 0 | H41: =sumif($J$19:BI40,H$19,$J41:BI41) -> 0 | I41: =if(D41=DATE(year(today()),month(today()),1),"Current",if(D41>DATE(year(today()),month(today()),1), "Future","Past")) -> Past | V41: =V$5 -> 344.35 | AE41: =if(and($D41>AE$7,$D41<AE$8),AE$5,0) -> 0 | AF41: =if(and($D41>AF$7,$D41<AF$8),AF$5,0) -> 0 | AG41: =if(and($D41>AG$7,$D41<AG$8),AG$5,0) -> 0 | AH41: =if(and($D41>AH$7,$D41<AH$8),AH$5,0) -> 0 | AI41: =if(and($D41>AI$7,$D41<AI$8),AI$5,0) -> 0 | AJ41: =if(and($D41>AJ$7,$D41<AJ$8),AJ$5,0) -> 0 | AK41: =if(and($D41>AK$7,$D41<AK$8),AK$5,0) -> 0 | AL41: =if(and($D41>AL$7,$D41<AL$8),AL$5,0) -> 0 | ... BF41: =if(and($D41>BF$7,$D41<BF$8),BF$5,0) -> 0
A42: =ceiling(sum(J42:BF139)-sum(J42:BF42),1) -> 981960 | B42: =ceiling(sum(J42:BF42),1) -> 5822 | C42: =sum(E42:H42) -> 5821.98 | D42: 45474 | E42: =sumif($J$19:BF41,E$19,$J42:BF42) -> 0 | F42: =sumif($J$19:BG41,F$19,$J42:BG42) -> 5821.98 | G42: =sumif($J$19:BH41,G$19,$J42:BH42) -> 0 | H42: =sumif($J$19:BI41,H$19,$J42:BI42) -> 0 | I42: =if(D42=DATE(year(today()),month(today()),1),"Current",if(D42>DATE(year(today()),month(today()),1), "Future","Past")) -> Past | K42: =K$5 -> 5477.63 | V42: =V$5 -> 344.35 | AE42: =if(and($D42>AE$7,$D42<AE$8),AE$5,0) -> 0 | AF42: =if(and($D42>AF$7,$D42<AF$8),AF$5,0) -> 0 | AG42: =if(and($D42>AG$7,$D42<AG$8),AG$5,0) -> 0 | AH42: =if(and($D42>AH$7,$D42<AH$8),AH$5,0) -> 0 | AI42: =if(and($D42>AI$7,$D42<AI$8),AI$5,0) -> 0 | AJ42: =if(and($D42>AJ$7,$D42<AJ$8),AJ$5,0) -> 0 | AK42: =if(and($D42>AK$7,$D42<AK$8),AK$5,0) -> 0 | AL42: =if(and($D42>AL$7,$D42<AL$8),AL$5,0) -> 0 | ... BF42: =if(and($D42>BF$7,$D42<BF$8),BF$5,0) -> 0
A43: =ceiling(sum(J43:BF140)-sum(J43:BF43),1) -> 976138 | B43: =ceiling(sum(J43:BF43),1) -> 5822 | C43: =sum(E43:H43) -> 5821.98 | D43: 45505 | E43: =sumif($J$19:BF42,E$19,$J43:BF43) -> 0 | F43: =sumif($J$19:BG42,F$19,$J43:BG43) -> 5821.98 | G43: =sumif($J$19:BH42,G$19,$J43:BH43) -> 0 | H43: =sumif($J$19:BI42,H$19,$J43:BI43) -> 0 | I43: =if(D43=DATE(year(today()),month(today()),1),"Current",if(D43>DATE(year(today()),month(today()),1), "Future","Past")) -> Past | K43: =K$5 -> 5477.63 | V43: =V$5 -> 344.35 | AE43: =if(and($D43>AE$7,$D43<AE$8),AE$5,0) -> 0 | AF43: =if(and($D43>AF$7,$D43<AF$8),AF$5,0) -> 0 | AG43: =if(and($D43>AG$7,$D43<AG$8),AG$5,0) -> 0 | AH43: =if(and($D43>AH$7,$D43<AH$8),AH$5,0) -> 0 | AI43: =if(and($D43>AI$7,$D43<AI$8),AI$5,0) -> 0 | AJ43: =if(and($D43>AJ$7,$D43<AJ$8),AJ$5,0) -> 0 | AK43: =if(and($D43>AK$7,$D43<AK$8),AK$5,0) -> 0 | AL43: =if(and($D43>AL$7,$D43<AL$8),AL$5,0) -> 0 | ... BF43: =if(and($D43>BF$7,$D43<BF$8),BF$5,0) -> 0
A44: =ceiling(sum(J44:BF141)-sum(J44:BF44),1) -> 970316 | B44: =ceiling(sum(J44:BF44),1) -> 5822 | C44: =sum(E44:H44) -> 5821.98 | D44: 45536 | E44: =sumif($J$19:BF43,E$19,$J44:BF44) -> 0 | F44: =sumif($J$19:BG43,F$19,$J44:BG44) -> 5821.98 | G44: =sumif($J$19:BH43,G$19,$J44:BH44) -> 0 | H44: =sumif($J$19:BI43,H$19,$J44:BI44) -> 0 | I44: =if(D44=DATE(year(today()),month(today()),1),"Current",if(D44>DATE(year(today()),month(today()),1), "Future","Past")) -> Past | K44: =K$5 -> 5477.63 | V44: =V$5 -> 344.35 | AE44: =if(and($D44>AE$7,$D44<AE$8),AE$5,0) -> 0 | AF44: =if(and($D44>AF$7,$D44<AF$8),AF$5,0) -> 0 | AG44: =if(and($D44>AG$7,$D44<AG$8),AG$5,0) -> 0 | AH44: =if(and($D44>AH$7,$D44<AH$8),AH$5,0) -> 0 | AI44: =if(and($D44>AI$7,$D44<AI$8),AI$5,0) -> 0 | AJ44: =if(and($D44>AJ$7,$D44<AJ$8),AJ$5,0) -> 0 | AK44: =if(and($D44>AK$7,$D44<AK$8),AK$5,0) -> 0 | AL44: =if(and($D44>AL$7,$D44<AL$8),AL$5,0) -> 0 | ... BF44: =if(and($D44>BF$7,$D44<BF$8),BF$5,0) -> 0
A45: =ceiling(sum(J45:BF142)-sum(J45:BF45),1) -> 956759 | B45: =ceiling(sum(J45:BF45),1) -> 13558 | C45: =sum(E45:H45) -> 13557.27 | D45: 45566 | E45: =sumif($J$19:BF44,E$19,$J45:BF45) -> 0 | F45: =sumif($J$19:BG44,F$19,$J45:BG45) -> 5821.98 | G45: =sumif($J$19:BH44,G$19,$J45:BH45) -> 5951.39 | H45: =sumif($J$19:BI44,H$19,$J45:BI45) -> 1783.9 | I45: =if(D45=DATE(year(today()),month(today()),1),"Current",if(D45>DATE(year(today()),month(today()),1), "Future","Past")) -> Past | K45: =K$5 -> 5477.63 | M45: =M$5 -> 4254.87 | Q45: =Q$5 -> 1011.15 | R45: =R$5 -> 685.37 | V45: =V$5 -> 344.35 | AE45: =if(and($D45>AE$7,$D45<AE$8),AE$5,0) -> 490.91 | AF45: =if(and($D45>AF$7,$D45<AF$8),AF$5,0) -> 266.76 | AG45: =if(and($D45>AG$7,$D45<AG$8),AG$5,0) -> 262.71 | AH45: =if(and($D45>AH$7,$D45<AH$8),AH$5,0) -> 261.42 | AI45: =if(and($D45>AI$7,$D45<AI$8),AI$5,0) -> 252.81 | AJ45: =if(and($D45>AJ$7,$D45<AJ$8),AJ$5,0) -> 249.29 | AK45: =if(and($D45>AK$7,$D45<AK$8),AK$5,0) -> 0 | AL45: =if(and($D45>AL$7,$D45<AL$8),AL$5,0) -> 0 | ... BF45: =if(and($D45>BF$7,$D45<BF$8),BF$5,0) -> 0
A46: =ceiling(sum(J46:BF143)-sum(J46:BF46),1) -> 942822 | B46: =ceiling(sum(J46:BF46),1) -> 13937 | C46: =sum(E46:H46) -> 0 | D46: 45597 | E46: 0 | F46: 0 | G46: 0 | H46: 0 | I46: =if(D46=DATE(year(today()),month(today()),1),"Current",if(D46>DATE(year(today()),month(today()),1), "Future","Past")) -> Past | K46: =K$5 -> 5477.63 | M46: =M$5 -> 4254.87 | Q46: =Q$5 -> 1011.15 | R46: =R$5 -> 685.37 | V46: =V$5 -> 344.35 | AA46: =AA$5 -> 140.89 | AE46: =if(and($D46>AE$7,$D46<AE$8),AE$5,0) -> 490.91 | AF46: =if(and($D46>AF$7,$D46<AF$8),AF$5,0) -> 266.76 | AG46: =if(and($D46>AG$7,$D46<AG$8),AG$5,0) -> 262.71 | AH46: =if(and($D46>AH$7,$D46<AH$8),AH$5,0) -> 261.42 | AI46: =if(and($D46>AI$7,$D46<AI$8),AI$5,0) -> 252.81 | AJ46: =if(and($D46>AJ$7,$D46<AJ$8),AJ$5,0) -> 249.29 | AK46: =if(and($D46>AK$7,$D46<AK$8),AK$5,0) -> 238.09 | AL46: =if(and($D46>AL$7,$D46<AL$8),AL$5,0) -> 0 | ... BF46: =if(and($D46>BF$7,$D46<BF$8),BF$5,0) -> 0
A47: =ceiling(sum(J47:BF144)-sum(J47:BF47),1) -> 928886 | B47: =ceiling(sum(J47:BF47),1) -> 13937 | C47: =sum(E47:H47) -> 0 | D47: 45627 | E47: 0 | F47: 0 | G47: 0 | H47: 0 | I47: =if(D47=DATE(year(today()),month(today()),1),"Current",if(D47>DATE(year(today()),month(today()),1), "Future","Past")) -> Past | K47: =K$5 -> 5477.63 | M47: =M$5 -> 4254.87 | Q47: =Q$5 -> 1011.15 | R47: =R$5 -> 685.37 | V47: =V$5 -> 344.35 | AA47: =AA$5 -> 140.89 | AE47: =if(and($D47>AE$7,$D47<AE$8),AE$5,0) -> 490.91 | AF47: =if(and($D47>AF$7,$D47<AF$8),AF$5,0) -> 266.76 | AG47: =if(and($D47>AG$7,$D47<AG$8),AG$5,0) -> 262.71 | AH47: =if(and($D47>AH$7,$D47<AH$8),AH$5,0) -> 261.42 | AI47: =if(and($D47>AI$7,$D47<AI$8),AI$5,0) -> 252.81 | AJ47: =if(and($D47>AJ$7,$D47<AJ$8),AJ$5,0) -> 249.29 | AK47: =if(and($D47>AK$7,$D47<AK$8),AK$5,0) -> 238.09 | AL47: =if(and($D47>AL$7,$D47<AL$8),AL$5,0) -> 0 | ... BF47: =if(and($D47>BF$7,$D47<BF$8),BF$5,0) -> 0
A48: =ceiling(sum(J48:BF145)-sum(J48:BF48),1) -> 898991 | B48: =ceiling(sum(J48:BF48),1) -> 29896 | C48: =sum(E48:H48) -> 0 | D48: 45658 | E48: 0 | F48: 0 | G48: 0 | H48: 0 | I48: =if(D48=DATE(year(today()),month(today()),1),"Current",if(D48>DATE(year(today()),month(today()),1), "Future","Past")) -> Past | J48: =J$5 -> 12605.29 | K48: =K$5 -> 5477.63 | M48: =M$5 -> 4254.87 | Q48: =Q$5 -> 1011.15 | R48: =R$5 -> 685.37 | S48: =S$5 -> 490.36 | T48: =T$5 -> 393.4 | V48: =V$5 -> 344.35 | W48: =W$5 -> 289.56 | X48: =X$5 -> 250.12 | Z48: =Z$5 -> 189.66 | AA48: =AA$5 -> 140.89 | AB48: =AB$5 -> 126.01 | AE48: =if(and($D48>AE$7,$D48<AE$8),AE$5,0) -> 490.91 | AF48: =if(and($D48>AF$7,$D48<AF$8),AF$5,0) -> 266.76 | AG48: =if(and($D48>AG$7,$D48<AG$8),AG$5,0) -> 262.71 | AH48: =if(and($D48>AH$7,$D48<AH$8),AH$5,0) -> 261.42 | AI48: =if(and($D48>AI$7,$D48<AI$8),AI$5,0) -> 252.81 | AJ48: =if(and($D48>AJ$7,$D48<AJ$8),AJ$5,0) -> 249.29 | AK48: =if(and($D48>AK$7,$D48<AK$8),AK$5,0) -> 238.09 | AL48: =if(and($D48>AL$7,$D48<AL$8),AL$5,0) -> 287.57 | ... BF48: =if(and($D48>BF$7,$D48<BF$8),BF$5,0) -> 0
A49: =ceiling(sum(J49:BF146)-sum(J49:BF49),1) -> 867296 | B49: =ceiling(sum(J49:BF49),1) -> 31696 | C49: =sum(E49:H49) -> 0 | D49: 45689 | E49: 0 | F49: 0 | G49: 0 | H49: 0 | I49: =if(D49=DATE(year(today()),month(today()),1),"Current",if(D49>DATE(year(today()),month(today()),1), "Future","Past")) -> Past | J49: =J$5 -> 12605.29 | K49: =K$5 -> 5477.63 | M49: =M$5 -> 4254.87 | Q49: =Q$5 -> 1011.15 | R49: =R$5 -> 685.37 | S49: =S$5 -> 490.36 | T49: =T$5 -> 393.4 | V49: =V$5 -> 344.35 | W49: =W$5 -> 289.56 | X49: =X$5 -> 250.12 | Z49: =Z$5 -> 189.66 | AA49: =AA$5 -> 140.89 | AB49: =AB$5 -> 126.01 | AE49: =if(and($D49>AE$7,$D49<AE$8),AE$5,0) -> 490.91 | AF49: =if(and($D49>AF$7,$D49<AF$8),AF$5,0) -> 266.76 | AG49: =if(and($D49>AG$7,$D49<AG$8),AG$5,0) -> 262.71 | AH49: =if(and($D49>AH$7,$D49<AH$8),AH$5,0) -> 261.42 | AI49: =if(and($D49>AI$7,$D49<AI$8),AI$5,0) -> 252.81 | AJ49: =if(and($D49>AJ$7,$D49<AJ$8),AJ$5,0) -> 249.29 | AK49: =if(and($D49>AK$7,$D49<AK$8),AK$5,0) -> 238.09 | AL49: =if(and($D49>AL$7,$D49<AL$8),AL$5,0) -> 287.57 | ... BF49: =if(and($D49>BF$7,$D49<BF$8),BF$5,0) -> 0
A50: =ceiling(sum(J50:BF147)-sum(J50:BF50),1) -> 835118 | B50: =ceiling(sum(J50:BF50),1) -> 32178 | C50: =sum(E50:H50) -> 0 | D50: 45717 | E50: 0 | F50: 0 | G50: 0 | H50: 0 | I50: =if(D50=DATE(year(today()),month(today()),1),"Current",if(D50>DATE(year(today()),month(today()),1), "Future","Past")) -> Past | J50: =J$5 -> 12605.29 | K50: =K$5 -> 5477.63 | M50: =M$5 -> 4254.87 | Q50: =Q$5 -> 1011.15 | R50: =R$5 -> 685.37 | S50: =S$5 -> 490.36 | T50: =T$5 -> 393.4 | V50: =V$5 -> 344.35 | W50: =W$5 -> 289.56 | X50: =X$5 -> 250.12 | Z50: =Z$5 -> 189.66 | AA50: =AA$5 -> 140.89 | AB50: =AB$5 -> 126.01 | AE50: =if(and($D50>AE$7,$D50<AE$8),AE$5,0) -> 490.91 | AF50: =if(and($D50>AF$7,$D50<AF$8),AF$5,0) -> 266.76 | AG50: =if(and($D50>AG$7,$D50<AG$8),AG$5,0) -> 262.71 | AH50: =if(and($D50>AH$7,$D50<AH$8),AH$5,0) -> 261.42 | AI50: =if(and($D50>AI$7,$D50<AI$8),AI$5,0) -> 252.81 | AJ50: =if(and($D50>AJ$7,$D50<AJ$8),AJ$5,0) -> 249.29 | AK50: =if(and($D50>AK$7,$D50<AK$8),AK$5,0) -> 238.09 | AL50: =if(and($D50>AL$7,$D50<AL$8),AL$5,0) -> 287.57 | ... BF50: =if(and($D50>BF$7,$D50<BF$8),BF$5,0) -> 0
A51: =ceiling(sum(J51:BF148)-sum(J51:BF51),1) -> 799957 | B51: 0 | C51: =sum(E51:H51) -> 0 | D51: 45748 | E51: 0 | F51: 0 | G51: 0 | H51: 0 | I51: =if(D51=DATE(year(today()),month(today()),1),"Current",if(D51>DATE(year(today()),month(today()),1), "Future","Past")) -> Past | J51: =J$5 -> 12605.29 | K51: =K$5 -> 5477.63 | M51: =M$5 -> 4254.87 | N51: =N$5 -> 2129.09 | Q51: =Q$5 -> 1011.15 | R51: =R$5 -> 685.37 | S51: =S$5 -> 490.36 | T51: =T$5 -> 393.4 | U51: =U$5 -> 357.35 | V51: =V$5 -> 344.35 | W51: =W$5 -> 289.56 | X51: =X$5 -> 250.12 | Z51: =Z$5 -> 189.66 | AA51: =AA$5 -> 140.89 | AB51: =AB$5 -> 126.01 | AE51: =if(and($D51>AE$7,$D51<AE$8),AE$5,0) -> 490.91 | AF51: =if(and($D51>AF$7,$D51<AF$8),AF$5,0) -> 266.76 | AG51: =if(and($D51>AG$7,$D51<AG$8),AG$5,0) -> 262.71 | AH51: =if(and($D51>AH$7,$D51<AH$8),AH$5,0) -> 261.42 | AI51: =if(and($D51>AI$7,$D51<AI$8),AI$5,0) -> 252.81 | AJ51: =if(and($D51>AJ$7,$D51<AJ$8),AJ$5,0) -> 249.29 | AK51: =if(and($D51>AK$7,$D51<AK$8),AK$5,0) -> 238.09 | AL51: =if(and($D51>AL$7,$D51<AL$8),AL$5,0) -> 287.57 | ... BF51: =if(and($D51>BF$7,$D51<BF$8),BF$5,0) -> 0
A52: =ceiling(sum(J52:BF149)-sum(J52:BF52),1) -> 759369 | B52: =ceiling(sum(J52:BF52),1) -> 40588 | C52: =sum(E52:H52) -> 0 | D52: 45778 | E52: 0 | F52: 0 | G52: 0 | H52: 0 | I52: =if(D52=DATE(year(today()),month(today()),1),"Current",if(D52>DATE(year(today()),month(today()),1), "Future","Past")) -> Past | J52: =J$5 -> 12605.29 | K52: =K$5 -> 5477.63 | M52: =M$5 -> 4254.87 | N52: =N$5 -> 2129.09 | O52: =O$5 -> 4774.58 | Q52: =Q$5 -> 1011.15 | R52: =R$5 -> 685.37 | S52: =S$5 -> 490.36 | T52: =T$5 -> 393.4 | U52: =U$5 -> 357.35 | V52: =V$5 -> 344.35 | W52: =W$5 -> 289.56 | X52: =X$5 -> 250.12 | Z52: =Z$5 -> 189.66 | AA52: =AA$5 -> 140.89 | AB52: =AB$5 -> 126.01 | AE52: =if(and($D52>AE$7,$D52<AE$8),AE$5,0) -> 490.91 | AF52: =if(and($D52>AF$7,$D52<AF$8),AF$5,0) -> 266.76 | AG52: =if(and($D52>AG$7,$D52<AG$8),AG$5,0) -> 262.71 | AH52: =if(and($D52>AH$7,$D52<AH$8),AH$5,0) -> 261.42 | AI52: =if(and($D52>AI$7,$D52<AI$8),AI$5,0) -> 252.81 | AJ52: =if(and($D52>AJ$7,$D52<AJ$8),AJ$5,0) -> 249.29 | AK52: =if(and($D52>AK$7,$D52<AK$8),AK$5,0) -> 238.09 | AL52: =if(and($D52>AL$7,$D52<AL$8),AL$5,0) -> 287.57 | ... BF52: =if(and($D52>BF$7,$D52<BF$8),BF$5,0) -> 0
A53: =ceiling(sum(J53:BF150)-sum(J53:BF53),1) -> 713272 | B53: =ceiling(sum(J53:BF53),1) -> 46098 | C53: =sum(E53:H53) -> 0 | D53: 45809 | E53: 0 | F53: 0 | G53: 0 | H53: 0 | I53: =if(D53=DATE(year(today()),month(today()),1),"Current",if(D53>DATE(year(today()),month(today()),1), "Future","Past")) -> Past | J53: =J$5 -> 12605.29 | K53: =K$5 -> 5477.63 | M53: =M$5 -> 4254.87 | N53: =N$5 -> 2129.09 | O53: =O$5 -> 4774.58 | P53: =P$5 -> 3983.19 | Q53: =Q$5 -> 1011.15 | R53: =R$5 -> 685.37 | S53: =S$5 -> 490.36 | T53: =T$5 -> 393.4 | ... AC53: =AC$5 -> 266.5 | AE53: =if(and($D53>AE$7,$D53<AE$8),AE$5,0) -> 490.91 | AF53: =if(and($D53>AF$7,$D53<AF$8),AF$5,0) -> 266.76 | AG53: =if(and($D53>AG$7,$D53<AG$8),AG$5,0) -> 262.71 | AH53: =if(and($D53>AH$7,$D53<AH$8),AH$5,0) -> 261.42 | AI53: =if(and($D53>AI$7,$D53<AI$8),AI$5,0) -> 252.81 | AJ53: =if(and($D53>AJ$7,$D53<AJ$8),AJ$5,0) -> 249.29 | AK53: =if(and($D53>AK$7,$D53<AK$8),AK$5,0) -> 238.09 | AL53: =if(and($D53>AL$7,$D53<AL$8),AL$5,0) -> 287.57 | ... BF53: =if(and($D53>BF$7,$D53<BF$8),BF$5,0) -> 190.46
A54: =ceiling(sum(J54:BF151)-sum(J54:BF54),1) -> 667175 | B54: =ceiling(sum(J54:BF54),1) -> 46098 | C54: =sum(E54:H54) -> 0 | D54: 45839 | E54: 0 | F54: 0 | G54: 0 | H54: 0 | I54: =if(D54=DATE(year(today()),month(today()),1),"Current",if(D54>DATE(year(today()),month(today()),1), "Future","Past")) -> Past | J54: =J$5 -> 12605.29 | K54: =K$5 -> 5477.63 | M54: =M$5 -> 4254.87 | N54: =N$5 -> 2129.09 | O54: =O$5 -> 4774.58 | P54: =P$5 -> 3983.19 | Q54: =Q$5 -> 1011.15 | R54: =R$5 -> 685.37 | S54: =S$5 -> 490.36 | T54: =T$5 -> 393.4 | ... AC54: =AC$5 -> 266.5 | AE54: =if(and($D54>AE$7,$D54<AE$8),AE$5,0) -> 490.91 | AF54: =if(and($D54>AF$7,$D54<AF$8),AF$5,0) -> 266.76 | AG54: =if(and($D54>AG$7,$D54<AG$8),AG$5,0) -> 262.71 | AH54: =if(and($D54>AH$7,$D54<AH$8),AH$5,0) -> 261.42 | AI54: =if(and($D54>AI$7,$D54<AI$8),AI$5,0) -> 252.81 | AJ54: =if(and($D54>AJ$7,$D54<AJ$8),AJ$5,0) -> 249.29 | AK54: =if(and($D54>AK$7,$D54<AK$8),AK$5,0) -> 238.09 | AL54: =if(and($D54>AL$7,$D54<AL$8),AL$5,0) -> 287.57 | ... BF54: =if(and($D54>BF$7,$D54<BF$8),BF$5,0) -> 190.46
A55: =ceiling(sum(J55:BF152)-sum(J55:BF55),1) -> 628706 | B55: =ceiling(sum(J55:BF55),1) -> 38470 | C55: =sum(E55:H55) -> 0 | D55: 45870 | E55: 0 | F55: 0 | G55: 0 | H55: 0 | I55: =if(D55=DATE(year(today()),month(today()),1),"Current",if(D55>DATE(year(today()),month(today()),1), "Future","Past")) -> Past | J55: =J$5 -> 12605.29 | K55: =K$5 -> 5477.63 | M55: =M$5 -> 4254.87 | N55: =N$5 -> 2129.09 | O55: =O$5 -> 4774.58 | P55: =P$5 -> 3983.19 | Q55: =Q$5 -> 1011.15 | R55: =R$5 -> 685.37 | S55: =S$5 -> 490.36 | T55: =T$5 -> 393.4 | ... AC55: =AC$5 -> 266.5 | AE55: 0 | AF55: 0 | AG55: 0 | AH55: 0 | AI55: 0 | AJ55: 0 | AK55: 0 | AL55: 0 | AM55: 0 | AN55: 0 | AO55: 0 | AP55: 0 | AQ55: 0 | AR55: 0 | AS55: 0 | AT55: 0 | AU55: 0 | AV55: 0 | AW55: 0 | AX55: 0 | AY55: 0 | AZ55: 0 | BA55: 0 | BB55: 0 | BC55: 0 | BD55: 0 | BE55: 0 | BF55: 0
A56: =ceiling(sum(J56:BF153)-sum(J56:BF56),1) -> 585237 | B56: =ceiling(sum(J56:BF56),1) -> 43470 | C56: =sum(E56:H56) -> 0 | D56: 45901 | E56: 0 | F56: 0 | G56: 0 | H56: 0 | I56: =if(D56=DATE(year(today()),month(today()),1),"Current",if(D56>DATE(year(today()),month(today()),1), "Future","Past")) -> Past | J56: =J$5 -> 12605.29 | K56: =K$5 -> 5477.63 | L56: 5000 | M56: =M$5 -> 4254.87 | N56: =N$5 -> 2129.09 | O56: =O$5 -> 4774.58 | P56: =P$5 -> 3983.19 | Q56: =Q$5 -> 1011.15 | R56: =R$5 -> 685.37 | S56: =S$5 -> 490.36 | T56: =T$5 -> 393.4 | ... AC56: =AC$5 -> 266.5 | AE56: 0 | AF56: 0 | AG56: 0 | AH56: 0 | AI56: 0 | AJ56: 0 | AK56: 0 | AL56: 0 | AM56: 0 | AN56: 0 | AO56: 0 | AP56: 0 | AQ56: 0 | AR56: 0 | AS56: 0 | AT56: 0 | AU56: 0 | AV56: 0 | AW56: 0 | AX56: 0 | AY56: 0 | AZ56: 0 | BA56: 0 | BB56: 0 | BC56: 0 | BD56: 0 | BE56: 0 | BF56: 0
A57: =ceiling(sum(J57:BF154)-sum(J57:BF57),1) -> 541768 | B57: =ceiling(sum(J57:BF57),1) -> 43470 | C57: 0 | D57: 45931 | E57: 0 | F57: 0 | G57: 0 | H57: 0 | I57: =if(D57=DATE(year(today()),month(today()),1),"Current",if(D57>DATE(year(today()),month(today()),1), "Future","Past")) -> Past | J57: =J$5 -> 12605.29 | K57: =K$5 -> 5477.63 | L57: 5000 | M57: =M$5 -> 4254.87 | N57: =N$5 -> 2129.09 | O57: =O$5 -> 4774.58 | P57: =P$5 -> 3983.19 | Q57: =Q$5 -> 1011.15 | R57: =R$5 -> 685.37 | S57: =S$5 -> 490.36 | T57: =T$5 -> 393.4 | ... AC57: =AC$5 -> 266.5 | AE57: 0 | AF57: 0 | AG57: 0 | AH57: 0 | AI57: 0 | AJ57: 0 | AK57: 0 | AL57: 0 | AM57: 0 | AN57: 0 | AO57: 0 | AP57: 0 | AQ57: 0 | AR57: 0 | AS57: 0 | AT57: 0 | AU57: 0 | AV57: 0 | AW57: 0 | AX57: 0 | AY57: 0 | AZ57: 0 | BA57: 0 | BB57: 0 | BC57: 0 | BD57: 0 | BE57: 0 | BF57: 0
A58: =ceiling(sum(J58:BF155)-sum(J58:BF58),1) -> 498299 | B58: =ceiling(sum(J58:BF58),1) -> 43470 | C58: =sum(E58:H58) -> 0 | D58: 45962 | E58: ="Paid "&2444.59 -> Paid 2444.59 | F58: ="Paid "&28715.49 -> Paid 28715.49 | G58: ="Paid "&19426.26 -> Paid 19426.26 | H58: ="Paid "&30502.12 -> Paid 30502.12 | I58: =if(D58=DATE(year(today()),month(today()),1),"Current",if(D58>DATE(year(today()),month(today()),1), "Future","Past")) -> Current | J58: =J$5 -> 12605.29 | K58: =K$5 -> 5477.63 | L58: 5000 | M58: =M$5 -> 4254.87 | N58: =N$5 -> 2129.09 | O58: =O$5 -> 4774.58 | P58: =P$5 -> 3983.19 | Q58: =Q$5 -> 1011.15 | R58: =R$5 -> 685.37 | S58: =S$5 -> 490.36 | T58: =T$5 -> 393.4 | ... AC58: =AC$5 -> 266.5 | AE58: 0 | AF58: 0 | AG58: 0 | AH58: 0 | AI58: 0 | AJ58: 0 | AK58: 0 | AL58: 0 | AM58: 0 | AN58: 0 | AO58: 0 | AP58: 0 | AQ58: 0 | AR58: 0 | AS58: 0 | AT58: 0 | AU58: 0 | AV58: 0 | AW58: 0 | AX58: 0 | AY58: 0 | AZ58: 0 | BA58: 0 | BB58: 0 | BC58: 0 | BD58: 0 | BE58: 0 | BF58: 0
A59: =ceiling(sum(J59:BF156)-sum(J59:BF59),1) -> 459779 | B59: =ceiling(sum(J59:BF59),1) -> 38520 | C59: =sum(E59:H59) -> 38519.68 | D59: 45992 | E59: =sumif($J$19:BF58,E$19,$J59:BF59) -> 2379.21 | F59: =sumif($J$19:BG58,F$19,$J59:BG59) -> 23820.67 | G59: =sumif($J$19:BH58,G$19,$J59:BH59) -> 12319.8 | H59: =sumif($J$19:BI58,H$19,$J59:BI59) -> 0 | I59: =if(D59=DATE(year(today()),month(today()),1),"Current",if(D59>DATE(year(today()),month(today()),1), "Future","Past")) -> Future | J59: =J$5 -> 12605.29 | K59: =K$5 -> 5477.63 | L59: 5000 | M59: =M$5 -> 4254.87 | N59: =N$5 -> 2129.09 | O59: =O$5 -> 4774.58 | Q59: =Q$5 -> 1011.15 | R59: =R$5 -> 685.37 | S59: =S$5 -> 490.36 | T59: =T$5 -> 393.4 | U59: =U$5 -> 357.35 | V59: =V$5 -> 344.35 | W59: =W$5 -> 289.56 | X59: =X$5 -> 250.12 | Z59: =Z$5 -> 189.66 | AA59: =AA$5 -> 140.89 | AB59: =AB$5 -> 126.01 | AE59: 0 | AF59: 0 | AG59: 0 | AH59: 0 | AI59: 0 | AJ59: 0 | AK59: 0 | AL59: 0 | AM59: 0 | AN59: 0 | AO59: 0 | AP59: 0 | AQ59: 0 | AR59: 0 | AS59: 0 | AT59: 0 | AU59: 0 | AV59: 0 | AW59: 0 | AX59: 0 | AY59: 0 | AZ59: 0 | BA59: 0 | BB59: 0 | BC59: 0 | BD59: 0 | BE59: 0 | BF59: 0
A60: =ceiling(sum(J60:BF157)-sum(J60:BF60),1) -> 421260 | B60: =ceiling(sum(J60:BF60),1) -> 38520 | C60: =sum(E60:H60) -> 38519.68 | D60: 46023 | E60: =sumif($J$19:BF59,E$19,$J60:BF60) -> 2379.21 | F60: =sumif($J$19:BG59,F$19,$J60:BG60) -> 23820.67 | G60: =sumif($J$19:BH59,G$19,$J60:BH60) -> 12319.8 | H60: =sumif($J$19:BI59,H$19,$J60:BI60) -> 0 | I60: =if(D60=DATE(year(today()),month(today()),1),"Current",if(D60>DATE(year(today()),month(today()),1), "Future","Past")) -> Future | J60: =J$5 -> 12605.29 | K60: =K$5 -> 5477.63 | L60: 5000 | M60: =M$5 -> 4254.87 | N60: =N$5 -> 2129.09 | O60: =O$5 -> 4774.58 | Q60: =Q$5 -> 1011.15 | R60: =R$5 -> 685.37 | S60: =S$5 -> 490.36 | T60: =T$5 -> 393.4 | U60: =U$5 -> 357.35 | V60: =V$5 -> 344.35 | W60: =W$5 -> 289.56 | X60: =X$5 -> 250.12 | Z60: =Z$5 -> 189.66 | AA60: =AA$5 -> 140.89 | AB60: =AB$5 -> 126.01 | AE60: 0 | AF60: 0 | AG60: 0 | AH60: 0 | AI60: 0 | AJ60: 0 | AK60: 0 | AL60: 0 | AM60: 0 | AN60: 0 | AO60: 0 | AP60: 0 | AQ60: 0 | AR60: 0 | AS60: 0 | AT60: 0 | AU60: 0 | AV60: 0 | AW60: 0 | AX60: 0 | AY60: 0 | AZ60: 0 | BA60: 0 | BB60: 0 | BC60: 0 | BD60: 0 | BE60: 0 | BF60: 0
A61: =ceiling(sum(J61:BF158)-sum(J61:BF61),1) -> 387859 | B61: =ceiling(sum(J61:BF61),1) -> 33401 | C61: =sum(E61:H61) -> 33400.75 | D61: 46054 | E61: =sumif($J$19:BF60,E$19,$J61:BF61) -> 2379.21 | F61: =sumif($J$19:BG60,F$19,$J61:BG61) -> 23476.32 | G61: =sumif($J$19:BH60,G$19,$J61:BH61) -> 7545.22 | H61: =sumif($J$19:BI60,H$19,$J61:BI61) -> 0 | I61: =if(D61=DATE(year(today()),month(today()),1),"Current",if(D61>DATE(year(today()),month(today()),1), "Future","Past")) -> Future | J61: =J$5 -> 12605.29 | K61: =K$5 -> 5477.63 | L61: 5000 | M61: =M$5 -> 4254.87 | N61: =N$5 -> 2129.09 | Q61: =Q$5 -> 1011.15 | R61: =R$5 -> 685.37 | S61: =S$5 -> 490.36 | T61: =T$5 -> 393.4 | U61: =U$5 -> 357.35 | W61: =W$5 -> 289.56 | X61: =X$5 -> 250.12 | Z61: =Z$5 -> 189.66 | AA61: =AA$5 -> 140.89 | AB61: =AB$5 -> 126.01 | AE61: 0 | AF61: 0 | AG61: 0 | AH61: 0 | AI61: 0 | AJ61: 0 | AK61: 0 | AL61: 0 | AM61: 0 | AN61: 0 | AO61: 0 | AP61: 0 | AQ61: 0 | AR61: 0 | AS61: 0 | AT61: 0 | AU61: 0 | AV61: 0 | AW61: 0 | AX61: 0 | AY61: 0 | AZ61: 0 | BA61: 0 | BB61: 0 | BC61: 0 | BD61: 0 | BE61: 0 | BF61: 0
A62: =ceiling(sum(J62:BF159)-sum(J62:BF62),1) -> 354458 | B62: =ceiling(sum(J62:BF62),1) -> 33401 | C62: =sum(E62:H62) -> 33400.75 | D62: 46082 | E62: =sumif($J$19:BF61,E$19,$J62:BF62) -> 2379.21 | F62: =sumif($J$19:BG61,F$19,$J62:BG62) -> 23476.32 | G62: =sumif($J$19:BH61,G$19,$J62:BH62) -> 7545.22 | H62: =sumif($J$19:BI61,H$19,$J62:BI62) -> 0 | I62: =if(D62=DATE(year(today()),month(today()),1),"Current",if(D62>DATE(year(today()),month(today()),1), "Future","Past")) -> Future | J62: =J$5 -> 12605.29 | K62: =K$5 -> 5477.63 | L62: 5000 | M62: =M$5 -> 4254.87 | N62: =N$5 -> 2129.09 | Q62: =Q$5 -> 1011.15 | R62: =R$5 -> 685.37 | S62: =S$5 -> 490.36 | T62: =T$5 -> 393.4 | U62: =U$5 -> 357.35 | W62: =W$5 -> 289.56 | X62: =X$5 -> 250.12 | Z62: =Z$5 -> 189.66 | AA62: =AA$5 -> 140.89 | AB62: =AB$5 -> 126.01 | AE62: 0 | AF62: 0 | AG62: 0 | AH62: 0 | AI62: 0 | AJ62: 0 | AK62: 0 | AL62: 0 | AM62: 0 | AN62: 0 | AO62: 0 | AP62: 0 | AQ62: 0 | AR62: 0 | AS62: 0 | AT62: 0 | AU62: 0 | AV62: 0 | AW62: 0 | AX62: 0 | AY62: 0 | AZ62: 0 | BA62: 0 | BB62: 0 | BC62: 0 | BD62: 0 | BE62: 0 | BF62: 0
A63: =ceiling(sum(J63:BF160)-sum(J63:BF63),1) -> 321057 | B63: =ceiling(sum(J63:BF63),1) -> 33401 | C63: =sum(E63:H63) -> 33400.75 | D63: 46113 | E63: =sumif($J$19:BF62,E$19,$J63:BF63) -> 2379.21 | F63: =sumif($J$19:BG62,F$19,$J63:BG63) -> 23476.32 | G63: =sumif($J$19:BH62,G$19,$J63:BH63) -> 7545.22 | H63: =sumif($J$19:BI62,H$19,$J63:BI63) -> 0 | I63: =if(D63=DATE(year(today()),month(today()),1),"Current",if(D63>DATE(year(today()),month(today()),1), "Future","Past")) -> Future | J63: =J$5 -> 12605.29 | K63: =K$5 -> 5477.63 | L63: 5000 | M63: =M$5 -> 4254.87 | N63: =N$5 -> 2129.09 | Q63: =Q$5 -> 1011.15 | R63: =R$5 -> 685.37 | S63: =S$5 -> 490.36 | T63: =T$5 -> 393.4 | U63: =U$5 -> 357.35 | W63: =W$5 -> 289.56 | X63: =X$5 -> 250.12 | Z63: =Z$5 -> 189.66 | AA63: =AA$5 -> 140.89 | AB63: =AB$5 -> 126.01 | AE63: 0 | AF63: 0 | AG63: 0 | AH63: 0 | AI63: 0 | AJ63: 0 | AK63: 0 | AL63: 0 | AM63: 0 | AN63: 0 | AO63: 0 | AP63: 0 | AQ63: 0 | AR63: 0 | AS63: 0 | AT63: 0 | AU63: 0 | AV63: 0 | AW63: 0 | AX63: 0 | AY63: 0 | AZ63: 0 | BA63: 0 | BB63: 0 | BC63: 0 | BD63: 0 | BE63: 0 | BF63: 0
A64: =ceiling(sum(J64:BF161)-sum(J64:BF64),1) -> 287657 | B64: =ceiling(sum(J64:BF64),1) -> 33401 | C64: =sum(E64:H64) -> 33400.75 | D64: 46143 | E64: =sumif($J$19:BF63,E$19,$J64:BF64) -> 2379.21 | F64: =sumif($J$19:BG63,F$19,$J64:BG64) -> 23476.32 | G64: =sumif($J$19:BH63,G$19,$J64:BH64) -> 7545.22 | H64: =sumif($J$19:BI63,H$19,$J64:BI64) -> 0 | I64: =if(D64=DATE(year(today()),month(today()),1),"Current",if(D64>DATE(year(today()),month(today()),1), "Future","Past")) -> Future | J64: =J$5 -> 12605.29 | K64: =K$5 -> 5477.63 | L64: 5000 | M64: =M$5 -> 4254.87 | N64: =N$5 -> 2129.09 | Q64: =Q$5 -> 1011.15 | R64: =R$5 -> 685.37 | S64: =S$5 -> 490.36 | T64: =T$5 -> 393.4 | U64: =U$5 -> 357.35 | W64: =W$5 -> 289.56 | X64: =X$5 -> 250.12 | Z64: =Z$5 -> 189.66 | AA64: =AA$5 -> 140.89 | AB64: =AB$5 -> 126.01 | AE64: 0 | AF64: 0 | AG64: 0 | AH64: 0 | AI64: 0 | AJ64: 0 | AK64: 0 | AL64: 0 | AM64: 0 | AN64: 0 | AO64: 0 | AP64: 0 | AQ64: 0 | AR64: 0 | AS64: 0 | AT64: 0 | AU64: 0 | AV64: 0 | AW64: 0 | AX64: 0 | AY64: 0 | AZ64: 0 | BA64: 0 | BB64: 0 | BC64: 0 | BD64: 0 | BE64: 0 | BF64: 0
A65: =ceiling(sum(J65:BF162)-sum(J65:BF65),1) -> 219733 | B65: =ceiling(sum(J65:BF65),1) -> 67924 | C65: =sum(E65:H65) -> 67923.12 | D65: 46174 | E65: =sumif($J$19:BF64,E$19,$J65:BF65) -> 2379.21 | F65: =sumif($J$19:BG64,F$19,$J65:BG65) -> 57998.69 | G65: =sumif($J$19:BH64,G$19,$J65:BH65) -> 7545.22 | H65: =sumif($J$19:BI64,H$19,$J65:BI65) -> 0 | I65: =if(D65=DATE(year(today()),month(today()),1),"Current",if(D65>DATE(year(today()),month(today()),1), "Future","Past")) -> Future | J65: =J$5 -> 12605.29 | K65: 40000 | L65: 5000 | M65: =M$5 -> 4254.87 | N65: =N$5 -> 2129.09 | Q65: =Q$5 -> 1011.15 | R65: =R$5 -> 685.37 | S65: =S$5 -> 490.36 | T65: =T$5 -> 393.4 | U65: =U$5 -> 357.35 | W65: =W$5 -> 289.56 | X65: =X$5 -> 250.12 | Z65: =Z$5 -> 189.66 | AA65: =AA$5 -> 140.89 | AB65: =AB$5 -> 126.01 | AE65: 0 | AF65: 0 | AG65: 0 | AH65: 0 | AI65: 0 | AJ65: 0 | AK65: 0 | AL65: 0 | AM65: 0 | AN65: 0 | AO65: 0 | AP65: 0 | AQ65: 0 | AR65: 0 | AS65: 0 | AT65: 0 | AU65: 0 | AV65: 0 | AW65: 0 | AX65: 0 | AY65: 0 | AZ65: 0 | BA65: 0 | BB65: 0 | BC65: 0 | BD65: 0 | BE65: 0 | BF65: 0
A66: =ceiling(sum(J66:BF163)-sum(J66:BF66),1) -> 191810 | B66: =ceiling(sum(J66:BF66),1) -> 27924 | C66: =sum(E66:H66) -> 27923.12 | D66: 46204 | E66: =sumif($J$19:BF65,E$19,$J66:BF66) -> 2379.21 | F66: =sumif($J$19:BG65,F$19,$J66:BG66) -> 17998.69 | G66: =sumif($J$19:BH65,G$19,$J66:BH66) -> 7545.22 | H66: =sumif($J$19:BI65,H$19,$J66:BI66) -> 0 | I66: =if(D66=DATE(year(today()),month(today()),1),"Current",if(D66>DATE(year(today()),month(today()),1), "Future","Past")) -> Future | J66: =J$5 -> 12605.29 | L66: 5000 | M66: =M$5 -> 4254.87 | N66: =N$5 -> 2129.09 | Q66: =Q$5 -> 1011.15 | R66: =R$5 -> 685.37 | S66: =S$5 -> 490.36 | T66: =T$5 -> 393.4 | U66: =U$5 -> 357.35 | W66: =W$5 -> 289.56 | X66: =X$5 -> 250.12 | Z66: =Z$5 -> 189.66 | AA66: =AA$5 -> 140.89 | AB66: =AB$5 -> 126.01 | AE66: 0 | AF66: 0 | AG66: 0 | AH66: 0 | AI66: 0 | AJ66: 0 | AK66: 0 | AL66: 0 | AM66: 0 | AN66: 0 | AO66: 0 | AP66: 0 | AQ66: 0 | AR66: 0 | AS66: 0 | AT66: 0 | AU66: 0 | AV66: 0 | AW66: 0 | AX66: 0 | AY66: 0 | AZ66: 0 | BA66: 0 | BB66: 0 | BC66: 0 | BD66: 0 | BE66: 0 | BF66: 0
A67: =ceiling(sum(J67:BF164)-sum(J67:BF67),1) -> 163887 | B67: =ceiling(sum(J67:BF67),1) -> 27924 | C67: =sum(E67:H67) -> 27923.12 | D67: 46235 | E67: =sumif($J$19:BF66,E$19,$J67:BF67) -> 2379.21 | F67: =sumif($J$19:BG66,F$19,$J67:BG67) -> 17998.69 | G67: =sumif($J$19:BH66,G$19,$J67:BH67) -> 7545.22 | H67: =sumif($J$19:BI66,H$19,$J67:BI67) -> 0 | I67: =if(D67=DATE(year(today()),month(today()),1),"Current",if(D67>DATE(year(today()),month(today()),1), "Future","Past")) -> Future | J67: =J$5 -> 12605.29 | L67: 5000 | M67: =M$5 -> 4254.87 | N67: =N$5 -> 2129.09 | Q67: =Q$5 -> 1011.15 | R67: =R$5 -> 685.37 | S67: =S$5 -> 490.36 | T67: =T$5 -> 393.4 | U67: =U$5 -> 357.35 | W67: =W$5 -> 289.56 | X67: =X$5 -> 250.12 | Z67: =Z$5 -> 189.66 | AA67: =AA$5 -> 140.89 | AB67: =AB$5 -> 126.01 | AE67: 0 | AF67: 0 | AG67: 0 | AH67: 0 | AI67: 0 | AJ67: 0 | AK67: 0 | AL67: 0 | AM67: 0 | AN67: 0 | AO67: 0 | AP67: 0 | AQ67: 0 | AR67: 0 | AS67: 0 | AT67: 0 | AU67: 0 | AV67: 0 | AW67: 0 | AX67: 0 | AY67: 0 | AZ67: 0 | BA67: 0 | BB67: 0 | BC67: 0 | BD67: 0 | BE67: 0 | BF67: 0
A68: =ceiling(sum(J68:BF165)-sum(J68:BF68),1) -> 135964 | B68: =ceiling(sum(J68:BF68),1) -> 27924 | C68: =sum(E68:H68) -> 27923.12 | D68: 46266 | E68: =sumif($J$19:BF67,E$19,$J68:BF68) -> 2379.21 | F68: =sumif($J$19:BG67,F$19,$J68:BG68) -> 17998.69 | G68: =sumif($J$19:BH67,G$19,$J68:BH68) -> 7545.22 | H68: =sumif($J$19:BI67,H$19,$J68:BI68) -> 0 | I68: =if(D68=DATE(year(today()),month(today()),1),"Current",if(D68>DATE(year(today()),month(today()),1), "Future","Past")) -> Future | J68: =J$5 -> 12605.29 | L68: 5000 | M68: =M$5 -> 4254.87 | N68: =N$5 -> 2129.09 | Q68: =Q$5 -> 1011.15 | R68: =R$5 -> 685.37 | S68: =S$5 -> 490.36 | T68: =T$5 -> 393.4 | U68: =U$5 -> 357.35 | W68: =W$5 -> 289.56 | X68: =X$5 -> 250.12 | Z68: =Z$5 -> 189.66 | AA68: =AA$5 -> 140.89 | AB68: =AB$5 -> 126.01 | AE68: 0 | AF68: 0 | AG68: 0 | AH68: 0 | AI68: 0 | AJ68: 0 | AK68: 0 | AL68: 0 | AM68: 0 | AN68: 0 | AO68: 0 | AP68: 0 | AQ68: 0 | AR68: 0 | AS68: 0 | AT68: 0 | AU68: 0 | AV68: 0 | AW68: 0 | AX68: 0 | AY68: 0 | AZ68: 0 | BA68: 0 | BB68: 0 | BC68: 0 | BD68: 0 | BE68: 0 | BF68: 0
A69: =ceiling(sum(J69:BF166)-sum(J69:BF69),1) -> 113992 | B69: =ceiling(sum(J69:BF69),1) -> 21972 | C69: =sum(E69:H69) -> 21971.73 | D69: 46296 | E69: =sumif($J$19:BF68,E$19,$J69:BF69) -> 2379.21 | F69: =sumif($J$19:BG68,F$19,$J69:BG69) -> 17998.69 | G69: =sumif($J$19:BH68,G$19,$J69:BH69) -> 1593.83 | H69: =sumif($J$19:BI68,H$19,$J69:BI69) -> 0 | I69: =if(D69=DATE(year(today()),month(today()),1),"Current",if(D69>DATE(year(today()),month(today()),1), "Future","Past")) -> Future | J69: =J$5 -> 12605.29 | L69: 5000 | N69: =N$5 -> 2129.09 | S69: =S$5 -> 490.36 | T69: =T$5 -> 393.4 | U69: =U$5 -> 357.35 | W69: =W$5 -> 289.56 | X69: =X$5 -> 250.12 | Z69: =Z$5 -> 189.66 | AA69: =AA$5 -> 140.89 | AB69: =AB$5 -> 126.01 | AE69: 0 | AF69: 0 | AG69: 0 | AH69: 0 | AI69: 0 | AJ69: 0 | AK69: 0 | AL69: 0 | AM69: 0 | AN69: 0 | AO69: 0 | AP69: 0 | AQ69: 0 | AR69: 0 | AS69: 0 | AT69: 0 | AU69: 0 | AV69: 0 | AW69: 0 | AX69: 0 | AY69: 0 | AZ69: 0 | BA69: 0 | BB69: 0 | BC69: 0 | BD69: 0 | BE69: 0 | BF69: 0
A70: =ceiling(sum(J70:BF167)-sum(J70:BF70),1) -> 92162 | B70: =ceiling(sum(J70:BF70),1) -> 21831 | C70: =sum(E70:H70) -> 21830.84 | D70: 46327 | E70: =sumif($J$19:BF69,E$19,$J70:BF70) -> 2379.21 | F70: =sumif($J$19:BG69,F$19,$J70:BG70) -> 17998.69 | G70: =sumif($J$19:BH69,G$19,$J70:BH70) -> 1452.94 | H70: =sumif($J$19:BI69,H$19,$J70:BI70) -> 0 | I70: =if(D70=DATE(year(today()),month(today()),1),"Current",if(D70>DATE(year(today()),month(today()),1), "Future","Past")) -> Future | J70: =J$5 -> 12605.29 | L70: 5000 | N70: =N$5 -> 2129.09 | S70: =S$5 -> 490.36 | T70: =T$5 -> 393.4 | U70: =U$5 -> 357.35 | W70: =W$5 -> 289.56 | X70: =X$5 -> 250.12 | Z70: =Z$5 -> 189.66 | AB70: =AB$5 -> 126.01 | AE70: 0 | AF70: 0 | AG70: 0 | AH70: 0 | AI70: 0 | AJ70: 0 | AK70: 0 | AL70: 0 | AM70: 0 | AN70: 0 | AO70: 0 | AP70: 0 | AQ70: 0 | AR70: 0 | AS70: 0 | AT70: 0 | AU70: 0 | AV70: 0 | AW70: 0 | AX70: 0 | AY70: 0 | AZ70: 0 | BA70: 0 | BB70: 0 | BC70: 0 | BD70: 0 | BE70: 0 | BF70: 0
A71: =ceiling(sum(J71:BF168)-sum(J71:BF71),1) -> 70331 | B71: =ceiling(sum(J71:BF71),1) -> 21831 | C71: =sum(E71:H71) -> 21830.84 | D71: 46357 | E71: =sumif($J$19:BF70,E$19,$J71:BF71) -> 2379.21 | F71: =sumif($J$19:BG70,F$19,$J71:BG71) -> 17998.69 | G71: =sumif($J$19:BH70,G$19,$J71:BH71) -> 1452.94 | H71: =sumif($J$19:BI70,H$19,$J71:BI71) -> 0 | I71: =if(D71=DATE(year(today()),month(today()),1),"Current",if(D71>DATE(year(today()),month(today()),1), "Future","Past")) -> Future | J71: =J$5 -> 12605.29 | L71: 5000 | N71: =N$5 -> 2129.09 | S71: =S$5 -> 490.36 | T71: =T$5 -> 393.4 | U71: =U$5 -> 357.35 | W71: =W$5 -> 289.56 | X71: =X$5 -> 250.12 | Z71: =Z$5 -> 189.66 | AB71: =AB$5 -> 126.01 | AE71: 0 | AF71: 0 | AG71: 0 | AH71: 0 | AI71: 0 | AJ71: 0 | AK71: 0 | AL71: 0 | AM71: 0 | AN71: 0 | AO71: 0 | AP71: 0 | AQ71: 0 | AR71: 0 | AS71: 0 | AT71: 0 | AU71: 0 | AV71: 0 | AW71: 0 | AX71: 0 | AY71: 0 | AZ71: 0 | BA71: 0 | BB71: 0 | BC71: 0 | BD71: 0 | BE71: 0 | BF71: 0
A72: =ceiling(sum(J72:BF169)-sum(J72:BF72),1) -> 62844 | B72: =ceiling(sum(J72:BF72),1) -> 7487 | C72: =sum(E72:H72) -> 7486.44 | D72: 46388 | E72: =sumif($J$19:BF71,E$19,$J72:BF72) -> 2129.09 | F72: =sumif($J$19:BG71,F$19,$J72:BG72) -> 5000 | G72: =sumif($J$19:BH71,G$19,$J72:BH72) -> 357.35 | H72: =sumif($J$19:BI71,H$19,$J72:BI72) -> 0 | I72: =if(D72=DATE(year(today()),month(today()),1),"Current",if(D72>DATE(year(today()),month(today()),1), "Future","Past")) -> Future | L72: 5000 | N72: =N$5 -> 2129.09 | U72: =U$5 -> 357.35 | AE72: 0 | AF72: 0 | AG72: 0 | AH72: 0 | AI72: 0 | AJ72: 0 | AK72: 0 | AL72: 0 | AM72: 0 | AN72: 0 | AO72: 0 | AP72: 0 | AQ72: 0 | AR72: 0 | AS72: 0 | AT72: 0 | AU72: 0 | AV72: 0 | AW72: 0 | AX72: 0 | AY72: 0 | AZ72: 0 | BA72: 0 | BB72: 0 | BC72: 0 | BD72: 0 | BE72: 0 | BF72: 0
A73: =ceiling(sum(J73:BF170)-sum(J73:BF73),1) -> 55358 | B73: =ceiling(sum(J73:BF73),1) -> 7487 | C73: =sum(E73:H73) -> 7486.44 | D73: 46419 | E73: =sumif($J$19:BF72,E$19,$J73:BF73) -> 2129.09 | F73: =sumif($J$19:BG72,F$19,$J73:BG73) -> 5000 | G73: =sumif($J$19:BH72,G$19,$J73:BH73) -> 357.35 | H73: =sumif($J$19:BI72,H$19,$J73:BI73) -> 0 | I73: =if(D73=DATE(year(today()),month(today()),1),"Current",if(D73>DATE(year(today()),month(today()),1), "Future","Past")) -> Future | L73: 5000 | N73: =N$5 -> 2129.09 | U73: =U$5 -> 357.35 | AE73: 0 | AF73: 0 | AG73: 0 | AH73: 0 | AI73: 0 | AJ73: 0 | AK73: 0 | AL73: 0 | AM73: 0 | AN73: 0 | AO73: 0 | AP73: 0 | AQ73: 0 | AR73: 0 | AS73: 0 | AT73: 0 | AU73: 0 | AV73: 0 | AW73: 0 | AX73: 0 | AY73: 0 | AZ73: 0 | BA73: 0 | BB73: 0 | BC73: 0 | BD73: 0 | BE73: 0 | BF73: 0
A74: =ceiling(sum(J74:BF171)-sum(J74:BF74),1) -> 25000 | B74: =ceiling(sum(J74:BF74),1) -> 30358 | C74: =sum(E74:H74) -> 30357.35 | D74: 46447 | E74: =sumif($J$19:BF73,E$19,$J74:BF74) -> 25000 | F74: =sumif($J$19:BG73,F$19,$J74:BG74) -> 5000 | G74: =sumif($J$19:BH73,G$19,$J74:BH74) -> 357.35 | H74: =sumif($J$19:BI73,H$19,$J74:BI74) -> 0 | I74: =if(D74=DATE(year(today()),month(today()),1),"Current",if(D74>DATE(year(today()),month(today()),1), "Future","Past")) -> Future | L74: 5000 | N74: 25000 | U74: =U$5 -> 357.35 | AE74: 0 | AF74: 0 | AG74: 0 | AH74: 0 | AI74: 0 | AJ74: 0 | AK74: 0 | AL74: 0 | AM74: 0 | AN74: 0 | AO74: 0 | AP74: 0 | AQ74: 0 | AR74: 0 | AS74: 0 | AT74: 0 | AU74: 0 | AV74: 0 | AW74: 0 | AX74: 0 | AY74: 0 | AZ74: 0 | BA74: 0 | BB74: 0 | BC74: 0 | BD74: 0 | BE74: 0 | BF74: 0
A75: =ceiling(sum(J75:BF172)-sum(J75:BF75),1) -> 20000 | B75: =ceiling(sum(J75:BF75),1) -> 5000 | C75: =sum(E75:H75) -> 5000 | D75: 46478 | E75: =sumif($J$19:BF74,E$19,$J75:BF75) -> 0 | F75: =sumif($J$19:BG74,F$19,$J75:BG75) -> 5000 | G75: =sumif($J$19:BH74,G$19,$J75:BH75) -> 0 | H75: =sumif($J$19:BI74,H$19,$J75:BI75) -> 0 | I75: =if(D75=DATE(year(today()),month(today()),1),"Current",if(D75>DATE(year(today()),month(today()),1), "Future","Past")) -> Future | L75: 5000 | AE75: 0 | AF75: 0 | AG75: 0 | AH75: 0 | AI75: 0 | AJ75: 0 | AK75: 0 | AL75: 0 | AM75: 0 | AN75: 0 | AO75: 0 | AP75: 0 | AQ75: 0 | AR75: 0 | AS75: 0 | AT75: 0 | AU75: 0 | AV75: 0 | AW75: 0 | AX75: 0 | AY75: 0 | AZ75: 0 | BA75: 0 | BB75: 0 | BC75: 0 | BD75: 0 | BE75: 0 | BF75: 0
A76: =ceiling(sum(J76:BF173)-sum(J76:BF76),1) -> 15000 | B76: =ceiling(sum(J76:BF76),1) -> 5000 | C76: =sum(E76:H76) -> 5000 | D76: 46508 | E76: =sumif($J$19:BF75,E$19,$J76:BF76) -> 0 | F76: =sumif($J$19:BG75,F$19,$J76:BG76) -> 5000 | G76: =sumif($J$19:BH75,G$19,$J76:BH76) -> 0 | H76: =sumif($J$19:BI75,H$19,$J76:BI76) -> 0 | I76: =if(D76=DATE(year(today()),month(today()),1),"Current",if(D76>DATE(year(today()),month(today()),1), "Future","Past")) -> Future | L76: 5000 | AE76: 0 | AF76: 0 | AG76: 0 | AH76: 0 | AI76: 0 | AJ76: 0 | AK76: 0 | AL76: 0 | AM76: 0 | AN76: 0 | AO76: 0 | AP76: 0 | AQ76: 0 | AR76: 0 | AS76: 0 | AT76: 0 | AU76: 0 | AV76: 0 | AW76: 0 | AX76: 0 | AY76: 0 | AZ76: 0 | BA76: 0 | BB76: 0 | BC76: 0 | BD76: 0 | BE76: 0 | BF76: 0
A77: =ceiling(sum(J77:BF174)-sum(J77:BF77),1) -> 10000 | B77: =ceiling(sum(J77:BF77),1) -> 5000 | C77: =sum(E77:H77) -> 5000 | D77: 46539 | E77: =sumif($J$19:BF76,E$19,$J77:BF77) -> 0 | F77: =sumif($J$19:BG76,F$19,$J77:BG77) -> 5000 | G77: =sumif($J$19:BH76,G$19,$J77:BH77) -> 0 | H77: =sumif($J$19:BI76,H$19,$J77:BI77) -> 0 | I77: =if(D77=DATE(year(today()),month(today()),1),"Current",if(D77>DATE(year(today()),month(today()),1), "Future","Past")) -> Future | L77: 5000 | AE77: 0 | AF77: 0 | AG77: 0 | AH77: 0 | AI77: 0 | AJ77: 0 | AK77: 0 | AL77: 0 | AM77: 0 | AN77: 0 | AO77: 0 | AP77: 0 | AQ77: 0 | AR77: 0 | AS77: 0 | AT77: 0 | AU77: 0 | AV77: 0 | AW77: 0 | AX77: 0 | AY77: 0 | AZ77: 0 | BA77: 0 | BB77: 0 | BC77: 0 | BD77: 0 | BE77: 0 | BF77: 0
A78: =ceiling(sum(J78:BF175)-sum(J78:BF78),1) -> 5000 | B78: =ceiling(sum(J78:BF78),1) -> 5000 | C78: =sum(E78:H78) -> 5000 | D78: 46569 | E78: =sumif($J$19:BF77,E$19,$J78:BF78) -> 0 | F78: =sumif($J$19:BG77,F$19,$J78:BG78) -> 5000 | G78: =sumif($J$19:BH77,G$19,$J78:BH78) -> 0 | H78: =sumif($J$19:BI77,H$19,$J78:BI78) -> 0 | I78: =if(D78=DATE(year(today()),month(today()),1),"Current",if(D78>DATE(year(today()),month(today()),1), "Future","Past")) -> Future | L78: 5000 | AE78: 0 | AF78: 0 | AG78: 0 | AH78: 0 | AI78: 0 | AJ78: 0 | AK78: 0 | AL78: 0 | AM78: 0 | AN78: 0 | AO78: 0 | AP78: 0 | AQ78: 0 | AR78: 0 | AS78: 0 | AT78: 0 | AU78: 0 | AV78: 0 | AW78: 0 | AX78: 0 | AY78: 0 | AZ78: 0 | BA78: 0 | BB78: 0 | BC78: 0 | BD78: 0 | BE78: 0 | BF78: 0
A79: =ceiling(sum(J79:BF176)-sum(J79:BF79),1) -> 0 | B79: =ceiling(sum(J79:BF79),1) -> 5000 | C79: =sum(E79:H79) -> 5000 | D79: 46600 | E79: =sumif($J$19:BF78,E$19,$J79:BF79) -> 0 | F79: =sumif($J$19:BG78,F$19,$J79:BG79) -> 5000 | G79: =sumif($J$19:BH78,G$19,$J79:BH79) -> 0 | H79: =sumif($J$19:BI78,H$19,$J79:BI79) -> 0 | I79: =if(D79=DATE(year(today()),month(today()),1),"Current",if(D79>DATE(year(today()),month(today()),1), "Future","Past")) -> Future | L79: 5000 | AE79: 0 | AF79: 0 | AG79: 0 | AH79: 0 | AI79: 0 | AJ79: 0 | AK79: 0 | AL79: 0 | AM79: 0 | AN79: 0 | AO79: 0 | AP79: 0 | AQ79: 0 | AR79: 0 | AS79: 0 | AT79: 0 | AU79: 0 | AV79: 0 | AW79: 0 | AX79: 0 | AY79: 0 | AZ79: 0 | BA79: 0 | BB79: 0 | BC79: 0 | BD79: 0 | BE79: 0 | BF79: 0
A80: =ceiling(sum(J80:BF177)-sum(J80:BF80),1) -> 0 | B80: =ceiling(sum(J80:BF80),1) -> 0 | C80: =sum(E80:H80) -> 0 | D80: 46631 | E80: =sumif($J$19:BF79,E$19,$J80:BF80) -> 0 | F80: =sumif($J$19:BG79,F$19,$J80:BG80) -> 0 | G80: =sumif($J$19:BH79,G$19,$J80:BH80) -> 0 | H80: =sumif($J$19:BI79,H$19,$J80:BI80) -> 0 | I80: =if(D80=DATE(year(today()),month(today()),1),"Current",if(D80>DATE(year(today()),month(today()),1), "Future","Past")) -> Future | AE80: 0 | AF80: 0 | AG80: 0 | AH80: 0 | AI80: 0 | AJ80: 0 | AK80: 0 | AL80: 0 | AM80: 0 | AN80: 0 | AO80: 0 | AP80: 0 | AQ80: 0 | AR80: 0 | AS80: 0 | AT80: 0 | AU80: 0 | AV80: 0 | AW80: 0 | AX80: 0 | AY80: 0 | AZ80: 0 | BA80: 0 | BB80: 0 | BC80: 0 | BD80: 0 | BE80: 0 | BF80: 0
A81: =ceiling(sum(J81:BF178)-sum(J81:BF81),1) -> 0 | B81: =ceiling(sum(J81:BF81),1) -> 0 | C81: =sum(E81:H81) -> 0 | D81: 46661 | E81: =sumif($J$19:BF80,E$19,$J81:BF81) -> 0 | F81: =sumif($J$19:BG80,F$19,$J81:BG81) -> 0 | G81: =sumif($J$19:BH80,G$19,$J81:BH81) -> 0 | H81: =sumif($J$19:BI80,H$19,$J81:BI81) -> 0 | I81: =if(D81=DATE(year(today()),month(today()),1),"Current",if(D81>DATE(year(today()),month(today()),1), "Future","Past")) -> Future | AE81: 0 | AF81: 0 | AG81: 0 | AH81: 0 | AI81: 0 | AJ81: 0 | AK81: 0 | AL81: 0 | AM81: 0 | AN81: 0 | AO81: 0 | AP81: 0 | AQ81: 0 | AR81: 0 | AS81: 0 | AT81: 0 | AU81: 0 | AV81: 0 | AW81: 0 | AX81: 0 | AY81: 0 | AZ81: 0 | BA81: 0 | BB81: 0 | BC81: 0 | BD81: 0 | BE81: 0 | BF81: 0
A82: =ceiling(sum(J82:BF179)-sum(J82:BF82),1) -> 0 | B82: =ceiling(sum(J82:BF82),1) -> 0 | C82: =sum(E82:H82) -> 0 | D82: 46692 | E82: =sumif($J$19:BF81,E$19,$J82:BF82) -> 0 | F82: =sumif($J$19:BG81,F$19,$J82:BG82) -> 0 | G82: =sumif($J$19:BH81,G$19,$J82:BH82) -> 0 | H82: =sumif($J$19:BI81,H$19,$J82:BI82) -> 0 | I82: =if(D82=DATE(year(today()),month(today()),1),"Current",if(D82>DATE(year(today()),month(today()),1), "Future","Past")) -> Future | AE82: 0 | AF82: 0 | AG82: 0 | AH82: 0 | AI82: 0 | AJ82: 0 | AK82: 0 | AL82: 0 | AM82: 0 | AN82: 0 | AO82: 0 | AP82: 0 | AQ82: 0 | AR82: 0 | AS82: 0 | AT82: 0 | AU82: 0 | AV82: 0 | AW82: 0 | AX82: 0 | AY82: 0 | AZ82: 0 | BA82: 0 | BB82: 0 | BC82: 0 | BD82: 0 | BE82: 0 | BF82: 0
A83: =ceiling(sum(J83:BF180)-sum(J83:BF83),1) -> 0 | B83: =ceiling(sum(J83:BF83),1) -> 0 | C83: =sum(E83:H83) -> 0 | D83: 46722 | E83: =sumif($J$19:BF82,E$19,$J83:BF83) -> 0 | F83: =sumif($J$19:BG82,F$19,$J83:BG83) -> 0 | G83: =sumif($J$19:BH82,G$19,$J83:BH83) -> 0 | H83: =sumif($J$19:BI82,H$19,$J83:BI83) -> 0 | I83: =if(D83=DATE(year(today()),month(today()),1),"Current",if(D83>DATE(year(today()),month(today()),1), "Future","Past")) -> Future | AE83: 0 | AF83: 0 | AG83: 0 | AH83: 0 | AI83: 0 | AJ83: 0 | AK83: 0 | AL83: 0 | AM83: 0 | AN83: 0 | AO83: 0 | AP83: 0 | AQ83: 0 | AR83: 0 | AS83: 0 | AT83: 0 | AU83: 0 | AV83: 0 | AW83: 0 | AX83: 0 | AY83: 0 | AZ83: 0 | BA83: 0 | BB83: 0 | BC83: 0 | BD83: 0 | BE83: 0 | BF83: 0
A84: =ceiling(sum(J84:BF181)-sum(J84:BF84),1) -> 0 | B84: =ceiling(sum(J84:BF84),1) -> 0 | C84: =sum(E84:H84) -> 0 | D84: 46753 | E84: =sumif($J$19:BF83,E$19,$J84:BF84) -> 0 | F84: =sumif($J$19:BG83,F$19,$J84:BG84) -> 0 | G84: =sumif($J$19:BH83,G$19,$J84:BH84) -> 0 | H84: =sumif($J$19:BI83,H$19,$J84:BI84) -> 0 | I84: =if(D84=DATE(year(today()),month(today()),1),"Current",if(D84>DATE(year(today()),month(today()),1), "Future","Past")) -> Future | AE84: 0 | AF84: 0 | AG84: 0 | AH84: 0 | AI84: 0 | AJ84: 0 | AK84: 0 | AL84: 0 | AM84: 0 | AN84: 0 | AO84: 0 | AP84: 0 | AQ84: 0 | AR84: 0 | AS84: 0 | AT84: 0 | AU84: 0 | AV84: 0 | AW84: 0 | AX84: 0 | AY84: 0 | AZ84: 0 | BA84: 0 | BB84: 0 | BC84: 0 | BD84: 0 | BE84: 0 | BF84: 0
A85: =ceiling(sum(J85:BF182)-sum(J85:BF85),1) -> 0 | B85: =ceiling(sum(J85:BF85),1) -> 0 | C85: =sum(E85:H85) -> 0 | D85: 46784 | E85: =sumif($J$19:BF84,E$19,$J85:BF85) -> 0 | F85: =sumif($J$19:BG84,F$19,$J85:BG85) -> 0 | G85: =sumif($J$19:BH84,G$19,$J85:BH85) -> 0 | H85: =sumif($J$19:BI84,H$19,$J85:BI85) -> 0 | I85: =if(D85=DATE(year(today()),month(today()),1),"Current",if(D85>DATE(year(today()),month(today()),1), "Future","Past")) -> Future | AE85: 0 | AF85: 0 | AG85: 0 | AH85: 0 | AI85: 0 | AJ85: 0 | AK85: 0 | AL85: 0 | AM85: 0 | AN85: 0 | AO85: 0 | AP85: 0 | AQ85: 0 | AR85: 0 | AS85: 0 | AT85: 0 | AU85: 0 | AV85: 0 | AW85: 0 | AX85: 0 | AY85: 0 | AZ85: 0 | BA85: 0 | BB85: 0 | BC85: 0 | BD85: 0 | BE85: 0 | BF85: 0
A86: =ceiling(sum(J86:BF183)-sum(J86:BF86),1) -> 0 | B86: =ceiling(sum(J86:BF86),1) -> 0 | C86: =sum(E86:H86) -> 0 | D86: 46813 | E86: =sumif($J$19:BF85,E$19,$J86:BF86) -> 0 | F86: =sumif($J$19:BG85,F$19,$J86:BG86) -> 0 | G86: =sumif($J$19:BH85,G$19,$J86:BH86) -> 0 | H86: =sumif($J$19:BI85,H$19,$J86:BI86) -> 0 | I86: =if(D86=DATE(year(today()),month(today()),1),"Current",if(D86>DATE(year(today()),month(today()),1), "Future","Past")) -> Future | AE86: 0 | AF86: 0 | AG86: 0 | AH86: 0 | AI86: 0 | AJ86: 0 | AK86: 0 | AL86: 0 | AM86: 0 | AN86: 0 | AO86: 0 | AP86: 0 | AQ86: 0 | AR86: 0 | AS86: 0 | AT86: 0 | AU86: 0 | AV86: 0 | AW86: 0 | AX86: 0 | AY86: 0 | AZ86: 0 | BA86: 0 | BB86: 0 | BC86: 0 | BD86: 0 | BE86: 0 | BF86: 0
A87: =ceiling(sum(J87:BF184)-sum(J87:BF87),1) -> 0 | B87: =ceiling(sum(J87:BF87),1) -> 0 | C87: =sum(E87:H87) -> 0 | D87: 46844 | E87: =sumif($J$19:BF86,E$19,$J87:BF87) -> 0 | F87: =sumif($J$19:BG86,F$19,$J87:BG87) -> 0 | G87: =sumif($J$19:BH86,G$19,$J87:BH87) -> 0 | H87: =sumif($J$19:BI86,H$19,$J87:BI87) -> 0 | I87: =if(D87=DATE(year(today()),month(today()),1),"Current",if(D87>DATE(year(today()),month(today()),1), "Future","Past")) -> Future | AE87: 0 | AF87: 0 | AG87: 0 | AH87: 0 | AI87: 0 | AJ87: 0 | AK87: 0 | AL87: 0 | AM87: 0 | AN87: 0 | AO87: 0 | AP87: 0 | AQ87: 0 | AR87: 0 | AS87: 0 | AT87: 0 | AU87: 0 | AV87: 0 | AW87: 0 | AX87: 0 | AY87: 0 | AZ87: 0 | BA87: 0 | BB87: 0 | BC87: 0 | BD87: 0 | BE87: 0 | BF87: 0
A88: =ceiling(sum(J88:BF185)-sum(J88:BF88),1) -> 0 | B88: =ceiling(sum(J88:BF88),1) -> 0 | C88: =sum(E88:H88) -> 0 | D88: 46874 | E88: =sumif($J$19:BF87,E$19,$J88:BF88) -> 0 | F88: =sumif($J$19:BG87,F$19,$J88:BG88) -> 0 | G88: =sumif($J$19:BH87,G$19,$J88:BH88) -> 0 | H88: =sumif($J$19:BI87,H$19,$J88:BI88) -> 0 | I88: =if(D88=DATE(year(today()),month(today()),1),"Current",if(D88>DATE(year(today()),month(today()),1), "Future","Past")) -> Future | AE88: 0 | AF88: 0 | AG88: 0 | AH88: 0 | AI88: 0 | AJ88: 0 | AK88: 0 | AL88: 0 | AM88: 0 | AN88: 0 | AO88: 0 | AP88: 0 | AQ88: 0 | AR88: 0 | AS88: 0 | AT88: 0 | AU88: 0 | AV88: 0 | AW88: 0 | AX88: 0 | AY88: 0 | AZ88: 0 | BA88: 0 | BB88: 0 | BC88: 0 | BD88: 0 | BE88: 0 | BF88: 0
A89: =ceiling(sum(J89:BF186)-sum(J89:BF89),1) -> 0 | B89: =ceiling(sum(J89:BF89),1) -> 0 | C89: =sum(E89:H89) -> 0 | D89: 46905 | E89: =sumif($J$19:BF88,E$19,$J89:BF89) -> 0 | F89: =sumif($J$19:BG88,F$19,$J89:BG89) -> 0 | G89: =sumif($J$19:BH88,G$19,$J89:BH89) -> 0 | H89: =sumif($J$19:BI88,H$19,$J89:BI89) -> 0 | I89: =if(D89=DATE(year(today()),month(today()),1),"Current",if(D89>DATE(year(today()),month(today()),1), "Future","Past")) -> Future | AE89: 0 | AF89: 0 | AG89: 0 | AH89: 0 | AI89: 0 | AJ89: 0 | AK89: 0 | AL89: 0 | AM89: 0 | AN89: 0 | AO89: 0 | AP89: 0 | AQ89: 0 | AR89: 0 | AS89: 0 | AT89: 0 | AU89: 0 | AV89: 0 | AW89: 0 | AX89: 0 | AY89: 0 | AZ89: 0 | BA89: 0 | BB89: 0 | BC89: 0 | BD89: 0 | BE89: 0 | BF89: 0
A90: =ceiling(sum(J90:BF187)-sum(J90:BF90),1) -> 0 | B90: =ceiling(sum(J90:BF90),1) -> 0 | C90: =sum(E90:H90) -> 0 | D90: 46935 | E90: =sumif($J$19:BF89,E$19,$J90:BF90) -> 0 | F90: =sumif($J$19:BG89,F$19,$J90:BG90) -> 0 | G90: =sumif($J$19:BH89,G$19,$J90:BH90) -> 0 | H90: =sumif($J$19:BI89,H$19,$J90:BI90) -> 0 | I90: =if(D90=DATE(year(today()),month(today()),1),"Current",if(D90>DATE(year(today()),month(today()),1), "Future","Past")) -> Future | AE90: 0 | AF90: 0 | AG90: 0 | AH90: 0 | AI90: 0 | AJ90: 0 | AK90: 0 | AL90: 0 | AM90: 0 | AN90: 0 | AO90: 0 | AP90: 0 | AQ90: 0 | AR90: 0 | AS90: 0 | AT90: 0 | AU90: 0 | AV90: 0 | AW90: 0 | AX90: 0 | AY90: 0 | AZ90: 0 | BA90: 0 | BB90: 0 | BC90: 0 | BD90: 0 | BE90: 0 | BF90: 0
A91: =ceiling(sum(J91:BF188)-sum(J91:BF91),1) -> 0 | B91: =ceiling(sum(J91:BF91),1) -> 0 | C91: =sum(E91:H91) -> 0 | D91: 46966 | E91: =sumif($J$19:BF90,E$19,$J91:BF91) -> 0 | F91: =sumif($J$19:BG90,F$19,$J91:BG91) -> 0 | G91: =sumif($J$19:BH90,G$19,$J91:BH91) -> 0 | H91: =sumif($J$19:BI90,H$19,$J91:BI91) -> 0 | I91: =if(D91=DATE(year(today()),month(today()),1),"Current",if(D91>DATE(year(today()),month(today()),1), "Future","Past")) -> Future | AE91: 0 | AF91: 0 | AG91: 0 | AH91: 0 | AI91: 0 | AJ91: 0 | AK91: 0 | AL91: 0 | AM91: 0 | AN91: 0 | AO91: 0 | AP91: 0 | AQ91: 0 | AR91: 0 | AS91: 0 | AT91: 0 | AU91: 0 | AV91: 0 | AW91: 0 | AX91: 0 | AY91: 0 | AZ91: 0 | BA91: 0 | BB91: 0 | BC91: 0 | BD91: 0 | BE91: 0 | BF91: 0
... A117: =ceiling(sum(J117:BF214)-sum(J117:BF117),1) -> 0 | B117: =ceiling(sum(J117:BF117),1) -> 0 | C117: =sum(E117:H117) -> 0 | D117: 47757 | E117: =sumif($J$19:BF116,E$19,$J117:BF117) -> 0 | F117: =sumif($J$19:BG116,F$19,$J117:BG117) -> 0 | G117: =sumif($J$19:BH116,G$19,$J117:BH117) -> 0 | H117: =sumif($J$19:BI116,H$19,$J117:BI117) -> 0 | I117: =if(D117=DATE(year(today()),month(today()),1),"Current",if(D117>DATE(year(today()),month(today()),1), "Future","Past")) -> Future | AE117: 0 | AF117: 0 | AG117: 0 | AH117: 0 | AI117: 0 | AJ117: 0 | AK117: 0 | AL117: 0 | AM117: 0 | AN117: 0 | AO117: 0 | AP117: 0 | AQ117: 0 | AR117: 0 | AS117: 0 | AT117: 0 | AU117: 0 | AV117: 0 | AW117: 0 | AX117: 0 | AY117: 0 | AZ117: 0 | BA117: 0 | BB117: 0 | BC117: 0 | BD117: 0 | BE117: 0 | BF117: 0

Sheet Projections
B1: 44986 | C1: 45017 | D1: 45047 | E1: 45078 | F1: 45108 | G1: 45139 | H1: 45170 | I1: 45200 | J1: 45231 | K1: 45261 | L1: 45292 | M1: 45323 | N1: 45352 | O1: 45383 | P1: 45413 | Q1: 45444 | R1: 45474 | S1: 45505 | T1: 45536 | U1: 45566 | V1: 45597 | W1: 45627 | X1: 45658 | Y1: 45689 | Z1: 45717 | AA1: 45748 | AB1: 45778 | AC1: 45809 | AD1: 45839 | AE1: 45870 | AF1: 45901 | AG1: 45931 | AH1: 45962 | AI1: 45992 | AJ1: 46023 | AK1: 46054 | AL1: 46082 | AM1: 46113 | AN1: 46143 | AO1: 46174 | AP1: 46204 | AQ1: 46235 | AR1: 46266 | AS1: 46296 | AT1: 46327 | AU1: 46357 | AV1: 46388 | AW1: 46419 | AX1: 46447 | AY1: 46478 | AZ1: 46508 | BA1: 46539 | BB1: 46569 | BC1: 46600 | BD1: 46631 | BE1: 46661 | BF1: 46692 | BG1: 46722 | BH1: 46753 | BI1: 46784 | BJ1: 46813 | BK1: 46844 | BL1: 46874 | BM1: 46905 | BN1: 46935 | BO1: 46966 | BP1: 46997 | BQ1: 47027 | BR1: 47058 | BS1: 47088 | BT1: 47119 | BU1: 47150 | BV1: 47178 | BW1: 47209 | BX1: 47239 | BY1: 47270 | BZ1: 47300 | CA1: 47331 | CB1: 47362 | CC1: 47392 | CD1: 47423 | CE1: 47453 | CF1: 47484 | CG1: 47515 | CH1: 47543 | CI1: 47574 | CJ1: 47604 | CK1: 47635 | CL1: 47665 | CM1: 47696 | CN1: 47727 | CO1: 47757 | CP1: 47788
A2: Increment % | B2: 0 | C2: =(C3-B3)/C3 -> 0.18918919 | D2: =(D3-C3)/D3% -> 0 | E2: =(E3-D3)/E3% -> 0 | F2: =(F3-E3)/F3% -> 0 | G2: =(G3-F3)/G3% -> 0 | H2: =(H3-G3)/H3% -> 0 | I2: =(I3-H3)/I3% -> 0 | J2: =(J3-I3)/J3% -> 0 | K2: =(K3-J3)/K3% -> 0 | ... N2: =(N3-M3)/N3% -> 0 | O2: 0.12 | P2: 0 | Q2: 0 | R2: 0 | S2: 0 | T2: 0 | U2: 0 | V2: 0 | W2: 0 | X2: 0 | Y2: 0 | Z2: 0 | AA2: 0.1 | AB2: =(AB3-AA3)/AB3% -> 7.38627 | AC2: =(AC3-AB3)/AC3% -> 0 | AD2: =(AD3-AC3)/AD3% -> 0 | AE2: =(AE3-AD3)/AE3% -> 0 | AF2: =(AF3-AE3)/AF3% -> 0 | AG2: =(AG3-AF3)/AG3% -> 0 | AH2: =(AH3-AG3)/AH3% -> 0 | AI2: =(AI3-AH3)/AI3% -> 0 | ... AL2: =(AL3-AK3)/AL3% -> 0 | AM2: =(AM3-AL3)/AM3 -> 0.09622042 | AN2: =(AN3-AM3)/AN3% -> 0 | AO2: =(AO3-AN3)/AO3% -> 0 | AP2: =(AP3-AO3)/AP3% -> 0 | AQ2: =(AQ3-AP3)/AQ3% -> 0 | AR2: =(AR3-AQ3)/AR3% -> 0 | AS2: =(AS3-AR3)/AS3% -> 0 | AT2: =(AT3-AS3)/AT3% -> 0 | AU2: =(AU3-AT3)/AU3% -> 0 | ... AX2: =(AX3-AW3)/AX3% -> 0 | AY2: =(AY3-AX3)/AY3 -> 0.095712062 | AZ2: =(AZ3-AY3)/AZ3% -> 0 | BA2: =(BA3-AZ3)/BA3% -> 0 | BB2: =(BB3-BA3)/BB3% -> 0 | BC2: =(BC3-BB3)/BC3% -> 0 | BD2: =(BD3-BC3)/BD3% -> 0 | BE2: =(BE3-BD3)/BE3% -> 0 | BF2: =(BF3-BE3)/BF3% -> 0 | BG2: =(BG3-BF3)/BG3% -> 0 | ... BJ2: =(BJ3-BI3)/BJ3% -> 0 | BK2: =(BK3-BJ3)/BK3 -> 0.095254557 | BL2: =(BL3-BK3)/BL3% -> 0 | BM2: =(BM3-BL3)/BM3% -> 0 | BN2: =(BN3-BM3)/BN3% -> 0 | BO2: =(BO3-BN3)/BO3% -> 0 | BP2: =(BP3-BO3)/BP3% -> 0 | BQ2: =(BQ3-BP3)/BQ3% -> 0 | BR2: =(BR3-BQ3)/BR3% -> 0 | BS2: =(BS3-BR3)/BS3% -> 0 | ... BV2: =(BV3-BU3)/BV3% -> 0 | BW2: =(BW3-BV3)/BW3 -> 0.094842423 | BX2: =(BX3-BW3)/BX3% -> 0 | BY2: =(BY3-BX3)/BY3% -> 0 | BZ2: =(BZ3-BY3)/BZ3% -> 0 | CA2: =(CA3-BZ3)/CA3% -> 0 | CB2: =(CB3-CA3)/CB3% -> 0 | CC2: =(CC3-CB3)/CC3% -> 0 | CD2: =(CD3-CC3)/CD3% -> 0 | CE2: =(CE3-CD3)/CE3% -> 0 | ... CH2: =(CH3-CG3)/CH3% -> 0 | CI2: =(CI3-CH3)/CI3 -> 0.094470837 | CJ2: =(CJ3-CI3)/CJ3% -> 0 | CK2: =(CK3-CJ3)/CK3% -> 0 | CL2: =(CL3-CK3)/CL3% -> 0 | CM2: =(CM3-CL3)/CM3% -> 0 | CN2: =(CN3-CM3)/CN3% -> 0 | CO2: =(CO3-CN3)/CO3% -> 0 | CP2: =(CP3-CO3)/CP3% -> 0
A3: Package | B3: 1500000 | C3: 1850000 | D3: 1850000 | E3: 1850000 | F3: 1850000 | G3: 1850000 | H3: 1850000 | I3: 1850000 | J3: 1850000 | K3: 1850000 | L3: 1850000 | M3: 1850000 | N3: 1850000 | O3: 2099750 | P3: =O3 -> 2099750 | Q3: =P3 -> 2099750 | R3: =Q3 -> 2099750 | S3: =R3 -> 2099750 | T3: =S3 -> 2099750 | U3: =T3 -> 2099750 | V3: =U3 -> 2099750 | W3: =V3 -> 2099750 | ... Z3: =Y3 -> 2099750 | AA3: =AA4*12 -> 2273830 | AB3: =AB4*12 -> 2455175.9 | AC3: =AC4*12 -> 2455175.9 | AD3: =AD4*12 -> 2455175.9 | AE3: =AE4*12 -> 2455175.9 | AF3: =AF4*12 -> 2455175.9 | AG3: =AG4*12 -> 2455175.9 | AH3: =AH4*12 -> 2455175.9 | ... CP3: =CP4*12 -> 4050982
A4: Monthly Before Tax | B4: =B3/12 -> 125000 | C4: =C3/12 -> 154166.67 | D4: =D3/12 -> 154166.67 | E4: =E3/12 -> 154166.67 | F4: =F3/12 -> 154166.67 | G4: =G3/12 -> 154166.67 | H4: =H3/12 -> 154166.67 | I4: =I3/12 -> 154166.67 | ... N4: =N3/12 -> 154166.67 | O4: 172667 | P4: =O4 -> 172667 | Q4: =P4 -> 172667 | R4: =Q4 -> 172667 | S4: =R4 -> 172667 | T4: =S4 -> 172667 | U4: =T4 -> 172667 | V4: =U4 -> 172667 | W4: =V4 -> 172667 | ... Z4: =Y4 -> 172667 | AA4: =AA5+AA8 -> 189485.83 | AB4: =AB5+AB8 -> 204597.99 | AC4: =AC5+AC8 -> 204597.99 | AD4: =AD5+AD8 -> 204597.99 | AE4: =AE5+AE8 -> 204597.99 | AF4: =AF5+AF8 -> 204597.99 | AG4: =AG5+AG8 -> 204597.99 | AH4: =AH5+AH8 -> 204597.99 | ... CP4: =CP5+CP8 -> 337581.83
A5: Tax Deductions | B5: =B4-B8 -> -130 | C5: =C4-C8 -> 55506.667 | D5: =D4-D8 -> 24534.667 | E5: =E4-E8 -> 24534.667 | F5: =F4-F8 -> 24534.667 | G5: =G4-G8 -> 24534.667 | H5: =H4-H8 -> 24534.667 | I5: =I4-I8 -> 24534.667 | ... N5: =N4-N8 -> 24534.667 | O5: 31925 | P5: =O5 -> 31925 | Q5: =P5 -> 31925 | R5: =Q5 -> 31925 | S5: =R5 -> 31925 | T5: =S5 -> 31925 | U5: =T5 -> 31925 | V5: =U5 -> 31925 | W5: =V5 -> 31925 | ... Z5: =Y5 -> 31925 | AA5: =(AA8-Z8)*31%+Z5 -> 34743.83 | AB5: =(AB8-AA8)*31%+AA5 -> 38319.99 | AC5: =(AC8-AB8)*31%+AB5 -> 38319.99 | AD5: =(AD8-AC8)*31%+AC5 -> 38319.99 | AE5: =(AE8-AD8)*31%+AD5 -> 38319.99 | AF5: =(AF8-AE8)*31%+AE5 -> 38319.99 | AG5: =(AG8-AF8)*31%+AF5 -> 38319.99 | AH5: =(AH8-AG8)*31%+AG5 -> 38319.99 | ... CP5: =(CP8-CO8)*31%+CO5 -> 69789.448
A6: Carry Forward (Previous Month) | B6: 3466.81 | C6: =B22 -> 18000 | D6: =C22 -> 24000 | E6: =D22 -> 30000 | F6: =E22 -> 0 | G6: =F22 -> 10800 | H6: =G22 -> 0 | I6: =H22 -> 0 | J6: =I22 -> 0 | K6: =J22 -> 0 | L6: 17592.61 | M6: 18307.73 | N6: 140217.66 | O6: 137106.52 | P6: 143883.23 | Q6: 152410.71 | R6: 157367.16 | S6: 123416.54 | T6: 120331.87 | U6: 76707.13 | V6: =U22 -> 64441.75 | W6: =V22 -> 12282 | X6: =W22 -> 75350.04 | Y6: =X22 -> 86178.85 | Z6: =Y22 -> 136769.87 | AA6: =Z22 -> 148220.83 | AB6: =AA22 -> 38355.87 | AC6: =AB22 -> 4671.78 | ... CP6: =CO22 -> 7254161.5
A7: Increment % | B7: 0 | C7: =(C8-B8)/C8% -> -26.829516 | D7: =(D8-C8)/D8% -> 23.892249 | E7: =(E8-D8)/E8% -> 0 | F7: =(F8-E8)/F8% -> 0 | G7: =(G8-F8)/G8% -> 0 | H7: =(H8-G8)/H8% -> 0 | I7: =(I8-H8)/I8% -> 0 | J7: =(J8-I8)/J8% -> 0 | ... M7: =(M8-L8)/M8% -> 0 | N7: 0 | O7: 0.135 | P7: 0 | Q7: 0 | R7: 0 | S7: 0 | T7: 0 | U7: 0 | V7: 0 | W7: 0 | X7: 0 | Y7: 0 | Z7: 0 | AA7: =(AA8-Z8)/Z8 -> 0.062430913 | AB7: 0 | AC7: 0 | AD7: 0 | AE7: 0 | AF7: 0 | AG7: 0 | AH7: 0 | AI7: 0 | AJ7: 0 | AK7: 0 | AL7: 0 | AM7: 0.1 | AN7: 0 | AO7: 0 | AP7: 0 | AQ7: 0 | AR7: 0 | AS7: 0 | AT7: 0 | AU7: 0 | AV7: 0 | AW7: 0 | AX7: 0 | AY7: 0.1 | AZ7: 0 | BA7: 0 | BB7: 0 | BC7: 0 | BD7: 0 | BE7: 0 | BF7: 0 | BG7: 0 | BH7: 0 | BI7: 0 | BJ7: 0 | BK7: 0.1 | BL7: 0 | BM7: 0 | BN7: 0 | BO7: 0 | BP7: 0 | BQ7: 0 | BR7: 0 | BS7: 0 | BT7: 0 | BU7: 0 | BV7: 0 | BW7: 0.1 | BX7: 0 | BY7: 0 | BZ7: 0 | CA7: 0 | CB7: 0 | CC7: 0 | CD7: 0 | CE7: 0 | CF7: 0 | CG7: 0 | CH7: 0 | CI7: 0.1 | CJ7: 0 | CK7: 0 | CL7: 0 | CM7: 0 | CN7: 0 | CO7: 0 | CP7: 0
A8: Salary Credit | B8: 125130 | C8: 98660 | D8: 129632 | E8: 129632 | F8: 129632 | G8: 129632 | H8: 129632 | I8: 129632 | J8: 129632 | K8: 129632 | L8: 129632 | M8: 129632 | N8: =M8+M8*N7 -> 129632 | O8: 129632 | P8: 161790 | Q8: 143373 | R8: 143373 | S8: 143373 | T8: 145649 | U8: 145649 | V8: 145649 | W8: 145649 | X8: 145649 | Y8: 145649 | Z8: 145649 | AA8: 154742 | AB8: 166278 | AC8: =AB8+AB8*AC7 -> 166278 | AD8: =AC8+AC8*AD7 -> 166278 | AE8: =AD8+AD8*AE7 -> 166278 | AF8: =AE8+AE8*AF7 -> 166278 | AG8: =AF8+AF8*AG7 -> 166278 | AH8: =AG8+AG8*AH7 -> 166278 | AI8: =AH8+AH8*AI7 -> 166278 | AJ8: =AI8+AI8*AJ7 -> 166278 | ... CP8: =CO8+CO8*CP7 -> 267792.38
A9: Laxminarayan FD Amount External | B9: 0 | C9: 0 | D9: 0 | E9: 0 | F9: 0 | G9: 0 | H9: 0 | I9: 0 | J9: 0 | K9: 0 | L9: 17500 | M9: 1000 | N9: 1000 | O9: 1000 | P9: 1000 | Q9: 1000 | R9: =1000+12000+6053 -> 19053 | S9: 0 | T9: 2000 | U9: 0 | V9: 0 | W9: 0 | X9: 0 | Y9: 0 | Z9: 0 | AA9: 0 | AB9: 0 | AC9: 0 | AD9: 0 | AE9: 0 | AF9: 0 | AG9: 0 | AH9: 0 | AI9: 0 | AJ9: 0 | AK9: 0 | AL9: 0 | AM9: 0 | AN9: 0 | AO9: 0 | AP9: 0 | AQ9: 0 | AR9: 0 | AS9: 0 | AT9: 0 | AU9: 0 | AV9: 0 | AW9: 0 | AX9: 0 | AY9: 0 | AZ9: 0 | BA9: 0 | BB9: 0 | BC9: 0 | BD9: 0 | BE9: 0 | BF9: 0 | BG9: 0 | BH9: 0 | BI9: 0 | BJ9: 0 | BK9: 0 | BL9: 0 | BM9: 0 | BN9: 0 | BO9: 0 | BP9: 0 | BQ9: 0 | BR9: 0 | BS9: 0 | BT9: 0 | BU9: 0 | BV9: 0 | BW9: 0 | BX9: 0 | BY9: 0 | BZ9: 0 | CA9: 0 | CB9: 0 | CC9: 0 | CD9: 0 | CE9: 0 | CF9: 0 | CG9: 0 | CH9: 0 | CI9: 0 | CJ9: 0 | CK9: 0 | CL9: 0 | CM9: 0 | CN9: 0 | CO9: 0 | CP9: 0
A10: Srikant Medical Friends Loans External | B10: 0 | C10: 0 | D10: =500 -> 500 | E10: =500 -> 500 | F10: =500 -> 500 | G10: =500+1000 -> 1500 | H10: =500+3000 -> 3500 | I10: =500+3000 -> 3500 | J10: =500+3000 -> 3500 | K10: =500+3000 -> 3500 | L10: =500+3000 -> 3500 | M10: =500+3000 -> 3500 | N10: =500+3000 -> 3500 | O10: =500+3000 -> 3500 | ... R10: =500+3000 -> 3500 | S10: =2120+1000+500 -> 3620 | T10: =1695+1000+1000 -> 3695 | U10: =1195+1000+1000 -> 3195 | V10: =1195+1000+1000 -> 3195 | W10: =1195+1000+1000 -> 3195 | X10: =1195+1000+1000 -> 3195 | Y10: =1195+1000+1000 -> 3195 | Z10: =1195+1200+1000 -> 3395 | AA10: 0 | AB10: 0 | AC10: 0 | AD10: 0 | AE10: 0 | AF10: 0 | AG10: 0 | AH10: 0 | AI10: 0 | AJ10: 0 | AK10: 0 | AL10: 0 | AM10: 0 | AN10: 0 | AO10: 0 | AP10: 0 | AQ10: 0 | AR10: 0 | AS10: 0 | AT10: 0 | AU10: 0 | AV10: 0 | AW10: 0 | AX10: 0 | AY10: 0 | AZ10: 0 | BA10: 0 | BB10: 0 | BC10: 0 | BD10: 0 | BE10: 0 | BF10: 0 | BG10: 0 | BH10: 0 | BI10: 0 | BJ10: 0 | BK10: 0 | BL10: 0 | BM10: 0 | BN10: 0 | BO10: 0 | BP10: 0 | BQ10: 0 | BR10: 0 | BS10: 0 | BT10: 0 | BU10: 0 | BV10: 0 | BW10: 0 | BX10: 0 | BY10: 0 | BZ10: 0 | CA10: 0 | CB10: 0 | CC10: 0 | CD10: 0 | CE10: 0 | CF10: 0 | CG10: 0 | CH10: 0 | CI10: 0 | CJ10: 0 | CK10: 0 | CL10: 0 | CM10: 0 | CN10: 0 | CO10: 0 | CP10: 0
A11: Tutoring | X11: 0 | Y11: 0 | Z11: 0 | AA11: 0 | AB11: =2070.01+672.66+673.18 -> 3415.85 | AC11: =672.2+673.18+673 -> 2018.38 | AD11: 0 | AE11: 0 | AF11: 0 | AG11: 0 | AH11: 0 | AI11: 0 | AJ11: 0 | AK11: 0 | AL11: 0 | AM11: 0 | AN11: 0 | AO11: 0 | AP11: 0 | AQ11: 0 | AR11: 0 | AS11: 0 | AT11: 0 | AU11: 0 | AV11: 0 | AW11: 0 | AX11: 0 | AY11: 0 | AZ11: 0 | BA11: 0 | BB11: 0 | BC11: 0 | BD11: 0 | BE11: 0 | BF11: 0 | BG11: 0 | BH11: 0 | BI11: 0 | BJ11: 0 | BK11: 0 | BL11: 0 | BM11: 0 | BN11: 0 | BO11: 0 | BP11: 0 | BQ11: 0 | BR11: 0 | BS11: 0 | BT11: 0 | BU11: 0 | BV11: 0 | BW11: 0 | BX11: 0 | BY11: 0 | BZ11: 0 | CA11: 0 | CB11: 0 | CC11: 0 | CD11: 0 | CE11: 0 | CF11: 0 | CG11: 0 | CH11: 0 | CI11: 0 | CJ11: 0 | CK11: 0 | CL11: 0 | CM11: 0 | CN11: 0 | CO11: 0 | CP11: 0
A12: MITS Solutions Freelance - Variable | B12: 0 | C12: 0 | D12: 0 | E12: 0 | F12: 0 | G12: 0 | H12: 0 | I12: 0 | J12: 0 | K12: 0 | L12: 0 | M12: 0 | N12: 5200 | O12: =3725+6800+7725+2975 -> 21225 | P12: =2975+4250+1700+1700 -> 10625 | Q12: =1275+2125+850+850 -> 5100 | R12: =850+850+850+2550+6700 -> 11800 | S12: =2250+850 -> 3100 | T12: 0 | U12: 0 | V12: 0 | W12: 0 | X12: 0 | Y12: 0 | Z12: =5300+5.5*850+0.5*1100 -> 10525 | AA12: =9700+4500+6950 -> 21150 | AB12: =5350+2550+1700+2125 -> 11725 | AC12: =850*3/7*365/12 -> 11080.357 | AD12: =850*3/7*365/12 -> 11080.357 | AE12: =850*3/7*365/12 -> 11080.357 | AF12: =850*3/7*365/12 -> 11080.357 | AG12: =850*3/7*365/12 -> 11080.357 | AH12: 2125 | AI12: 0 | AJ12: 0 | AK12: 0 | AL12: 0 | AM12: 0 | AN12: 0 | AO12: 0 | AP12: 0 | AQ12: 0 | AR12: 0 | AS12: 0 | AT12: 0 | AU12: 0 | AV12: 0 | AW12: 0 | AX12: 0 | AY12: 0 | AZ12: 0 | BA12: 0 | BB12: 0 | BC12: 0 | BD12: 0 | BE12: 0 | BF12: 0 | BG12: 0 | BH12: 0 | BI12: 0 | BJ12: 0 | BK12: 0 | BL12: 0 | BM12: 0 | BN12: 0 | BO12: 0 | BP12: 0 | BQ12: 0 | BR12: 0 | BS12: 0 | BT12: 0 | BU12: 0 | BV12: 0 | BW12: 0 | BX12: 0 | BY12: 0 | BZ12: 0 | CA12: 0 | CB12: 0 | CC12: 0 | CD12: 0 | CE12: 0 | CF12: 0 | CG12: 0 | CH12: 0 | CI12: 0 | CJ12: 0 | CK12: 0 | CL12: 0 | CM12: 0 | CN12: 0 | CO12: 0 | CP12: 0
A13: Ishika Freelance Private Freelance - Variable - 45KPM | B13: 0 | C13: 0 | D13: 0 | E13: 0 | F13: 0 | G13: 0 | H13: 0 | I13: 0 | J13: 0 | K13: 0 | L13: 0 | M13: 0 | N13: 0 | O13: =45100+6000+7000 -> 58100 | P13: 45000 | Q13: 50000 | R13: 45000 | S13: 45000 | T13: 45000 | U13: 0 | V13: 0 | W13: 0 | X13: 0 | Y13: 0 | Z13: 0 | AA13: 21000 | AB13: 21095 | AC13: 21145 | AD13: 21547 | AE13: =AVERAGE(AA13:AD13) -> 21196.75 | AF13: =AVERAGE(AB13:AE13) -> 21245.938 | AG13: =AVERAGE(AC13:AF13) -> 21283.672 | AH13: 21885 | AI13: 0 | AJ13: 0 | AK13: 0 | AL13: 0 | AM13: 0 | AN13: 0 | AO13: 0 | AP13: 0 | AQ13: 0 | AR13: 0 | AS13: 0 | AT13: 0 | AU13: 0 | AV13: 0 | AW13: 0 | AX13: 0 | AY13: 0 | AZ13: 0 | BA13: 0 | BB13: 0 | BC13: 0 | BD13: 0 | BE13: 0 | BF13: 0 | BG13: 0 | BH13: 0 | BI13: 0 | BJ13: 0 | BK13: 0 | BL13: 0 | BM13: 0 | BN13: 0 | BO13: 0 | BP13: 0 | BQ13: 0 | BR13: 0 | BS13: 0 | BT13: 0 | BU13: 0 | BV13: 0 | BW13: 0 | BX13: 0 | BY13: 0 | BZ13: 0 | CA13: 0 | CB13: 0 | CC13: 0 | CD13: 0 | CE13: 0 | CF13: 0 | CG13: 0 | CH13: 0 | CI13: 0 | CJ13: 0 | CK13: 0 | CL13: 0 | CM13: 0 | CN13: 0 | CO13: 0 | CP13: 0
A14: Starting Balance | B14: =sum(B6:B13) -> 128596.81 | C14: =sum(C6:C12) -> 116633.17 | D14: =sum(D6:D12) -> 154155.89 | E14: =sum(E6:E12) -> 160132 | F14: =sum(F6:F12) -> 130132 | G14: =sum(G6:G12) -> 141932 | H14: =sum(H6:H12) -> 133132 | I14: =sum(I6:I12) -> 133132 | J14: =sum(J6:J12) -> 133132 | ... N14: =sum(N6:N12) -> 279549.66 | O14: =sum(O6:O12)-O7 -> 292463.52 | P14: =sum(P6:P13) -> 365798.23 | Q14: =sum(Q6:Q13) -> 355383.71 | R14: =sum(R6:R13) -> 380093.16 | S14: =sum(S6:S13) -> 318509.54 | T14: =sum(T6:T13) -> 316675.87 | U14: =sum(U6:U13) -> 225551.13 | V14: =sum(V6:V13) -> 213285.75 | W14: =sum(W6:W13) -> 161126 | ... CP14: =sum(CP6:CP13) -> 7521953.9
A15: Total Salary Credit | B15: =B8+B12+B13+B10 -> 125130 | C15: =C8+C12+C13+C10 -> 98660 | D15: =D8+D12+D13+D10 -> 130132 | E15: =E8+E12+E13+E10 -> 130132 | F15: =F8+F12+F13+F10 -> 130132 | G15: =G8+G12+G13+G10 -> 131132 | H15: =H8+H12+H13+H10 -> 133132 | I15: =I8+I12+I13+I10 -> 133132 | ... R15: =R8+R12+R13+R10 -> 203673 | S15: =S8+S12+S13+S10+S9 -> 195093 | T15: =T8+T12+T13+T10+T9 -> 196344 | U15: =U8+U12+U13+U10+U9 -> 148844 | V15: =V8+V12+V13+V10+V9 -> 148844 | W15: =W8+W12+W13+W10+W9 -> 148844 | X15: =X8+X12+X13+X10+X9 -> 148844 | Y15: =Y8+Y12+Y13+Y10+Y9 -> 148844 | Z15: =Z8+Z12+Z13+Z10+Z9 -> 159569 | AA15: =AA8+AA12+AA13+AA10+AA9 -> 196892 | AB15: =sum(AB8:AB13) -> 202513.85 | AC15: =sum(AC8:AC13) -> 200521.74 | AD15: =sum(AD8:AD13) -> 198905.36 | AE15: =sum(AE8:AE13) -> 198555.11 | AF15: =sum(AF8:AF13) -> 198604.29 | AG15: =sum(AG8:AG13) -> 198642.03 | AH15: =sum(AH8:AH13) -> 190288 | AI15: =sum(AI8:AI13) -> 166278 | ... CP15: =sum(CP8:CP13) -> 267792.38
A16: Start Date | B16: =if(today()<B17,today(),B17) -> 45016 | C16: =if(today()>B17,if(today()<C17,today(),C17),"1 Apr 2023") -> 45046 | D16: =if(today()>C17,if(today()<D17,today(),D17),"1 May 2023") -> 45077 | E16: =if(today()>D17,if(today()<E17,today(),E17),"1 Jun 2023") -> 45107 | F16: =if(today()>E17,if(today()<F17,today(),F17),"1 Jul 2023") -> 45138 | G16: =if(today()>F17,if(today()<G17,today(),G17),"1 Aug 2023") -> 45169 | H16: =if(today()>G17,if(today()<H17,today(),H17),"1 Sep 2023") -> 45199 | I16: =if(today()>H17,if(today()<I17,today(),I17),"1 Oct 2023") -> 45230 | J16: =if(today()>I17,if(today()<J17,today(),J17),"1 Nov 2023") -> 45260 | K16: =if(today()>J17,if(today()<K17,today(),K17),"1 Dec 2023") -> 45291 | L16: 45292 | M16: 45323 | N16: 45352 | O16: 45383 | P16: 45413 | Q16: 45444 | R16: 45474 | S16: 45505 | T16: 45536 | U16: 45566 | V16: 45597 | W16: 45627 | X16: 45658 | Y16: 45689 | Z16: 45717 | AA16: 45748 | AB16: 45778 | AC16: 45809 | AD16: 45839 | AE16: 45870 | AF16: 45901 | AG16: 45931 | AH16: 45962 | AI16: 45992 | AJ16: 46023 | AK16: 46054 | AL16: 46082 | AM16: 46113 | AN16: 46143 | AO16: 46174 | AP16: 46204 | AQ16: 46235 | AR16: 46266 | AS16: 46296 | AT16: 46327 | AU16: 46357 | AV16: 46388 | AW16: 46419 | AX16: 46447 | AY16: 46478 | AZ16: 46508 | BA16: 46539 | BB16: 46569 | BC16: 46600 | BD16: 46631 | BE16: 46661 | BF16: 46692 | BG16: 46722 | BH16: 46753 | BI16: 46784 | BJ16: 46813 | BK16: 46844 | BL16: 46874 | BM16: 46905 | BN16: 46935 | BO16: 46966 | BP16: 46997 | BQ16: 46997 | BR16: 46997 | BS16: 46997 | BT16: 46997 | BU16: 46997 | BV16: 46997 | BW16: 46844 | BX16: 46874 | BY16: 46905 | BZ16: 46905 | CA16: 46844 | CB16: 46874 | CC16: 46905 | CD16: 46905 | CE16: 46844 | CF16: 46874 | CG16: 46905 | CH16: 46905 | CI16: 46844 | CJ16: 46874 | CK16: 46905 | CL16: 46905 | CM16: 46844 | CN16: 46905 | CO16: 46905 | CP16: 46844
A17: End Date | B17: 45016 | C17: 45046 | D17: 45077 | E17: 45107 | F17: 45138 | G17: 45169 | H17: 45199 | I17: 45230 | J17: 45260 | K17: 45291 | L17: 45322 | M17: 45351 | N17: 45382 | O17: 45412 | P17: 45443 | Q17: 45473 | R17: 45504 | S17: 45535 | T17: 45565 | U17: 45596 | V17: 45626 | W17: 45657 | X17: 45688 | Y17: 45716 | Z17: 45747 | AA17: 45777 | AB17: 45808 | AC17: 45838 | AD17: 45869 | AE17: 45900 | AF17: 45930 | AG17: 45961 | AH17: 45991 | AI17: 46022 | AJ17: 46053 | AK17: 46081 | AL17: 46112 | AM17: 46142 | AN17: 46173 | AO17: 46203 | AP17: 46234 | AQ17: 46265 | AR17: 46295 | AS17: 46326 | AT17: 46356 | AU17: 46387 | AV17: 46418 | AW17: 46446 | AX17: 46477 | AY17: 46507 | AZ17: 46538 | BA17: 46568 | BB17: 46599 | BC17: 46630 | BD17: 46660 | BE17: 46691 | BF17: 46721 | BG17: 46752 | BH17: 46783 | BI17: 46812 | BJ17: 46843 | BK17: 46873 | BL17: 46904 | BM17: 46934 | BN17: 46965 | BO17: 46996 | BP17: 47026 | BQ17: 47026 | BR17: 47026 | BS17: 47026 | BT17: 47026 | BU17: 47026 | BV17: 47026 | BW17: 46873 | BX17: 46904 | BY17: 46934 | BZ17: 46934 | CA17: 46873 | CB17: 46904 | CC17: 46934 | CD17: 46934 | CE17: 46873 | CF17: 46904 | CG17: 46934 | CH17: 46934 | CI17: 46873 | CJ17: 46904 | CK17: 46934 | CL17: 46934 | CM17: 46873 | CN17: 46934 | CO17: 46934 | CP17: 46873
A18: Remaining Days | B18: =if( today()>B17,0,days(B17,B16)+1) -> 0 | C18: =if( today()>C17,0,days(C17,C16)+1) -> 0 | D18: =if( today()>D17,0,days(D17,D16)+1) -> 0 | E18: =if( today()>E17,0,days(E17,E16)+1) -> 0 | F18: =if( today()>F17,0,days(F17,F16)+1) -> 0 | G18: =if( today()>G17,0,days(G17,G16)+1) -> 0 | H18: =if( today()>H17,0,days(H17,H16)+1) -> 0 | I18: =if( today()>I17,0,days(I17,I16)+1) -> 0 | ... CP18: =if( today()>CP17,0,days(CP17,CP16)+1) -> 30
A19: Remaining Total Usable Balance | B19: 0 | C19: 0 | D19: 0 | E19: 0 | F19: 0 | G19: 0 | H19: 0 | I19: 0 | J19: 0 | K19: 0 | L19: 0 | M19: 0 | N19: 0 | O19: 0 | P19: 0 | Q19: 0 | R19: 0 | S19: 0 | T19: 0 | U19: ='Planned Expenses'!A294 -> 35441.75 | V19: ='Planned Expenses'!A305 -> 12282 | W19: ='Planned Expenses'!A316 -> 75350.04 | X19: ='Planned Expenses'!A327 -> 86178.85 | Y19: ='Planned Expenses'!A338 -> 136769.87 | Z19: ='Planned Expenses'!A349 -> 148220.83 | AA19: ='Planned Expenses'!A360 -> 38355.87 | AB19: ='Planned Expenses'!A371 -> 4671.78 | AC19: ='Planned Expenses'!A382 -> 0 | AD19: ='Planned Expenses'!A393 -> 54732.34 | AE19: ='Planned Expenses'!A404 -> 67019.95 | AF19: ='Planned Expenses'!A415 -> 11649.34 | AG19: ='Planned Expenses'!A426 -> 13113.85 | AH19: ='Planned Expenses'!A437 -> 31041 | AI19: ='Planned Expenses'!A448 -> 87280.32 | AJ19: ='Planned Expenses'!A459 -> 141543.64 | AK19: ='Planned Expenses'!A470 -> 199420.89 | AL19: ='Planned Expenses'!A481 -> 250793.14 | AM19: ='Planned Expenses'!A492 -> 317298.29 | AN19: ='Planned Expenses'!A503 -> 387301.34 | AO19: ='Planned Expenses'!A514 -> 421281.02 | AP19: ='Planned Expenses'!A525 -> 492461.7 | AQ19: ='Planned Expenses'!A536 -> 563441.38 | AR19: ='Planned Expenses'!A547 -> 632921.06 | AS19: ='Planned Expenses'!A558 -> 692126.13 | AT19: ='Planned Expenses'!A569 -> 764698.09 | AU19: ='Planned Expenses'!A580 -> 835770.05 | AV19: ='Planned Expenses'!A591 -> 919186.41 | AW19: ='Planned Expenses'!A602 -> 996102.77 | AX19: ='Planned Expenses'!A613 -> 1048648.2 | AY19: ='Planned Expenses'!A624 -> 1148341.7 | AZ19: ='Planned Expenses'!A635 -> 1246535.1 | BA19: ='Planned Expenses'!A646 -> 1343228.5 | BB19: ='Planned Expenses'!A657 -> 1437121.8 | BC19: ='Planned Expenses'!A668 -> 1530815.2 | BD19: ='Planned Expenses'!A679 -> 1628008.6 | BE19: ='Planned Expenses'!A690 -> 1708976 | BF19: ='Planned Expenses'!A701 -> 1803169.4 | BG19: ='Planned Expenses'!A712 -> 1890862.7 | BH19: ='Planned Expenses'!A723 -> 1981556.1 | BI19: ='Planned Expenses'!A734 -> 2070749.5 | BJ19: ='Planned Expenses'!A745 -> 2153442.9 | BK19: ='Planned Expenses'!A756 -> 2275333 | BL19: ='Planned Expenses'!A767 -> 2395723 | BM19: ='Planned Expenses'!A778 -> 2514613 | BN19: ='Planned Expenses'!A789 -> 2630703.1 | BO19: ='Planned Expenses'!A800 -> 2746593.1 | BP19: ='Planned Expenses'!A811 -> 2860983.1 | BQ19: ='Planned Expenses'!A822 -> 2954175.1 | BR19: ='Planned Expenses'!A833 -> 3074855.1 | BS19: ='Planned Expenses'!A844 -> 3194035.1 | BT19: ='Planned Expenses'!A855 -> 3311215.2 | BU19: ='Planned Expenses'!A866 -> 3426895.2 | BV19: ='Planned Expenses'!A877 -> 3541075.2 | BW19: ='Planned Expenses'!A888 -> 3670886.9 | BX19: ='Planned Expenses'!A899 -> 3804198.5 | BY19: ='Planned Expenses'!A910 -> 3936010.2 | BZ19: ='Planned Expenses'!A921 -> 4065021.8 | CA19: ='Planned Expenses'!A932 -> 4189333.4 | CB19: ='Planned Expenses'!A943 -> 4333145 | CC19: ='Planned Expenses'!A954 -> 4461230.6 | CD19: ='Planned Expenses'!A965 -> 4603042.3 | CE19: ='Planned Expenses'!A976 -> 4743853.9 | CF19: ='Planned Expenses'!A987 -> 4883165.5 | CG19: ='Planned Expenses'!A998 -> 5021477.1 | CH19: ='Planned Expenses'!A1009 -> 5158788.7 | CI19: ='Planned Expenses'!A1020 -> 5321917.2 | CJ19: ='Planned Expenses'!A1031 -> 5478545.6 | CK19: ='Planned Expenses'!A1042 -> 5633674 | CL19: ='Planned Expenses'!A1053 -> 5791002.4 | CM19: ='Planned Expenses'!A1064 -> 5948130.7 | CN19: ='Planned Expenses'!A1075 -> 6104259.1 | CO19: ='Planned Expenses'!A1086 -> 6244661.5 | CP19: ='Planned Expenses'!A1097 -> 6411559.9
A20: Unused Expense Balance Carryforward | B20: =sum('Planned Expenses'!D32) -> 0 | C20: 0 | D20: 0 | E20: 0 | F20: 0 | G20: 0 | H20: 0 | I20: 0 | J20: 0 | K20: 0 | L20: 0 | M20: 0 | N20: 0 | O20: 0 | P20: 0 | Q20: 0 | R20: 0 | S20: 0 | T20: 0 | U20: 0 | V20: 0 | W20: 0 | X20: 0 | Y20: 0 | Z20: 0 | AA20: 0 | AB20: 0 | AC20: 0 | AD20: 0 | AE20: 0 | AF20: 0 | AG20: 0 | AH20: 0 | AI20: 0 | AJ20: 0 | AK20: 0 | AL20: 0 | AM20: 0 | AN20: 0 | AO20: 0 | AP20: 0 | AQ20: 0 | AR20: 0 | AS20: 0 | AT20: 0 | AU20: 0 | AV20: 0 | AW20: 0 | AX20: 0 | AY20: 0 | AZ20: 0 | BA20: 0 | BB20: 0 | BC20: 0 | BD20: 0 | BE20: 0 | BF20: 0 | BG20: 0 | BH20: 0 | BI20: 0 | BJ20: 0 | BK20: 0 | BL20: 0 | BM20: 0 | BN20: 0 | BO20: 0 | BP20: 0 | BQ20: 0 | BR20: 0 | BS20: 0 | BT20: 0 | BU20: 0 | BV20: 0 | BW20: 0 | BX20: 0 | BY20: 0 | BZ20: 0 | CA20: 0 | CB20: 0 | CC20: 0 | CD20: 0 | CE20: 0 | CF20: 0 | CG20: 0 | CH20: 0 | CI20: 0 | CJ20: 0 | CK20: 0 | CL20: 0 | CM20: 0 | CN20: 0 | CO20: 0 | CP20: 0
A21: Planned Fixed Balances | B21: ='Planned Expenses'!B32 -> 18000 | C21: ='Planned Expenses'!B47 -> 24000 | D21: ='Planned Expenses'!B62 -> 30000 | E21: ='Planned Expenses'!B78 -> 0 | F21: ='Planned Expenses'!B93 -> 10800 | G21: ='Planned Expenses'!B108 -> 0 | H21: 0 | I21: 0 | J21: 0 | K21: 0 | L21: 0 | M21: 0 | N21: 0 | O21: 0 | P21: 0 | Q21: 0 | R21: 0 | S21: 0 | T21: 0 | U21: ='Planned Expenses'!B294 -> 29000 | V21: ='Planned Expenses'!B305 -> 0 | W21: ='Planned Expenses'!B316 -> 0 | X21: ='Planned Expenses'!B327 -> 0 | Y21: ='Planned Expenses'!B338 -> 0 | Z21: ='Planned Expenses'!B349 -> 0 | AA21: ='Planned Expenses'!B360 -> 0 | AB21: ='Planned Expenses'!B371 -> 0 | AC21: ='Planned Expenses'!B382 -> 0 | AD21: ='Planned Expenses'!B393 -> 0 | AE21: ='Planned Expenses'!B404 -> 0 | AF21: ='Planned Expenses'!B415 -> 0 | AG21: ='Planned Expenses'!B426 -> 13000 | AH21: ='Planned Expenses'!B437 -> 24500 | AI21: ='Planned Expenses'!B448 -> 27500 | AJ21: ='Planned Expenses'!B459 -> 31000 | AK21: ='Planned Expenses'!B470 -> 35000 | AL21: ='Planned Expenses'!B481 -> 39500 | AM21: ='Planned Expenses'!B492 -> 44500 | AN21: ='Planned Expenses'!B503 -> 50000 | AO21: ='Planned Expenses'!B514 -> 56000 | AP21: ='Planned Expenses'!B525 -> 62500 | AQ21: ='Planned Expenses'!B536 -> 69500 | AR21: ='Planned Expenses'!B547 -> 77000 | AS21: ='Planned Expenses'!B558 -> 85000 | AT21: ='Planned Expenses'!B569 -> 93500 | AU21: ='Planned Expenses'!B580 -> 102500 | AV21: ='Planned Expenses'!B591 -> 112000 | AW21: ='Planned Expenses'!B602 -> 122000 | AX21: ='Planned Expenses'!B613 -> 132500 | AY21: ='Planned Expenses'!B624 -> 143500 | AZ21: ='Planned Expenses'!B635 -> 155000 | BA21: ='Planned Expenses'!B646 -> 167000 | BB21: ='Planned Expenses'!B657 -> 179500 | BC21: ='Planned Expenses'!B668 -> 192500 | BD21: ='Planned Expenses'!B679 -> 206000 | BE21: ='Planned Expenses'!B690 -> 220000 | BF21: ='Planned Expenses'!B701 -> 234500 | BG21: ='Planned Expenses'!B712 -> 249500 | BH21: ='Planned Expenses'!B723 -> 265000 | BI21: ='Planned Expenses'!B734 -> 281000 | BJ21: ='Planned Expenses'!B745 -> 297500 | BK21: ='Planned Expenses'!B756 -> 314500 | BL21: ='Planned Expenses'!B767 -> 332000 | BM21: ='Planned Expenses'!B778 -> 350000 | BN21: ='Planned Expenses'!B789 -> 368500 | BO21: ='Planned Expenses'!B800 -> 387500 | BP21: ='Planned Expenses'!B811 -> 407000 | BQ21: ='Planned Expenses'!B822 -> 427000 | BR21: ='Planned Expenses'!B833 -> 447500 | BS21: ='Planned Expenses'!B844 -> 468500 | BT21: ='Planned Expenses'!B855 -> 490000 | BU21: ='Planned Expenses'!B866 -> 512000 | BV21: ='Planned Expenses'!B877 -> 534500 | BW21: ='Planned Expenses'!B888 -> 557500 | BX21: ='Planned Expenses'!B899 -> 581000 | BY21: ='Planned Expenses'!B910 -> 605000 | BZ21: ='Planned Expenses'!B921 -> 629500 | CA21: ='Planned Expenses'!B932 -> 654000 | CB21: ='Planned Expenses'!B943 -> 678500 | CC21: ='Planned Expenses'!B954 -> 703000 | CD21: ='Planned Expenses'!B965 -> 727500 | CE21: ='Planned Expenses'!B976 -> 752000 | CF21: ='Planned Expenses'!B987 -> 776500 | CG21: ='Planned Expenses'!B998 -> 801000 | CH21: ='Planned Expenses'!B1009 -> 825500 | CI21: ='Planned Expenses'!B1020 -> 850500 | CJ21: ='Planned Expenses'!B1031 -> 876000 | CK21: ='Planned Expenses'!B1042 -> 902000 | CL21: ='Planned Expenses'!B1053 -> 928500 | CM21: ='Planned Expenses'!B1064 -> 955500 | CN21: ='Planned Expenses'!B1075 -> 982500 | CO21: ='Planned Expenses'!B1086 -> 1009500 | CP21: ='Planned Expenses'!B1097 -> 1036500
A22: Final Carry Forward | B22: =sum(B19:B21) -> 18000 | C22: =sum(C19:C21) -> 24000 | D22: =sum(D19:D21) -> 30000 | E22: =sum(E19:E21) -> 0 | F22: =sum(F19:F21) -> 10800 | G22: =sum(G19:G21) -> 0 | H22: =sum(H19:H21) -> 0 | I22: =sum(I19:I21) -> 0 | ... CP22: =sum(CP19:CP21) -> 7448059.9

Sheet Bills - Loans
D1: =sum(H1:K1) -> 0 | G1: Balance
B2: 4173.59 | G2: Subject | H2: Car Loan | I2: MoneyView Loan | J2: Cred | K2: Bajaj Salaried Loan | L2: Axis Personal Loan | M2: Axis Personal Loan | N2: Fibe | O2: Ruppek Gold Loan
B3: 271.28 | G3: Merchant Name | H3: Citroen | I3: Money View | J3: Cred | K3: Bajaj | L3: Axis | M3: Axis | N3: Axis
B4: 145822.76 | G4: Original Amount | I4: 300000 | J4: 500000 | K4: 692275 | L4: 134000 | M4: 750000 | N4: 134000
G5: Tenure
G6: EMI Amt With Interest
G7: Pending EMI
B8: 45383 | G8: 1st EMI | H8: 45231 | I8: 45018 | J8: 45018 | K8: 45018
G9: Last EMI | H9: 47757 | I9: 46814 | J9: 46814 | K9: 46814
G10: Status Of EMI Transaction
G11: Monthly Interest
B12: 224954 | G12: Remaining Amount | H12: =SUMIFS(H20:H117,$D20:$D117,">"&#REF!) -> 0 | I12: =SUMIFS(I20:I117,$D20:$D117,">"&#REF!) -> 0 | J12: =SUMIFS(J20:J117,$D20:$D117,">"&#REF!) -> 0 | K12: =SUMIFS(K20:K117,$D20:$D117,">"&#REF!) -> 0 | L12: 60 | M12: =SUMIFS(M20:M117,$D20:$D117,">"&#REF!) -> 0 | N12: 60
G13: Remaining EMIs | H13: =COUNTIFs(H20:H117,">"&0,$D20:$D117,">"&#REF!) -> 0 | I13: 48 | J13: 48 | K13: =COUNTIFs(K20:K117,">"&0,$D20:$D117,">"&#REF!) -> 0 | L13: 60 | M13: =COUNTIFs(M20:M117,">"&0,$D20:$D117,">"&#REF!) -> 0 | N13: 60
G14: Today
G15: Principal
G16: Interest
G17: GST 18%
E18: =sum(E20:E117) -> 1197824 | F18: =sum(F20:F117) -> 1729874 | G18: Total EMI | H18: 12770 | I18: 9290 | J18: 9290 | K18: 15577 | L18: 2972 | M18: 1674 | N18: 7000 | O18: 2500
A19: Remaining Loan Amount | B19: Total EMIs | C19: CC EMIs | D19: =sumif(G20:G117,"Future",B20:B117) -> 2366752 | E19: Axis A/C 0370 | F19: ICICI A/C 3945 | G19: Card | H19: Axis A/C 0370 | I19: ICICI A/C 3945 | J19: ICICI A/C 3945 | K19: ICICI A/C 3945 | L19: Axis A/C 0370 | M19: Axis A/C 0370 | N19: ICICI A/C 3945 | O19: ICICI A/C 3945
A20: =ceiling(sum(H20:O117)-sum(H20:O20),1) -> 3253773 | B20: =ceiling(sum(H20:O20),1) -> 5900 | C20: =sum(E20:F20) -> 5900 | D20: 44805 | E20: =sumif($H$19:O19,E$19,$H20:O20) -> 5900 | F20: =sumif($H$19:P19,F$19,$H20:P20) -> 0 | G20: =if(D20=DATE(year(today()),month(today()),1),"Current",if(D20>DATE(year(today()),month(today()),1), "Future","Past")) -> Past | M20: 5900
A21: =ceiling(sum(H21:O118)-sum(H21:O21),1) -> 3247873 | B21: =ceiling(sum(H21:O21),1) -> 5900 | C21: =sum(E21:F21) -> 5900 | D21: 44835 | E21: =sumif($H$19:O20,E$19,$H21:O21) -> 5900 | F21: =sumif($H$19:P20,F$19,$H21:P21) -> 0 | G21: =if(D21=DATE(year(today()),month(today()),1),"Current",if(D21>DATE(year(today()),month(today()),1), "Future","Past")) -> Past | M21: 5900
A22: =ceiling(sum(H22:O119)-sum(H22:O22),1) -> 3241973 | B22: =ceiling(sum(H22:O22),1) -> 5900 | C22: =sum(E22:F22) -> 5900 | D22: 44866 | E22: =sumif($H$19:O21,E$19,$H22:O22) -> 5900 | F22: =sumif($H$19:P21,F$19,$H22:P22) -> 0 | G22: =if(D22=DATE(year(today()),month(today()),1),"Current",if(D22>DATE(year(today()),month(today()),1), "Future","Past")) -> Past | M22: 5900
A23: =ceiling(sum(H23:O120)-sum(H23:O23),1) -> 3236073 | B23: =ceiling(sum(H23:O23),1) -> 5900 | C23: =sum(E23:F23) -> 5900 | D23: 44896 | E23: =sumif($H$19:O22,E$19,$H23:O23) -> 5900 | F23: =sumif($H$19:P22,F$19,$H23:P23) -> 0 | G23: =if(D23=DATE(year(today()),month(today()),1),"Current",if(D23>DATE(year(today()),month(today()),1), "Future","Past")) -> Past | M23: 5900
A24: =ceiling(sum(H24:O121)-sum(H24:O24),1) -> 3230173 | B24: =ceiling(sum(H24:O24),1) -> 5900 | C24: =sum(E24:F24) -> 5900 | D24: 44927 | E24: =sumif($H$19:O23,E$19,$H24:O24) -> 5900 | F24: =sumif($H$19:P23,F$19,$H24:P24) -> 0 | G24: =if(D24=DATE(year(today()),month(today()),1),"Current",if(D24>DATE(year(today()),month(today()),1), "Future","Past")) -> Past | M24: 5900
A25: =ceiling(sum(H25:O122)-sum(H25:O25),1) -> 3224273 | B25: =ceiling(sum(H25:O25),1) -> 5900 | C25: =sum(E25:F25) -> 5900 | D25: 44958 | E25: =sumif($H$19:O24,E$19,$H25:O25) -> 5900 | F25: =sumif($H$19:P24,F$19,$H25:P25) -> 0 | G25: =if(D25=DATE(year(today()),month(today()),1),"Current",if(D25>DATE(year(today()),month(today()),1), "Future","Past")) -> Past | M25: 5900
A26: =ceiling(sum(H26:O123)-sum(H26:O26),1) -> 3218373 | B26: =ceiling(sum(H26:O26),1) -> 5900 | C26: =sum(E26:F26) -> 5900 | D26: 44986 | E26: =sumif($H$19:O25,E$19,$H26:O26) -> 5900 | F26: =sumif($H$19:P25,F$19,$H26:P26) -> 0 | G26: =if(D26=DATE(year(today()),month(today()),1),"Current",if(D26>DATE(year(today()),month(today()),1), "Future","Past")) -> Past | M26: 5900
A27: =ceiling(sum(H27:O124)-sum(H27:O27),1) -> 3196896 | B27: =ceiling(sum(H27:O27),1) -> 21477 | C27: =sum(E27:F27) -> 21477 | D27: 45017 | E27: =sumif($H$19:O26,E$19,$H27:O27) -> 5900 | F27: =sumif($H$19:P26,F$19,$H27:P27) -> 15577 | G27: =if(D27=DATE(year(today()),month(today()),1),"Current",if(D27>DATE(year(today()),month(today()),1), "Future","Past")) -> Past | K27: =K$18 -> 15577 | M27: 5900
A28: =ceiling(sum(H28:O125)-sum(H28:O28),1) -> 3175419 | B28: =ceiling(sum(H28:O28),1) -> 21477 | C28: =sum(E28:F28) -> 21477 | D28: 45047 | E28: =sumif($H$19:O27,E$19,$H28:O28) -> 5900 | F28: =sumif($H$19:P27,F$19,$H28:P28) -> 15577 | G28: =if(D28=DATE(year(today()),month(today()),1),"Current",if(D28>DATE(year(today()),month(today()),1), "Future","Past")) -> Past | K28: =K$18 -> 15577 | M28: 5900
A29: =ceiling(sum(H29:O126)-sum(H29:O29),1) -> 3153942 | B29: =ceiling(sum(H29:O29),1) -> 21477 | C29: =sum(E29:F29) -> 21477 | D29: 45078 | E29: =sumif($H$19:O28,E$19,$H29:O29) -> 5900 | F29: =sumif($H$19:P28,F$19,$H29:P29) -> 15577 | G29: =if(D29=DATE(year(today()),month(today()),1),"Current",if(D29>DATE(year(today()),month(today()),1), "Future","Past")) -> Past | K29: =K$18 -> 15577 | M29: 5900
A30: =ceiling(sum(H30:O127)-sum(H30:O30),1) -> 3132465 | B30: =ceiling(sum(H30:O30),1) -> 21477 | C30: =sum(E30:F30) -> 21477 | D30: 45108 | E30: =sumif($H$19:O29,E$19,$H30:O30) -> 5900 | F30: =sumif($H$19:P29,F$19,$H30:P30) -> 15577 | G30: =if(D30=DATE(year(today()),month(today()),1),"Current",if(D30>DATE(year(today()),month(today()),1), "Future","Past")) -> Past | K30: =K$18 -> 15577 | M30: 5900
A31: =ceiling(sum(H31:O128)-sum(H31:O31),1) -> 3110988 | B31: =ceiling(sum(H31:O31),1) -> 21477 | C31: =sum(E31:F31) -> 21477 | D31: 45139 | E31: =sumif($H$19:O30,E$19,$H31:O31) -> 5900 | F31: =sumif($H$19:P30,F$19,$H31:P31) -> 15577 | G31: =if(D31=DATE(year(today()),month(today()),1),"Current",if(D31>DATE(year(today()),month(today()),1), "Future","Past")) -> Past | K31: =K$18 -> 15577 | M31: 5900
A32: =ceiling(sum(H32:O129)-sum(H32:O32),1) -> 3089511 | B32: =ceiling(sum(H32:O32),1) -> 21477 | C32: =sum(E32:F32) -> 21477 | D32: 45170 | E32: =sumif($H$19:O31,E$19,$H32:O32) -> 5900 | F32: =sumif($H$19:P31,F$19,$H32:P32) -> 15577 | G32: =if(D32=DATE(year(today()),month(today()),1),"Current",if(D32>DATE(year(today()),month(today()),1), "Future","Past")) -> Past | K32: =K$18 -> 15577 | M32: 5900
A33: =ceiling(sum(H33:O130)-sum(H33:O33),1) -> 3068034 | B33: =ceiling(sum(H33:O33),1) -> 21477 | C33: =sum(E33:F33) -> 21477 | D33: 45200 | E33: =sumif($H$19:O32,E$19,$H33:O33) -> 5900 | F33: =sumif($H$19:P32,F$19,$H33:P33) -> 15577 | G33: =if(D33=DATE(year(today()),month(today()),1),"Current",if(D33>DATE(year(today()),month(today()),1), "Future","Past")) -> Past | K33: =K$18 -> 15577 | M33: 5900
A34: =ceiling(sum(H34:O131)-sum(H34:O34),1) -> 3033787 | B34: =ceiling(sum(H34:O34),1) -> 34247 | C34: =sum(E34:F34) -> 34247 | D34: 45231 | E34: =sumif($H$19:O33,E$19,$H34:O34) -> 18670 | F34: =sumif($H$19:P33,F$19,$H34:P34) -> 15577 | G34: =if(D34=DATE(year(today()),month(today()),1),"Current",if(D34>DATE(year(today()),month(today()),1), "Future","Past")) -> Past | H34: =H$18 -> 12770 | K34: =K$18 -> 15577 | M34: 5900
A35: =ceiling(sum(H35:O132)-sum(H35:O35),1) -> 2999540 | B35: =ceiling(sum(H35:O35),1) -> 34247 | C35: =sum(E35:F35) -> 34247 | D35: 45261 | E35: =sumif($H$19:O34,E$19,$H35:O35) -> 18670 | F35: =sumif($H$19:P34,F$19,$H35:P35) -> 15577 | G35: =if(D35=DATE(year(today()),month(today()),1),"Current",if(D35>DATE(year(today()),month(today()),1), "Future","Past")) -> Past | H35: =H$18 -> 12770 | K35: =K$18 -> 15577 | M35: 5900
A36: =ceiling(sum(H36:O133)-sum(H36:O36),1) -> 2965293 | B36: =ceiling(sum(H36:O36),1) -> 34247 | C36: =sum(E36:F36) -> 34247 | D36: 45292 | E36: =sumif($H$19:O35,E$19,$H36:O36) -> 18670 | F36: =sumif($H$19:P35,F$19,$H36:P36) -> 15577 | G36: =if(D36=DATE(year(today()),month(today()),1),"Current",if(D36>DATE(year(today()),month(today()),1), "Future","Past")) -> Past | H36: =H$18 -> 12770 | K36: =K$18 -> 15577 | M36: 5900
A37: =ceiling(sum(H37:O134)-sum(H37:O37),1) -> 2931046 | B37: =ceiling(sum(H37:O37),1) -> 34247 | C37: =sum(E37:F37) -> 34247 | D37: 45323 | E37: =sumif($H$19:O36,E$19,$H37:O37) -> 18670 | F37: =sumif($H$19:P36,F$19,$H37:P37) -> 15577 | G37: =if(D37=DATE(year(today()),month(today()),1),"Current",if(D37>DATE(year(today()),month(today()),1), "Future","Past")) -> Past | H37: =H$18 -> 12770 | K37: =K$18 -> 15577 | M37: 5900
A38: =ceiling(sum(H38:O135)-sum(H38:O38),1) -> 2896799 | B38: =ceiling(sum(H38:O38),1) -> 34247 | C38: =sum(E38:F38) -> 34247 | D38: 45352 | E38: =sumif($H$19:O37,E$19,$H38:O38) -> 18670 | F38: =sumif($H$19:P37,F$19,$H38:P38) -> 15577 | G38: =if(D38=DATE(year(today()),month(today()),1),"Current",if(D38>DATE(year(today()),month(today()),1), "Future","Past")) -> Past | H38: =H$18 -> 12770 | K38: =K$18 -> 15577 | M38: 5900
A39: =ceiling(sum(H39:O136)-sum(H39:O39),1) -> 2862552 | B39: =ceiling(sum(H39:O39),1) -> 34247 | C39: =sum(E39:F39) -> 34247 | D39: 45383 | E39: =sumif($H$19:O38,E$19,$H39:O39) -> 18670 | F39: =sumif($H$19:P38,F$19,$H39:P39) -> 15577 | G39: =if(D39=DATE(year(today()),month(today()),1),"Current",if(D39>DATE(year(today()),month(today()),1), "Future","Past")) -> Past | H39: =H$18 -> 12770 | K39: =K$18 -> 15577 | M39: 5900
A40: =ceiling(sum(H40:O137)-sum(H40:O40),1) -> 2832531 | B40: =ceiling(sum(H40:O40),1) -> 30021 | C40: =sum(E40:F40) -> 30021 | D40: 45413 | E40: =sumif($H$19:O39,E$19,$H40:O40) -> 14444 | F40: =sumif($H$19:P39,F$19,$H40:P40) -> 15577 | G40: =if(D40=DATE(year(today()),month(today()),1),"Current",if(D40>DATE(year(today()),month(today()),1), "Future","Past")) -> Past | H40: =H$18 -> 12770 | K40: =K$18 -> 15577 | M40: =M$18 -> 1674
A41: =ceiling(sum(H41:O138)-sum(H41:O41),1) -> 2802510 | B41: =ceiling(sum(H41:O41),1) -> 30021 | C41: =sum(E41:F41) -> 30021 | D41: 45444 | E41: =sumif($H$19:O40,E$19,$H41:O41) -> 14444 | F41: =sumif($H$19:P40,F$19,$H41:P41) -> 15577 | G41: =if(D41=DATE(year(today()),month(today()),1),"Current",if(D41>DATE(year(today()),month(today()),1), "Future","Past")) -> Past | H41: =H$18 -> 12770 | K41: =K$18 -> 15577 | M41: =M$18 -> 1674
A42: =ceiling(sum(H42:O139)-sum(H42:O42),1) -> 2772489 | B42: =ceiling(sum(H42:O42),1) -> 30021 | C42: =sum(E42:F42) -> 30021 | D42: 45474 | E42: =sumif($H$19:O41,E$19,$H42:O42) -> 14444 | F42: =sumif($H$19:P41,F$19,$H42:P42) -> 15577 | G42: =if(D42=DATE(year(today()),month(today()),1),"Current",if(D42>DATE(year(today()),month(today()),1), "Future","Past")) -> Past | H42: =H$18 -> 12770 | K42: =K$18 -> 15577 | M42: =M$18 -> 1674
A43: =ceiling(sum(H43:O140)-sum(H43:O43),1) -> 2743324 | B43: =ceiling(sum(H43:O43),1) -> 29165 | C43: =sum(E43:F43) -> 29165 | D43: 45505 | E43: =sumif($H$19:O42,E$19,$H43:O43) -> 13588 | F43: =sumif($H$19:P42,F$19,$H43:P43) -> 15577 | G43: =if(D43=DATE(year(today()),month(today()),1),"Current",if(D43>DATE(year(today()),month(today()),1), "Future","Past")) -> Past | H43: =H$18 -> 12770 | K43: =K$18 -> 15577 | M43: 818
A44: =ceiling(sum(H44:O141)-sum(H44:O44),1) -> 2714977 | B44: =ceiling(sum(H44:O44),1) -> 28347 | C44: =sum(E44:F44) -> 28347 | D44: 45536 | E44: =sumif($H$19:O43,E$19,$H44:O44) -> 12770 | F44: =sumif($H$19:P43,F$19,$H44:P44) -> 15577 | G44: =if(D44=DATE(year(today()),month(today()),1),"Current",if(D44>DATE(year(today()),month(today()),1), "Future","Past")) -> Past | H44: =H$18 -> 12770 | K44: =K$18 -> 15577 | M44: 0
A45: =ceiling(sum(H45:O142)-sum(H45:O45),1) -> 2686630 | B45: =ceiling(sum(H45:O45),1) -> 28347 | C45: =sum(E45:F45) -> 28347 | D45: 45566 | E45: =sumif($H$19:O44,E$19,$H45:O45) -> 12770 | F45: =sumif($H$19:P44,F$19,$H45:P45) -> 15577 | G45: =if(D45=DATE(year(today()),month(today()),1),"Current",if(D45>DATE(year(today()),month(today()),1), "Future","Past")) -> Past | H45: =H$18 -> 12770 | K45: =K$18 -> 15577 | M45: 0
A46: =ceiling(sum(H46:O143)-sum(H46:O46),1) -> 2648118 | B46: =ceiling(sum(H46:O46),1) -> 38512 | C46: =sum(E46:F46) -> 0 | D46: 45597 | E46: 0 | F46: 0 | G46: =if(D46=DATE(year(today()),month(today()),1),"Current",if(D46>DATE(year(today()),month(today()),1), "Future","Past")) -> Past | H46: =H$18 -> 12770 | I46: 10165 | K46: =K$18 -> 15577 | M46: 0
A47: =ceiling(sum(H47:O144)-sum(H47:O47),1) -> 2648118 | B47: =ceiling(sum(H47:O47),1) -> 0 | C47: =sum(E47:F47) -> -24867 | D47: 45627 | E47: =sumif($H$19:O46,E$19,$H47:O47)-H47 -> 0 | F47: =sumif($H$19:O46,F$19,$H47:O47)-15577-9290 -> -24867 | G47: =if(D47=DATE(year(today()),month(today()),1),"Current",if(D47>DATE(year(today()),month(today()),1), "Future","Past")) -> Past | M47: 0
A48: =ceiling(sum(H48:O145)-sum(H48:O48),1) -> 2648118 | B48: =ceiling(sum(H48:O48),1) -> 0 | C48: =sum(E48:F48) -> 0 | D48: 45658 | E48: =sumif($H$19:O47,E$19,$H48:O48) -> 0 | F48: =sumif($H$19:P47,F$19,$H48:P48) -> 0 | G48: =if(D48=DATE(year(today()),month(today()),1),"Current",if(D48>DATE(year(today()),month(today()),1), "Future","Past")) -> Past | M48: 0
A49: =ceiling(sum(H49:O146)-sum(H49:O49),1) -> 2648118 | B49: =ceiling(sum(H49:O49),1) -> 0 | C49: =sum(E49:F49) -> 0 | D49: 45689 | E49: =sumif($H$19:O48,E$19,$H49:O49) -> 0 | F49: =sumif($H$19:P48,F$19,$H49:P49) -> 0 | G49: =if(D49=DATE(year(today()),month(today()),1),"Current",if(D49>DATE(year(today()),month(today()),1), "Future","Past")) -> Past | M49: 0
A50: =ceiling(sum(H50:O147)-sum(H50:O50),1) -> 2635348 | B50: 0 | C50: =sum(E50:F50) -> 0 | D50: 45717 | E50: 0 | F50: =sumif($H$19:O49,F$19,$H50:O50) -> 0 | G50: =if(D50=DATE(year(today()),month(today()),1),"Current",if(D50>DATE(year(today()),month(today()),1), "Future","Past")) -> Past | H50: =H$18 -> 12770 | I50: AUTO DEBITED | K50: AUTO DEBITED | M50: 0
A51: =ceiling(sum(H51:O148)-sum(H51:O51),1) -> 2594739 | B51: 0 | C51: =sum(E51:F51) -> 0 | D51: 45748 | E51: 0 | F51: 0 | G51: =if(D51=DATE(year(today()),month(today()),1),"Current",if(D51>DATE(year(today()),month(today()),1), "Future","Past")) -> Past | H51: =H$18 -> 12770 | I51: =I$18 -> 9290 | K51: =K$18 -> 15577 | L51: 2972 | M51: 0
A52: =ceiling(sum(H52:O149)-sum(H52:O52),1) -> 2581969 | B52: =ceiling(sum(H52:O52),1) -> 12770 | C52: =sum(E52:F52) -> 0 | D52: 45778 | E52: 0 | F52: 0 | G52: =if(D52=DATE(year(today()),month(today()),1),"Current",if(D52>DATE(year(today()),month(today()),1), "Future","Past")) -> Past | H52: =H$18 -> 12770 | I52: 0 | K52: 0 | L52: 0 | M52: 0 | N52: 0 | O52: 0
A53: =ceiling(sum(H53:O150)-sum(H53:O53),1) -> 2566699 | B53: =ceiling(sum(H53:O53),1) -> 15270 | C53: =sum(E53:F53) -> 0 | D53: 45809 | E53: 0 | F53: 0 | G53: =if(D53=DATE(year(today()),month(today()),1),"Current",if(D53>DATE(year(today()),month(today()),1), "Future","Past")) -> Past | H53: =H$18 -> 12770 | I53: 0 | K53: 0 | L53: 0 | M53: 0 | N53: 0 | O53: 2500
A54: =ceiling(sum(H54:O151)-sum(H54:O54),1) -> 2516772 | B54: =ceiling(sum(H54:O54),1) -> 49927 | C54: =sum(E54:F54) -> 0 | D54: 45839 | E54: 0 | F54: 0 | G54: =if(D54=DATE(year(today()),month(today()),1),"Current",if(D54>DATE(year(today()),month(today()),1), "Future","Past")) -> Past | H54: =H$18 -> 12770 | I54: =I$18 -> 9290 | K54: =K$18 -> 15577 | L54: 2972 | M54: 0 | N54: 6818 | O54: 2500
A55: =ceiling(sum(H55:O152)-sum(H55:O55),1) -> 2476163 | B55: =ceiling(sum(H55:O55),1) -> 40609 | C55: =sum(E55:F55) -> 0 | D55: 45870 | E55: 0 | F55: 0 | G55: =if(D55=DATE(year(today()),month(today()),1),"Current",if(D55>DATE(year(today()),month(today()),1), "Future","Past")) -> Past | H55: =H$18 -> 12770 | I55: =I$18 -> 9290 | K55: =K$18 -> 15577 | L55: 2972 | M55: 0 | N55: 0 | O55: 0
A56: =ceiling(sum(H56:O153)-sum(H56:O56),1) -> 2435631 | B56: =ceiling(sum(H56:O56),1) -> 40532 | C56: =sum(E56:F56) -> 0 | D56: 45901 | E56: 0 | F56: 0 | G56: =if(D56=DATE(year(today()),month(today()),1),"Current",if(D56>DATE(year(today()),month(today()),1), "Future","Past")) -> Past | H56: =H$18 -> 12770 | I56: =I$18 -> 9290 | J56: 15500 | K56: 0 | L56: 2972 | M56: 0 | N56: 0 | O56: 0
A57: =ceiling(sum(H57:O154)-sum(H57:O57),1) -> 2379522 | B57: =ceiling(sum(H57:O57),1) -> 56109 | C57: =sum(E57:F57) -> 0 | D57: 45931 | E57: 0 | F57: 0 | G57: =if(D57=DATE(year(today()),month(today()),1),"Current",if(D57>DATE(year(today()),month(today()),1), "Future","Past")) -> Past | H57: =H$18 -> 12770 | I57: =I$18 -> 9290 | J57: 15500 | K57: =K$18 -> 15577 | L57: 2972 | M57: 0 | N57: 0 | O57: 0
A58: =ceiling(sum(H58:O155)-sum(H58:O58),1) -> 2366752 | B58: =ceiling(sum(H58:O58),1) -> 12770 | C58: =sum(E58:F58) -> 12770 | D58: 45962 | E58: =sumif($H$19:O57,E$19,$H58:O58) -> 12770 | F58: =sumif($H$19:P57,F$19,$H58:P58) -> 0 | G58: =if(D58=DATE(year(today()),month(today()),1),"Current",if(D58>DATE(year(today()),month(today()),1), "Future","Past")) -> Current | H58: =H$18 -> 12770 | I58: ="PAID "&I$18 -> PAID 9290 | J58: ="PAID "&15500 -> PAID 15500 | K58: ="PAID"&K$18 -> PAID15577 | L58: ="PAID "&2972 -> PAID 2972 | M58: 0 | N58: 0 | O58: 0
A59: =ceiling(sum(H59:O156)-sum(H59:O59),1) -> 2310643 | B59: =ceiling(sum(H59:O59),1) -> 56109 | C59: =sum(E59:F59) -> 56109 | D59: 45992 | E59: =sumif($H$19:O58,E$19,$H59:O59) -> 15742 | F59: =sumif($H$19:P58,F$19,$H59:P59) -> 40367 | G59: =if(D59=DATE(year(today()),month(today()),1),"Current",if(D59>DATE(year(today()),month(today()),1), "Future","Past")) -> Future | H59: =H$18 -> 12770 | I59: =I$18 -> 9290 | J59: 15500 | K59: =K$18 -> 15577 | L59: 2972 | M59: 0 | N59: 0 | O59: 0
A60: =ceiling(sum(H60:O157)-sum(H60:O60),1) -> 2254534 | B60: =ceiling(sum(H60:O60),1) -> 56109 | C60: =sum(E60:F60) -> 56109 | D60: 46023 | E60: =sumif($H$19:O59,E$19,$H60:O60) -> 15742 | F60: =sumif($H$19:P59,F$19,$H60:P60) -> 40367 | G60: =if(D60=DATE(year(today()),month(today()),1),"Current",if(D60>DATE(year(today()),month(today()),1), "Future","Past")) -> Future | H60: =H$18 -> 12770 | I60: =I$18 -> 9290 | J60: 15500 | K60: =K$18 -> 15577 | L60: 2972 | M60: 0 | N60: 0 | O60: 0
A61: =ceiling(sum(H61:O158)-sum(H61:O61),1) -> 2198425 | B61: =ceiling(sum(H61:O61),1) -> 56109 | C61: =sum(E61:F61) -> 56109 | D61: 46054 | E61: =sumif($H$19:O60,E$19,$H61:O61) -> 15742 | F61: =sumif($H$19:P60,F$19,$H61:P61) -> 40367 | G61: =if(D61=DATE(year(today()),month(today()),1),"Current",if(D61>DATE(year(today()),month(today()),1), "Future","Past")) -> Future | H61: =H$18 -> 12770 | I61: =I$18 -> 9290 | J61: 15500 | K61: =K$18 -> 15577 | L61: 2972 | M61: 0 | N61: 0 | O61: 0
A62: =ceiling(sum(H62:O159)-sum(H62:O62),1) -> 2142316 | B62: =ceiling(sum(H62:O62),1) -> 56109 | C62: =sum(E62:F62) -> 56109 | D62: 46082 | E62: =sumif($H$19:O61,E$19,$H62:O62) -> 15742 | F62: =sumif($H$19:P61,F$19,$H62:P62) -> 40367 | G62: =if(D62=DATE(year(today()),month(today()),1),"Current",if(D62>DATE(year(today()),month(today()),1), "Future","Past")) -> Future | H62: =H$18 -> 12770 | I62: =I$18 -> 9290 | J62: 15500 | K62: =K$18 -> 15577 | L62: 2972 | M62: 0 | N62: 0 | O62: 0
A63: =ceiling(sum(H63:O160)-sum(H63:O63),1) -> 2086207 | B63: =ceiling(sum(H63:O63),1) -> 56109 | C63: =sum(E63:F63) -> 56109 | D63: 46113 | E63: =sumif($H$19:O62,E$19,$H63:O63) -> 15742 | F63: =sumif($H$19:P62,F$19,$H63:P63) -> 40367 | G63: =if(D63=DATE(year(today()),month(today()),1),"Current",if(D63>DATE(year(today()),month(today()),1), "Future","Past")) -> Future | H63: =H$18 -> 12770 | I63: =I$18 -> 9290 | J63: 15500 | K63: =K$18 -> 15577 | L63: 2972 | M63: 0 | N63: 0 | O63: 0
A64: =ceiling(sum(H64:O161)-sum(H64:O64),1) -> 2030098 | B64: =ceiling(sum(H64:O64),1) -> 56109 | C64: =sum(E64:F64) -> 56109 | D64: 46143 | E64: =sumif($H$19:O63,E$19,$H64:O64) -> 15742 | F64: =sumif($H$19:P63,F$19,$H64:P64) -> 40367 | G64: =if(D64=DATE(year(today()),month(today()),1),"Current",if(D64>DATE(year(today()),month(today()),1), "Future","Past")) -> Future | H64: =H$18 -> 12770 | I64: =I$18 -> 9290 | J64: 15500 | K64: =K$18 -> 15577 | L64: 2972 | M64: 0 | N64: 0
A65: =ceiling(sum(H65:O162)-sum(H65:O65),1) -> 1973989 | B65: =ceiling(sum(H65:O65),1) -> 56109 | C65: =sum(E65:F65) -> 56109 | D65: 46174 | E65: =sumif($H$19:O64,E$19,$H65:O65) -> 15742 | F65: =sumif($H$19:P64,F$19,$H65:P65) -> 40367 | G65: =if(D65=DATE(year(today()),month(today()),1),"Current",if(D65>DATE(year(today()),month(today()),1), "Future","Past")) -> Future | H65: =H$18 -> 12770 | I65: =I$18 -> 9290 | J65: 15500 | K65: =K$18 -> 15577 | L65: 2972 | M65: 0 | N65: 0
A66: =ceiling(sum(H66:O163)-sum(H66:O66),1) -> 1917880 | B66: =ceiling(sum(H66:O66),1) -> 56109 | C66: =sum(E66:F66) -> 56109 | D66: 46204 | E66: =sumif($H$19:O65,E$19,$H66:O66) -> 15742 | F66: =sumif($H$19:P65,F$19,$H66:P66) -> 40367 | G66: =if(D66=DATE(year(today()),month(today()),1),"Current",if(D66>DATE(year(today()),month(today()),1), "Future","Past")) -> Future | H66: =H$18 -> 12770 | I66: =I$18 -> 9290 | J66: 15500 | K66: =K$18 -> 15577 | L66: 2972 | M66: 0 | N66: 0
A67: =ceiling(sum(H67:O164)-sum(H67:O67),1) -> 1861771 | B67: =ceiling(sum(H67:O67),1) -> 56109 | C67: =sum(E67:F67) -> 56109 | D67: 46235 | E67: =sumif($H$19:O66,E$19,$H67:O67) -> 15742 | F67: =sumif($H$19:P66,F$19,$H67:P67) -> 40367 | G67: =if(D67=DATE(year(today()),month(today()),1),"Current",if(D67>DATE(year(today()),month(today()),1), "Future","Past")) -> Future | H67: =H$18 -> 12770 | I67: =I$18 -> 9290 | J67: 15500 | K67: =K$18 -> 15577 | L67: 2972 | M67: 0 | N67: 0
A68: =ceiling(sum(H68:O165)-sum(H68:O68),1) -> 1805662 | B68: =ceiling(sum(H68:O68),1) -> 56109 | C68: =sum(E68:F68) -> 56109 | D68: 46266 | E68: =sumif($H$19:O67,E$19,$H68:O68) -> 15742 | F68: =sumif($H$19:P67,F$19,$H68:P68) -> 40367 | G68: =if(D68=DATE(year(today()),month(today()),1),"Current",if(D68>DATE(year(today()),month(today()),1), "Future","Past")) -> Future | H68: =H$18 -> 12770 | I68: =I$18 -> 9290 | J68: 15500 | K68: =K$18 -> 15577 | L68: 2972 | M68: 0 | N68: 0
A69: =ceiling(sum(H69:O166)-sum(H69:O69),1) -> 1749553 | B69: =ceiling(sum(H69:O69),1) -> 56109 | C69: =sum(E69:F69) -> 56109 | D69: 46296 | E69: =sumif($H$19:O68,E$19,$H69:O69) -> 15742 | F69: =sumif($H$19:P68,F$19,$H69:P69) -> 40367 | G69: =if(D69=DATE(year(today()),month(today()),1),"Current",if(D69>DATE(year(today()),month(today()),1), "Future","Past")) -> Future | H69: =H$18 -> 12770 | I69: =I$18 -> 9290 | J69: 15500 | K69: =K$18 -> 15577 | L69: 2972 | M69: 0 | N69: 0
A70: =ceiling(sum(H70:O167)-sum(H70:O70),1) -> 1693444 | B70: =ceiling(sum(H70:O70),1) -> 56109 | C70: =sum(E70:F70) -> 56109 | D70: 46327 | E70: =sumif($H$19:O69,E$19,$H70:O70) -> 15742 | F70: =sumif($H$19:P69,F$19,$H70:P70) -> 40367 | G70: =if(D70=DATE(year(today()),month(today()),1),"Current",if(D70>DATE(year(today()),month(today()),1), "Future","Past")) -> Future | H70: =H$18 -> 12770 | I70: =I$18 -> 9290 | J70: 15500 | K70: =K$18 -> 15577 | L70: 2972 | M70: 0
A71: =ceiling(sum(H71:O168)-sum(H71:O71),1) -> 1637335 | B71: =ceiling(sum(H71:O71),1) -> 56109 | C71: =sum(E71:F71) -> 56109 | D71: 46357 | E71: =sumif($H$19:O70,E$19,$H71:O71) -> 15742 | F71: =sumif($H$19:P70,F$19,$H71:P71) -> 40367 | G71: =if(D71=DATE(year(today()),month(today()),1),"Current",if(D71>DATE(year(today()),month(today()),1), "Future","Past")) -> Future | H71: =H$18 -> 12770 | I71: =I$18 -> 9290 | J71: 15500 | K71: =K$18 -> 15577 | L71: 2972 | M71: 0
A72: =ceiling(sum(H72:O169)-sum(H72:O72),1) -> 1581226 | B72: =ceiling(sum(H72:O72),1) -> 56109 | C72: =sum(E72:F72) -> 56109 | D72: 46388 | E72: =sumif($H$19:O71,E$19,$H72:O72) -> 15742 | F72: =sumif($H$19:P71,F$19,$H72:P72) -> 40367 | G72: =if(D72=DATE(year(today()),month(today()),1),"Current",if(D72>DATE(year(today()),month(today()),1), "Future","Past")) -> Future | H72: =H$18 -> 12770 | I72: =I$18 -> 9290 | J72: 15500 | K72: =K$18 -> 15577 | L72: 2972 | M72: 0
A73: =ceiling(sum(H73:O170)-sum(H73:O73),1) -> 1525117 | B73: =ceiling(sum(H73:O73),1) -> 56109 | C73: =sum(E73:F73) -> 56109 | D73: 46419 | E73: =sumif($H$19:O72,E$19,$H73:O73) -> 15742 | F73: =sumif($H$19:P72,F$19,$H73:P73) -> 40367 | G73: =if(D73=DATE(year(today()),month(today()),1),"Current",if(D73>DATE(year(today()),month(today()),1), "Future","Past")) -> Future | H73: =H$18 -> 12770 | I73: =I$18 -> 9290 | J73: 15500 | K73: =K$18 -> 15577 | L73: 2972 | M73: 0
A74: =ceiling(sum(H74:O171)-sum(H74:O74),1) -> 1469008 | B74: =ceiling(sum(H74:O74),1) -> 56109 | C74: =sum(E74:F74) -> 56109 | D74: 46447 | E74: =sumif($H$19:O73,E$19,$H74:O74) -> 15742 | F74: =sumif($H$19:P73,F$19,$H74:P74) -> 40367 | G74: =if(D74=DATE(year(today()),month(today()),1),"Current",if(D74>DATE(year(today()),month(today()),1), "Future","Past")) -> Future | H74: =H$18 -> 12770 | I74: =I$18 -> 9290 | J74: 15500 | K74: =K$18 -> 15577 | L74: 2972 | M74: 0
A75: =ceiling(sum(H75:O172)-sum(H75:O75),1) -> 1412899 | B75: =ceiling(sum(H75:O75),1) -> 56109 | C75: =sum(E75:F75) -> 56109 | D75: 46478 | E75: =sumif($H$19:O74,E$19,$H75:O75) -> 15742 | F75: =sumif($H$19:P74,F$19,$H75:P75) -> 40367 | G75: =if(D75=DATE(year(today()),month(today()),1),"Current",if(D75>DATE(year(today()),month(today()),1), "Future","Past")) -> Future | H75: =H$18 -> 12770 | I75: =I$18 -> 9290 | J75: 15500 | K75: =K$18 -> 15577 | L75: 2972 | M75: 0
A76: =ceiling(sum(H76:O173)-sum(H76:O76),1) -> 1356790 | B76: =ceiling(sum(H76:O76),1) -> 56109 | C76: =sum(E76:F76) -> 56109 | D76: 46508 | E76: =sumif($H$19:O75,E$19,$H76:O76) -> 15742 | F76: =sumif($H$19:P75,F$19,$H76:P76) -> 40367 | G76: =if(D76=DATE(year(today()),month(today()),1),"Current",if(D76>DATE(year(today()),month(today()),1), "Future","Past")) -> Future | H76: =H$18 -> 12770 | I76: =I$18 -> 9290 | J76: 15500 | K76: =K$18 -> 15577 | L76: 2972 | M76: 0
A77: =ceiling(sum(H77:O174)-sum(H77:O77),1) -> 1300681 | B77: =ceiling(sum(H77:O77),1) -> 56109 | C77: =sum(E77:F77) -> 56109 | D77: 46539 | E77: =sumif($H$19:O76,E$19,$H77:O77) -> 15742 | F77: =sumif($H$19:P76,F$19,$H77:P77) -> 40367 | G77: =if(D77=DATE(year(today()),month(today()),1),"Current",if(D77>DATE(year(today()),month(today()),1), "Future","Past")) -> Future | H77: =H$18 -> 12770 | I77: =I$18 -> 9290 | J77: 15500 | K77: =K$18 -> 15577 | L77: 2972 | M77: 0
A78: =ceiling(sum(H78:O175)-sum(H78:O78),1) -> 1244572 | B78: =ceiling(sum(H78:O78),1) -> 56109 | C78: =sum(E78:F78) -> 56109 | D78: 46569 | E78: =sumif($H$19:O77,E$19,$H78:O78) -> 15742 | F78: =sumif($H$19:P77,F$19,$H78:P78) -> 40367 | G78: =if(D78=DATE(year(today()),month(today()),1),"Current",if(D78>DATE(year(today()),month(today()),1), "Future","Past")) -> Future | H78: =H$18 -> 12770 | I78: =I$18 -> 9290 | J78: 15500 | K78: =K$18 -> 15577 | L78: 2972 | M78: 0
A79: =ceiling(sum(H79:O176)-sum(H79:O79),1) -> 1188463 | B79: =ceiling(sum(H79:O79),1) -> 56109 | C79: =sum(E79:F79) -> 56109 | D79: 46600 | E79: =sumif($H$19:O78,E$19,$H79:O79) -> 15742 | F79: =sumif($H$19:P78,F$19,$H79:P79) -> 40367 | G79: =if(D79=DATE(year(today()),month(today()),1),"Current",if(D79>DATE(year(today()),month(today()),1), "Future","Past")) -> Future | H79: =H$18 -> 12770 | I79: =I$18 -> 9290 | J79: 15500 | K79: =K$18 -> 15577 | L79: 2972 | M79: 0
A80: =ceiling(sum(H80:O177)-sum(H80:O80),1) -> 1132354 | B80: =ceiling(sum(H80:O80),1) -> 56109 | C80: =sum(E80:F80) -> 56109 | D80: 46631 | E80: =sumif($H$19:O79,E$19,$H80:O80) -> 15742 | F80: =sumif($H$19:P79,F$19,$H80:P80) -> 40367 | G80: =if(D80=DATE(year(today()),month(today()),1),"Current",if(D80>DATE(year(today()),month(today()),1), "Future","Past")) -> Future | H80: =H$18 -> 12770 | I80: =I$18 -> 9290 | J80: 15500 | K80: =K$18 -> 15577 | L80: 2972 | M80: 0
A81: =ceiling(sum(H81:O178)-sum(H81:O81),1) -> 1076245 | B81: =ceiling(sum(H81:O81),1) -> 56109 | C81: =sum(E81:F81) -> 56109 | D81: 46661 | E81: =sumif($H$19:O80,E$19,$H81:O81) -> 15742 | F81: =sumif($H$19:P80,F$19,$H81:P81) -> 40367 | G81: =if(D81=DATE(year(today()),month(today()),1),"Current",if(D81>DATE(year(today()),month(today()),1), "Future","Past")) -> Future | H81: =H$18 -> 12770 | I81: =I$18 -> 9290 | J81: 15500 | K81: =K$18 -> 15577 | L81: 2972 | M81: 0
... A86: =ceiling(sum(H86:O183)-sum(H86:O86),1) -> 795700 | B86: =ceiling(sum(H86:O86),1) -> 56109 | C86: =sum(E86:F86) -> 56109 | D86: 46813 | E86: =sumif($H$19:O85,E$19,$H86:O86) -> 15742 | F86: =sumif($H$19:P85,F$19,$H86:P86) -> 40367 | G86: =if(D86=DATE(year(today()),month(today()),1),"Current",if(D86>DATE(year(today()),month(today()),1), "Future","Past")) -> Future | H86: =H$18 -> 12770 | I86: =I$18 -> 9290 | J86: 15500 | K86: =K$18 -> 15577 | L86: 2972 | M86: 0
A87: =ceiling(sum(H87:O184)-sum(H87:O87),1) -> 755168 | B87: =ceiling(sum(H87:O87),1) -> 40532 | C87: =sum(E87:F87) -> 40532 | D87: 46844 | E87: =sumif($H$19:O86,E$19,$H87:O87) -> 15742 | F87: =sumif($H$19:P86,F$19,$H87:P87) -> 24790 | G87: =if(D87=DATE(year(today()),month(today()),1),"Current",if(D87>DATE(year(today()),month(today()),1), "Future","Past")) -> Future | H87: =H$18 -> 12770 | I87: =I$18 -> 9290 | J87: 15500 | L87: 2972 | M87: 0
A88: =ceiling(sum(H88:O185)-sum(H88:O88),1) -> 714636 | B88: =ceiling(sum(H88:O88),1) -> 40532 | C88: =sum(E88:F88) -> 40532 | D88: 46874 | E88: =sumif($H$19:O87,E$19,$H88:O88) -> 15742 | F88: =sumif($H$19:P87,F$19,$H88:P88) -> 24790 | G88: =if(D88=DATE(year(today()),month(today()),1),"Current",if(D88>DATE(year(today()),month(today()),1), "Future","Past")) -> Future | H88: =H$18 -> 12770 | I88: =I$18 -> 9290 | J88: 15500 | L88: 2972 | M88: 0
A89: =ceiling(sum(H89:O186)-sum(H89:O89),1) -> 674104 | B89: =ceiling(sum(H89:O89),1) -> 40532 | C89: =sum(E89:F89) -> 40532 | D89: 46905 | E89: =sumif($H$19:O88,E$19,$H89:O89) -> 15742 | F89: =sumif($H$19:P88,F$19,$H89:P89) -> 24790 | G89: =if(D89=DATE(year(today()),month(today()),1),"Current",if(D89>DATE(year(today()),month(today()),1), "Future","Past")) -> Future | H89: =H$18 -> 12770 | I89: =I$18 -> 9290 | J89: 15500 | L89: 2972 | M89: 0
A90: =ceiling(sum(H90:O187)-sum(H90:O90),1) -> 633572 | B90: =ceiling(sum(H90:O90),1) -> 40532 | C90: =sum(E90:F90) -> 40532 | D90: 46935 | E90: =sumif($H$19:O89,E$19,$H90:O90) -> 15742 | F90: =sumif($H$19:P89,F$19,$H90:P90) -> 24790 | G90: =if(D90=DATE(year(today()),month(today()),1),"Current",if(D90>DATE(year(today()),month(today()),1), "Future","Past")) -> Future | H90: =H$18 -> 12770 | I90: =I$18 -> 9290 | J90: 15500 | L90: 2972 | M90: 0
A91: =ceiling(sum(H91:O188)-sum(H91:O91),1) -> 593040 | B91: =ceiling(sum(H91:O91),1) -> 40532 | C91: =sum(E91:F91) -> 40532 | D91: 46966 | E91: =sumif($H$19:O90,E$19,$H91:O91) -> 15742 | F91: =sumif($H$19:P90,F$19,$H91:P91) -> 24790 | G91: =if(D91=DATE(year(today()),month(today()),1),"Current",if(D91>DATE(year(today()),month(today()),1), "Future","Past")) -> Future | H91: =H$18 -> 12770 | I91: =I$18 -> 9290 | J91: 15500 | L91: 2972 | M91: 0
A92: =ceiling(sum(H92:O189)-sum(H92:O92),1) -> 552508 | B92: =ceiling(sum(H92:O92),1) -> 40532 | C92: =sum(E92:F92) -> 40532 | D92: 46997 | E92: =sumif($H$19:O91,E$19,$H92:O92) -> 15742 | F92: =sumif($H$19:P91,F$19,$H92:P92) -> 24790 | G92: =if(D92=DATE(year(today()),month(today()),1),"Current",if(D92>DATE(year(today()),month(today()),1), "Future","Past")) -> Future | H92: =H$18 -> 12770 | I92: =I$18 -> 9290 | J92: 15500 | L92: 2972 | M92: 0
A93: =ceiling(sum(H93:O190)-sum(H93:O93),1) -> 512004 | B93: =ceiling(sum(H93:O93),1) -> 40504 | C93: =sum(E93:F93) -> 40504 | D93: 47027 | E93: =sumif($H$19:O92,E$19,$H93:O93) -> 15742 | F93: =sumif($H$19:P92,F$19,$H93:P93) -> 24762 | G93: =if(D93=DATE(year(today()),month(today()),1),"Current",if(D93>DATE(year(today()),month(today()),1), "Future","Past")) -> Future | H93: =H$18 -> 12770 | I93: 9262 | J93: 15500 | L93: 2972 | M93: 0
A94: =ceiling(sum(H94:O191)-sum(H94:O94),1) -> 480762 | B94: =ceiling(sum(H94:O94),1) -> 31242 | C94: =sum(E94:F94) -> 31242 | D94: 47058 | E94: =sumif($H$19:O93,E$19,$H94:O94) -> 15742 | F94: =sumif($H$19:P93,F$19,$H94:P94) -> 15500 | G94: =if(D94=DATE(year(today()),month(today()),1),"Current",if(D94>DATE(year(today()),month(today()),1), "Future","Past")) -> Future | H94: =H$18 -> 12770 | J94: 15500 | L94: 2972 | M94: 0
A95: =ceiling(sum(H95:O192)-sum(H95:O95),1) -> 449520 | B95: =ceiling(sum(H95:O95),1) -> 31242 | C95: =sum(E95:F95) -> 31242 | D95: 47088 | E95: =sumif($H$19:O94,E$19,$H95:O95) -> 15742 | F95: =sumif($H$19:P94,F$19,$H95:P95) -> 15500 | G95: =if(D95=DATE(year(today()),month(today()),1),"Current",if(D95>DATE(year(today()),month(today()),1), "Future","Past")) -> Future | H95: =H$18 -> 12770 | J95: 15500 | L95: 2972 | M95: 0
A96: =ceiling(sum(H96:O193)-sum(H96:O96),1) -> 418278 | B96: =ceiling(sum(H96:O96),1) -> 31242 | C96: =sum(E96:F96) -> 31242 | D96: 47119 | E96: =sumif($H$19:O95,E$19,$H96:O96) -> 15742 | F96: =sumif($H$19:P95,F$19,$H96:P96) -> 15500 | G96: =if(D96=DATE(year(today()),month(today()),1),"Current",if(D96>DATE(year(today()),month(today()),1), "Future","Past")) -> Future | H96: =H$18 -> 12770 | J96: 15500 | L96: 2972 | M96: 0
A97: =ceiling(sum(H97:O194)-sum(H97:O97),1) -> 387036 | B97: =ceiling(sum(H97:O97),1) -> 31242 | C97: =sum(E97:F97) -> 31242 | D97: 47150 | E97: =sumif($H$19:O96,E$19,$H97:O97) -> 15742 | F97: =sumif($H$19:P96,F$19,$H97:P97) -> 15500 | G97: =if(D97=DATE(year(today()),month(today()),1),"Current",if(D97>DATE(year(today()),month(today()),1), "Future","Past")) -> Future | H97: =H$18 -> 12770 | J97: 15500 | L97: 2972 | M97: 0
A98: =ceiling(sum(H98:O195)-sum(H98:O98),1) -> 355794 | B98: =ceiling(sum(H98:O98),1) -> 31242 | C98: =sum(E98:F98) -> 31242 | D98: 47178 | E98: =sumif($H$19:O97,E$19,$H98:O98) -> 15742 | F98: =sumif($H$19:P97,F$19,$H98:P98) -> 15500 | G98: =if(D98=DATE(year(today()),month(today()),1),"Current",if(D98>DATE(year(today()),month(today()),1), "Future","Past")) -> Future | H98: =H$18 -> 12770 | J98: 15500 | L98: 2972 | M98: 0
A99: =ceiling(sum(H99:O196)-sum(H99:O99),1) -> 324552 | B99: =ceiling(sum(H99:O99),1) -> 31242 | C99: =sum(E99:F99) -> 31242 | D99: 47209 | E99: =sumif($H$19:O98,E$19,$H99:O99) -> 15742 | F99: =sumif($H$19:P98,F$19,$H99:P99) -> 15500 | G99: =if(D99=DATE(year(today()),month(today()),1),"Current",if(D99>DATE(year(today()),month(today()),1), "Future","Past")) -> Future | H99: =H$18 -> 12770 | J99: 15500 | L99: 2972 | M99: 0
A100: =ceiling(sum(H100:O197)-sum(H100:O100),1) -> 293310 | B100: =ceiling(sum(H100:O100),1) -> 31242 | C100: =sum(E100:F100) -> 31242 | D100: 47239 | E100: =sumif($H$19:O99,E$19,$H100:O100) -> 15742 | F100: =sumif($H$19:P99,F$19,$H100:P100) -> 15500 | G100: =if(D100=DATE(year(today()),month(today()),1),"Current",if(D100>DATE(year(today()),month(today()),1), "Future","Past")) -> Future | H100: =H$18 -> 12770 | J100: 15500 | L100: 2972 | M100: 0
A101: =ceiling(sum(H101:O198)-sum(H101:O101),1) -> 262068 | B101: =ceiling(sum(H101:O101),1) -> 31242 | C101: =sum(E101:F101) -> 31242 | D101: 47270 | E101: =sumif($H$19:O100,E$19,$H101:O101) -> 15742 | F101: =sumif($H$19:P100,F$19,$H101:P101) -> 15500 | G101: =if(D101=DATE(year(today()),month(today()),1),"Current",if(D101>DATE(year(today()),month(today()),1), "Future","Past")) -> Future | H101: =H$18 -> 12770 | J101: 15500 | L101: 2972 | M101: 0
A102: =ceiling(sum(H102:O199)-sum(H102:O102),1) -> 230826 | B102: =ceiling(sum(H102:O102),1) -> 31242 | C102: =sum(E102:F102) -> 31242 | D102: 47300 | E102: =sumif($H$19:O101,E$19,$H102:O102) -> 15742 | F102: =sumif($H$19:P101,F$19,$H102:P102) -> 15500 | G102: =if(D102=DATE(year(today()),month(today()),1),"Current",if(D102>DATE(year(today()),month(today()),1), "Future","Past")) -> Future | H102: =H$18 -> 12770 | J102: 15500 | L102: 2972 | M102: 0
A103: =ceiling(sum(H103:O200)-sum(H103:O103),1) -> 199584 | B103: =ceiling(sum(H103:O103),1) -> 31242 | C103: =sum(E103:F103) -> 31242 | D103: 47331 | E103: =sumif($H$19:O102,E$19,$H103:O103) -> 15742 | F103: =sumif($H$19:P102,F$19,$H103:P103) -> 15500 | G103: =if(D103=DATE(year(today()),month(today()),1),"Current",if(D103>DATE(year(today()),month(today()),1), "Future","Past")) -> Future | H103: =H$18 -> 12770 | J103: 15500 | L103: 2972 | M103: 0
A104: =ceiling(sum(H104:O201)-sum(H104:O104),1) -> 183842 | B104: =ceiling(sum(H104:O104),1) -> 15742 | C104: =sum(E104:F104) -> 15742 | D104: 47362 | E104: =sumif($H$19:O103,E$19,$H104:O104) -> 15742 | F104: =sumif($H$19:P103,F$19,$H104:P104) -> 0 | G104: =if(D104=DATE(year(today()),month(today()),1),"Current",if(D104>DATE(year(today()),month(today()),1), "Future","Past")) -> Future | H104: =H$18 -> 12770 | L104: 2972 | M104: 0
...

Sheet EMIs
D1: Loan Amount | E1: Completed EMIs | F1: Total EMIs | G1: Loan Amount | H1: Completed EMIs | I1: Total EMIs | J1: Loan Amount | K1: Completed EMIs | L1: Total EMIs | M1: Loan Amount | N1: Completed EMIs | O1: Total EMIs | P1: Loan Amount | Q1: Completed EMIs | R1: Total EMIs | S1: Loan Amount | T1: Completed EMIs | U1: Total EMIs
D2: 800000 | E2: =countif(E8:E1012,"Paid") -> 25 | F2: =count(D8:D1012) -> 84 | G2: 692275 | H2: =countif(H8:H1012,"Paid") -> 32 | I2: =count(G8:G1012) -> 60 | J2: 300000 | K2: =countif(K8:K1012,"Paid") -> 13 | L2: =count(J8:J1012) -> 48 | M2: 134000 | N2: =countif(N8:N1012,"Paid") -> 8 | O2: =count(M8:M1012) -> 60 | P2: 100000 | Q2: =countif(Q8:Q1012,"Paid") -> 7 | R2: =count(P8:P1012) -> 18 | S2: 233687 | T2: =countif(T8:T1012,"Paid") -> 7 | U2: =count(S8:S1012) -> 12
D3: EMI | E3: Pending EMIs | G3: EMI | H3: Pending EMIs | J3: EMI | K3: Pending EMIs | M3: EMI | N3: Pending EMIs | P3: EMI | Q3: Pending EMIs | S3: EMI | T3: Pending EMIs
D4: 12770 | E4: =F2-E2 -> 59 | G4: 15577 | H4: =I2-H2 -> 28 | J4: 9290 | K4: =L2-K2 -> 35 | M4: 2972 | N4: =O2-N2 -> 52 | P4: 6818 | Q4: =R2-Q2 -> 11 | S4: =S2*1.1% -> 2570.557 | T4: =U2-T2 -> 5
D5: CAR LOAN | E5: CAR LOAN | F5: CAR LOAN | G5: BAJAJ LOAN | H5: BAJAJ LOAN | I5: BAJAJ LOAN | J5: MONEY VIEW | K5: MONEY VIEW | L5: MONEY VIEW | M5: AXIS | N5: AXIS | O5: AXIS | P5: FIBE | Q5: FIBE | R5: FIBE | S5: FIBE | T5: FIBE | U5: FIBE
D6: Total | E6: Paid | F6: Balance | G6: Total | H6: Paid | I6: Balance | J6: Total | K6: Paid | L6: Balance | M6: Total | N6: Paid | O6: Balance | P6: Total | Q6: Paid | R6: Balance | S6: Total | T6: Paid | U6: Balance
D7: =sum(D8:D1012) -> 1072680 | E7: =SUMIF(E8:E1012,E6,D8:D1012) -> 319250 | F7: =SUMIF(F8:F1012,F6,D8:D1012) -> 753430 | G7: =sum(G8:G1012) -> 957834 | H7: =SUMIF(H8:H1012,H6,G8:G1012) -> 521678 | I7: =SUMIF(I8:I1012,I6,G8:G1012) -> 436156 | J7: =sum(J8:J1012) -> 446795 | K7: =SUMIF(K8:K1012,K6,J8:J1012) -> 121645 | L7: =SUMIF(L8:L1012,L6,J8:J1012) -> 325150 | M7: =sum(M8:M1012) -> 178320 | N7: =SUMIF(N8:N1012,N6,M8:M1012) -> 23776 | O7: =SUMIF(O8:O1012,O6,M8:M1012) -> 154544 | P7: =sum(P8:P1012) -> 122724 | Q7: =SUMIF(Q8:Q1012,Q6,P8:P1012) -> 47726 | R7: =SUMIF(R8:R1012,R6,P8:P1012) -> 74998 | S7: =sum(S8:S1012) -> 30852 | T7: =SUMIF(T8:T1012,T6,S8:S1012) -> 17997 | U7: =SUMIF(U8:U1012,U6,S8:S1012) -> 12855
B8: =sum(D8:Z8) -> 0 | C8: 44958 | H8: =if(AND($C8<today(),G8>0), "Paid","N/A") -> N/A | I8: =if(AND($C8<today(),G8>0), "N/A","Balance") -> Balance | K8: =if(AND($C8<today(),J8>0), "Paid","N/A") -> N/A | L8: =if(AND($C8<today(),J8>0), "N/A","Balance") -> Balance | N8: =if(AND($C8<today(),M8>0), "Paid","N/A") -> N/A | O8: =if(AND($C8<today(),M8>0), "N/A","Balance") -> Balance | Q8: =if(AND($C8<today(),P8>0), "Paid","N/A") -> N/A | R8: =if(AND($C8<today(),P8>0), "N/A","Balance") -> Balance | T8: =if(AND($C8<today(),S8>0), "Paid","N/A") -> N/A | U8: =if(AND($C8<today(),S8>0), "N/A","Balance") -> Balance
B9: =sum(D9:Z9) -> 0 | C9: 44986 | H9: =if(AND($C9<today(),G9>0), "Paid","N/A") -> N/A | I9: =if(AND($C9<today(),G9>0), "N/A","Balance") -> Balance | K9: =if(AND($C9<today(),J9>0), "Paid","N/A") -> N/A | L9: =if(AND($C9<today(),J9>0), "N/A","Balance") -> Balance | N9: =if(AND($C9<today(),M9>0), "Paid","N/A") -> N/A | O9: =if(AND($C9<today(),M9>0), "N/A","Balance") -> Balance | Q9: =if(AND($C9<today(),P9>0), "Paid","N/A") -> N/A | R9: =if(AND($C9<today(),P9>0), "N/A","Balance") -> Balance | T9: =if(AND($C9<today(),S9>0), "Paid","N/A") -> N/A | U9: =if(AND($C9<today(),S9>0), "N/A","Balance") -> Balance
B10: =sum(D10:Z10) -> 22679 | C10: 45017 | G10: 22679 | H10: =if(AND($C10<today(),G10>0), "Paid","N/A") -> Paid | I10: =if(AND($C10<today(),G10>0), "N/A","Balance") -> N/A | K10: =if(AND($C10<today(),J10>0), "Paid","N/A") -> N/A | L10: =if(AND($C10<today(),J10>0), "N/A","Balance") -> Balance | N10: =if(AND($C10<today(),M10>0), "Paid","N/A") -> N/A | O10: =if(AND($C10<today(),M10>0), "N/A","Balance") -> Balance | Q10: =if(AND($C10<today(),P10>0), "Paid","N/A") -> N/A | R10: =if(AND($C10<today(),P10>0), "N/A","Balance") -> Balance | T10: =if(AND($C10<today(),S10>0), "Paid","N/A") -> N/A | U10: =if(AND($C10<today(),S10>0), "N/A","Balance") -> Balance
B11: =sum(D11:Z11) -> 15929 | C11: 45047 | G11: 15929 | H11: =if(AND($C11<today(),G11>0), "Paid","N/A") -> Paid | I11: =if(AND($C11<today(),G11>0), "N/A","Balance") -> N/A | K11: =if(AND($C11<today(),J11>0), "Paid","N/A") -> N/A | L11: =if(AND($C11<today(),J11>0), "N/A","Balance") -> Balance | N11: =if(AND($C11<today(),M11>0), "Paid","N/A") -> N/A | O11: =if(AND($C11<today(),M11>0), "N/A","Balance") -> Balance | Q11: =if(AND($C11<today(),P11>0), "Paid","N/A") -> N/A | R11: =if(AND($C11<today(),P11>0), "N/A","Balance") -> Balance | T11: =if(AND($C11<today(),S11>0), "Paid","N/A") -> N/A | U11: =if(AND($C11<today(),S11>0), "N/A","Balance") -> Balance
B12: =sum(D12:Z12) -> 15929 | C12: 45078 | G12: 15929 | H12: =if(AND($C12<today(),G12>0), "Paid","N/A") -> Paid | I12: =if(AND($C12<today(),G12>0), "N/A","Balance") -> N/A | K12: =if(AND($C12<today(),J12>0), "Paid","N/A") -> N/A | L12: =if(AND($C12<today(),J12>0), "N/A","Balance") -> Balance | N12: =if(AND($C12<today(),M12>0), "Paid","N/A") -> N/A | O12: =if(AND($C12<today(),M12>0), "N/A","Balance") -> Balance | Q12: =if(AND($C12<today(),P12>0), "Paid","N/A") -> N/A | R12: =if(AND($C12<today(),P12>0), "N/A","Balance") -> Balance | T12: =if(AND($C12<today(),S12>0), "Paid","N/A") -> N/A | U12: =if(AND($C12<today(),S12>0), "N/A","Balance") -> Balance
B13: =sum(D13:Z13) -> 15929 | C13: 45108 | G13: 15929 | H13: =if(AND($C13<today(),G13>0), "Paid","N/A") -> Paid | I13: =if(AND($C13<today(),G13>0), "N/A","Balance") -> N/A | K13: =if(AND($C13<today(),J13>0), "Paid","N/A") -> N/A | L13: =if(AND($C13<today(),J13>0), "N/A","Balance") -> Balance | N13: =if(AND($C13<today(),M13>0), "Paid","N/A") -> N/A | O13: =if(AND($C13<today(),M13>0), "N/A","Balance") -> Balance | Q13: =if(AND($C13<today(),P13>0), "Paid","N/A") -> N/A | R13: =if(AND($C13<today(),P13>0), "N/A","Balance") -> Balance | T13: =if(AND($C13<today(),S13>0), "Paid","N/A") -> N/A | U13: =if(AND($C13<today(),S13>0), "N/A","Balance") -> Balance
B14: =sum(D14:Z14) -> 15929 | C14: 45139 | G14: 15929 | H14: =if(AND($C14<today(),G14>0), "Paid","N/A") -> Paid | I14: =if(AND($C14<today(),G14>0), "N/A","Balance") -> N/A | K14: =if(AND($C14<today(),J14>0), "Paid","N/A") -> N/A | L14: =if(AND($C14<today(),J14>0), "N/A","Balance") -> Balance | N14: =if(AND($C14<today(),M14>0), "Paid","N/A") -> N/A | O14: =if(AND($C14<today(),M14>0), "N/A","Balance") -> Balance | Q14: =if(AND($C14<today(),P14>0), "Paid","N/A") -> N/A | R14: =if(AND($C14<today(),P14>0), "N/A","Balance") -> Balance | T14: =if(AND($C14<today(),S14>0), "Paid","N/A") -> N/A | U14: =if(AND($C14<today(),S14>0), "N/A","Balance") -> Balance
B15: =sum(D15:Z15) -> 15929 | C15: 45170 | G15: 15929 | H15: =if(AND($C15<today(),G15>0), "Paid","N/A") -> Paid | I15: =if(AND($C15<today(),G15>0), "N/A","Balance") -> N/A | K15: =if(AND($C15<today(),J15>0), "Paid","N/A") -> N/A | L15: =if(AND($C15<today(),J15>0), "N/A","Balance") -> Balance | N15: =if(AND($C15<today(),M15>0), "Paid","N/A") -> N/A | O15: =if(AND($C15<today(),M15>0), "N/A","Balance") -> Balance | Q15: =if(AND($C15<today(),P15>0), "Paid","N/A") -> N/A | R15: =if(AND($C15<today(),P15>0), "N/A","Balance") -> Balance | T15: =if(AND($C15<today(),S15>0), "Paid","N/A") -> N/A | U15: =if(AND($C15<today(),S15>0), "N/A","Balance") -> Balance
B16: =sum(D16:Z16) -> 29929 | C16: 45200 | G16: 29929 | H16: =if(AND($C16<today(),G16>0), "Paid","N/A") -> Paid | I16: =if(AND($C16<today(),G16>0), "N/A","Balance") -> N/A | K16: =if(AND($C16<today(),J16>0), "Paid","N/A") -> N/A | L16: =if(AND($C16<today(),J16>0), "N/A","Balance") -> Balance | N16: =if(AND($C16<today(),M16>0), "Paid","N/A") -> N/A | O16: =if(AND($C16<today(),M16>0), "N/A","Balance") -> Balance | Q16: =if(AND($C16<today(),P16>0), "Paid","N/A") -> N/A | R16: =if(AND($C16<today(),P16>0), "N/A","Balance") -> Balance | T16: =if(AND($C16<today(),S16>0), "Paid","N/A") -> N/A | U16: =if(AND($C16<today(),S16>0), "N/A","Balance") -> Balance
B17: =sum(D17:Z17) -> 28347 | C17: 45231 | D17: =D$4 -> 12770 | E17: =if(AND($C17<today(),D17>0), "Paid","N/A") -> Paid | F17: =if(AND($C17<today(),D17>0), "N/A","Balance") -> N/A | G17: 15577 | H17: =if(AND($C17<today(),G17>0), "Paid","N/A") -> Paid | I17: =if(AND($C17<today(),G17>0), "N/A","Balance") -> N/A | K17: =if(AND($C17<today(),J17>0), "Paid","N/A") -> N/A | L17: =if(AND($C17<today(),J17>0), "N/A","Balance") -> Balance | N17: =if(AND($C17<today(),M17>0), "Paid","N/A") -> N/A | O17: =if(AND($C17<today(),M17>0), "N/A","Balance") -> Balance | Q17: =if(AND($C17<today(),P17>0), "Paid","N/A") -> N/A | R17: =if(AND($C17<today(),P17>0), "N/A","Balance") -> Balance | T17: =if(AND($C17<today(),S17>0), "Paid","N/A") -> N/A | U17: =if(AND($C17<today(),S17>0), "N/A","Balance") -> Balance
B18: =sum(D18:Z18) -> 28347 | C18: 45261 | D18: =D$4 -> 12770 | E18: =if(AND($C18<today(),D18>0), "Paid","N/A") -> Paid | F18: =if(AND($C18<today(),D18>0), "N/A","Balance") -> N/A | G18: 15577 | H18: =if(AND($C18<today(),G18>0), "Paid","N/A") -> Paid | I18: =if(AND($C18<today(),G18>0), "N/A","Balance") -> N/A | K18: =if(AND($C18<today(),J18>0), "Paid","N/A") -> N/A | L18: =if(AND($C18<today(),J18>0), "N/A","Balance") -> Balance | N18: =if(AND($C18<today(),M18>0), "Paid","N/A") -> N/A | O18: =if(AND($C18<today(),M18>0), "N/A","Balance") -> Balance | Q18: =if(AND($C18<today(),P18>0), "Paid","N/A") -> N/A | R18: =if(AND($C18<today(),P18>0), "N/A","Balance") -> Balance | T18: =if(AND($C18<today(),S18>0), "Paid","N/A") -> N/A | U18: =if(AND($C18<today(),S18>0), "N/A","Balance") -> Balance
B19: =sum(D19:Z19) -> 28347 | C19: 45292 | D19: =D$4 -> 12770 | E19: =if(AND($C19<today(),D19>0), "Paid","N/A") -> Paid | F19: =if(AND($C19<today(),D19>0), "N/A","Balance") -> N/A | G19: 15577 | H19: =if(AND($C19<today(),G19>0), "Paid","N/A") -> Paid | I19: =if(AND($C19<today(),G19>0), "N/A","Balance") -> N/A | K19: =if(AND($C19<today(),J19>0), "Paid","N/A") -> N/A | L19: =if(AND($C19<today(),J19>0), "N/A","Balance") -> Balance | N19: =if(AND($C19<today(),M19>0), "Paid","N/A") -> N/A | O19: =if(AND($C19<today(),M19>0), "N/A","Balance") -> Balance | Q19: =if(AND($C19<today(),P19>0), "Paid","N/A") -> N/A | R19: =if(AND($C19<today(),P19>0), "N/A","Balance") -> Balance | T19: =if(AND($C19<today(),S19>0), "Paid","N/A") -> N/A | U19: =if(AND($C19<today(),S19>0), "N/A","Balance") -> Balance
B20: =sum(D20:Z20) -> 28347 | C20: 45323 | D20: =D$4 -> 12770 | E20: =if(AND($C20<today(),D20>0), "Paid","N/A") -> Paid | F20: =if(AND($C20<today(),D20>0), "N/A","Balance") -> N/A | G20: 15577 | H20: =if(AND($C20<today(),G20>0), "Paid","N/A") -> Paid | I20: =if(AND($C20<today(),G20>0), "N/A","Balance") -> N/A | K20: =if(AND($C20<today(),J20>0), "Paid","N/A") -> N/A | L20: =if(AND($C20<today(),J20>0), "N/A","Balance") -> Balance | N20: =if(AND($C20<today(),M20>0), "Paid","N/A") -> N/A | O20: =if(AND($C20<today(),M20>0), "N/A","Balance") -> Balance | Q20: =if(AND($C20<today(),P20>0), "Paid","N/A") -> N/A | R20: =if(AND($C20<today(),P20>0), "N/A","Balance") -> Balance | T20: =if(AND($C20<today(),S20>0), "Paid","N/A") -> N/A | U20: =if(AND($C20<today(),S20>0), "N/A","Balance") -> Balance
B21: =sum(D21:Z21) -> 28347 | C21: 45352 | D21: =D$4 -> 12770 | E21: =if(AND($C21<today(),D21>0), "Paid","N/A") -> Paid | F21: =if(AND($C21<today(),D21>0), "N/A","Balance") -> N/A | G21: 15577 | H21: =if(AND($C21<today(),G21>0), "Paid","N/A") -> Paid | I21: =if(AND($C21<today(),G21>0), "N/A","Balance") -> N/A | K21: =if(AND($C21<today(),J21>0), "Paid","N/A") -> N/A | L21: =if(AND($C21<today(),J21>0), "N/A","Balance") -> Balance | N21: =if(AND($C21<today(),M21>0), "Paid","N/A") -> N/A | O21: =if(AND($C21<today(),M21>0), "N/A","Balance") -> Balance | Q21: =if(AND($C21<today(),P21>0), "Paid","N/A") -> N/A | R21: =if(AND($C21<today(),P21>0), "N/A","Balance") -> Balance | T21: =if(AND($C21<today(),S21>0), "Paid","N/A") -> N/A | U21: =if(AND($C21<today(),S21>0), "N/A","Balance") -> Balance
B22: =sum(D22:Z22) -> 28347 | C22: 45383 | D22: =D$4 -> 12770 | E22: =if(AND($C22<today(),D22>0), "Paid","N/A") -> Paid | F22: =if(AND($C22<today(),D22>0), "N/A","Balance") -> N/A | G22: 15577 | H22: =if(AND($C22<today(),G22>0), "Paid","N/A") -> Paid | I22: =if(AND($C22<today(),G22>0), "N/A","Balance") -> N/A | K22: =if(AND($C22<today(),J22>0), "Paid","N/A") -> N/A | L22: =if(AND($C22<today(),J22>0), "N/A","Balance") -> Balance | N22: =if(AND($C22<today(),M22>0), "Paid","N/A") -> N/A | O22: =if(AND($C22<today(),M22>0), "N/A","Balance") -> Balance | Q22: =if(AND($C22<today(),P22>0), "Paid","N/A") -> N/A | R22: =if(AND($C22<today(),P22>0), "N/A","Balance") -> Balance | T22: =if(AND($C22<today(),S22>0), "Paid","N/A") -> N/A | U22: =if(AND($C22<today(),S22>0), "N/A","Balance") -> Balance
B23: =sum(D23:Z23) -> 28347 | C23: 45413 | D23: =D$4 -> 12770 | E23: =if(AND($C23<today(),D23>0), "Paid","N/A") -> Paid | F23: =if(AND($C23<today(),D23>0), "N/A","Balance") -> N/A | G23: 15577 | H23: =if(AND($C23<today(),G23>0), "Paid","N/A") -> Paid | I23: =if(AND($C23<today(),G23>0), "N/A","Balance") -> N/A | K23: =if(AND($C23<today(),J23>0), "Paid","N/A") -> N/A | L23: =if(AND($C23<today(),J23>0), "N/A","Balance") -> Balance | N23: =if(AND($C23<today(),M23>0), "Paid","N/A") -> N/A | O23: =if(AND($C23<today(),M23>0), "N/A","Balance") -> Balance | Q23: =if(AND($C23<today(),P23>0), "Paid","N/A") -> N/A | R23: =if(AND($C23<today(),P23>0), "N/A","Balance") -> Balance | T23: =if(AND($C23<today(),S23>0), "Paid","N/A") -> N/A | U23: =if(AND($C23<today(),S23>0), "N/A","Balance") -> Balance
B24: =sum(D24:Z24) -> 28347 | C24: 45444 | D24: =D$4 -> 12770 | E24: =if(AND($C24<today(),D24>0), "Paid","N/A") -> Paid | F24: =if(AND($C24<today(),D24>0), "N/A","Balance") -> N/A | G24: 15577 | H24: =if(AND($C24<today(),G24>0), "Paid","N/A") -> Paid | I24: =if(AND($C24<today(),G24>0), "N/A","Balance") -> N/A | K24: =if(AND($C24<today(),J24>0), "Paid","N/A") -> N/A | L24: =if(AND($C24<today(),J24>0), "N/A","Balance") -> Balance | N24: =if(AND($C24<today(),M24>0), "Paid","N/A") -> N/A | O24: =if(AND($C24<today(),M24>0), "N/A","Balance") -> Balance | Q24: =if(AND($C24<today(),P24>0), "Paid","N/A") -> N/A | R24: =if(AND($C24<today(),P24>0), "N/A","Balance") -> Balance | T24: =if(AND($C24<today(),S24>0), "Paid","N/A") -> N/A | U24: =if(AND($C24<today(),S24>0), "N/A","Balance") -> Balance
B25: =sum(D25:Z25) -> 28347 | C25: 45474 | D25: =D$4 -> 12770 | E25: =if(AND($C25<today(),D25>0), "Paid","N/A") -> Paid | F25: =if(AND($C25<today(),D25>0), "N/A","Balance") -> N/A | G25: 15577 | H25: =if(AND($C25<today(),G25>0), "Paid","N/A") -> Paid | I25: =if(AND($C25<today(),G25>0), "N/A","Balance") -> N/A | K25: =if(AND($C25<today(),J25>0), "Paid","N/A") -> N/A | L25: =if(AND($C25<today(),J25>0), "N/A","Balance") -> Balance | N25: =if(AND($C25<today(),M25>0), "Paid","N/A") -> N/A | O25: =if(AND($C25<today(),M25>0), "N/A","Balance") -> Balance | Q25: =if(AND($C25<today(),P25>0), "Paid","N/A") -> N/A | R25: =if(AND($C25<today(),P25>0), "N/A","Balance") -> Balance | T25: =if(AND($C25<today(),S25>0), "Paid","N/A") -> N/A | U25: =if(AND($C25<today(),S25>0), "N/A","Balance") -> Balance
B26: =sum(D26:Z26) -> 28347 | C26: 45505 | D26: =D$4 -> 12770 | E26: =if(AND($C26<today(),D26>0), "Paid","N/A") -> Paid | F26: =if(AND($C26<today(),D26>0), "N/A","Balance") -> N/A | G26: 15577 | H26: =if(AND($C26<today(),G26>0), "Paid","N/A") -> Paid | I26: =if(AND($C26<today(),G26>0), "N/A","Balance") -> N/A | K26: =if(AND($C26<today(),J26>0), "Paid","N/A") -> N/A | L26: =if(AND($C26<today(),J26>0), "N/A","Balance") -> Balance | N26: =if(AND($C26<today(),M26>0), "Paid","N/A") -> N/A | O26: =if(AND($C26<today(),M26>0), "N/A","Balance") -> Balance | Q26: =if(AND($C26<today(),P26>0), "Paid","N/A") -> N/A | R26: =if(AND($C26<today(),P26>0), "N/A","Balance") -> Balance | T26: =if(AND($C26<today(),S26>0), "Paid","N/A") -> N/A | U26: =if(AND($C26<today(),S26>0), "N/A","Balance") -> Balance
B27: =sum(D27:Z27) -> 28347 | C27: 45536 | D27: =D$4 -> 12770 | E27: =if(AND($C27<today(),D27>0), "Paid","N/A") -> Paid | F27: =if(AND($C27<today(),D27>0), "N/A","Balance") -> N/A | G27: 15577 | H27: =if(AND($C27<today(),G27>0), "Paid","N/A") -> Paid | I27: =if(AND($C27<today(),G27>0), "N/A","Balance") -> N/A | K27: =if(AND($C27<today(),J27>0), "Paid","N/A") -> N/A | L27: =if(AND($C27<today(),J27>0), "N/A","Balance") -> Balance | N27: =if(AND($C27<today(),M27>0), "Paid","N/A") -> N/A | O27: =if(AND($C27<today(),M27>0), "N/A","Balance") -> Balance | Q27: =if(AND($C27<today(),P27>0), "Paid","N/A") -> N/A | R27: =if(AND($C27<today(),P27>0), "N/A","Balance") -> Balance | T27: =if(AND($C27<today(),S27>0), "Paid","N/A") -> N/A | U27: =if(AND($C27<today(),S27>0), "N/A","Balance") -> Balance
B28: =sum(D28:Z28) -> 28347 | C28: 45566 | D28: =D$4 -> 12770 | E28: =if(AND($C28<today(),D28>0), "Paid","N/A") -> Paid | F28: =if(AND($C28<today(),D28>0), "N/A","Balance") -> N/A | G28: 15577 | H28: =if(AND($C28<today(),G28>0), "Paid","N/A") -> Paid | I28: =if(AND($C28<today(),G28>0), "N/A","Balance") -> N/A | K28: =if(AND($C28<today(),J28>0), "Paid","N/A") -> N/A | L28: =if(AND($C28<today(),J28>0), "N/A","Balance") -> Balance | N28: =if(AND($C28<today(),M28>0), "Paid","N/A") -> N/A | O28: =if(AND($C28<today(),M28>0), "N/A","Balance") -> Balance | Q28: =if(AND($C28<today(),P28>0), "Paid","N/A") -> N/A | R28: =if(AND($C28<today(),P28>0), "N/A","Balance") -> Balance | T28: =if(AND($C28<today(),S28>0), "Paid","N/A") -> N/A | U28: =if(AND($C28<today(),S28>0), "N/A","Balance") -> Balance
B29: =sum(D29:Z29) -> 38512 | C29: 45597 | D29: =D$4 -> 12770 | E29: =if(AND($C29<today(),D29>0), "Paid","N/A") -> Paid | F29: =if(AND($C29<today(),D29>0), "N/A","Balance") -> N/A | G29: 15577 | H29: =if(AND($C29<today(),G29>0), "Paid","N/A") -> Paid | I29: =if(AND($C29<today(),G29>0), "N/A","Balance") -> N/A | J29: 10165 | K29: =if(AND($C29<today(),J29>0), "Paid","N/A") -> Paid | L29: =if(AND($C29<today(),J29>0), "N/A","Balance") -> N/A | N29: =if(AND($C29<today(),M29>0), "Paid","N/A") -> N/A | O29: =if(AND($C29<today(),M29>0), "N/A","Balance") -> Balance | Q29: =if(AND($C29<today(),P29>0), "Paid","N/A") -> N/A | R29: =if(AND($C29<today(),P29>0), "N/A","Balance") -> Balance | T29: =if(AND($C29<today(),S29>0), "Paid","N/A") -> N/A | U29: =if(AND($C29<today(),S29>0), "N/A","Balance") -> Balance
B30: =sum(D30:Z30) -> 37637 | C30: 45627 | D30: =D$4 -> 12770 | E30: =if(AND($C30<today(),D30>0), "Paid","N/A") -> Paid | F30: =if(AND($C30<today(),D30>0), "N/A","Balance") -> N/A | G30: 15577 | H30: =if(AND($C30<today(),G30>0), "Paid","N/A") -> Paid | I30: =if(AND($C30<today(),G30>0), "N/A","Balance") -> N/A | J30: 9290 | K30: =if(AND($C30<today(),J30>0), "Paid","N/A") -> Paid | L30: =if(AND($C30<today(),J30>0), "N/A","Balance") -> N/A | N30: =if(AND($C30<today(),M30>0), "Paid","N/A") -> N/A | O30: =if(AND($C30<today(),M30>0), "N/A","Balance") -> Balance | Q30: =if(AND($C30<today(),P30>0), "Paid","N/A") -> N/A | R30: =if(AND($C30<today(),P30>0), "N/A","Balance") -> Balance | T30: =if(AND($C30<today(),S30>0), "Paid","N/A") -> N/A | U30: =if(AND($C30<today(),S30>0), "N/A","Balance") -> Balance
B31: =sum(D31:Z31) -> 37637 | C31: 45658 | D31: =D$4 -> 12770 | E31: =if(AND($C31<today(),D31>0), "Paid","N/A") -> Paid | F31: =if(AND($C31<today(),D31>0), "N/A","Balance") -> N/A | G31: 15577 | H31: =if(AND($C31<today(),G31>0), "Paid","N/A") -> Paid | I31: =if(AND($C31<today(),G31>0), "N/A","Balance") -> N/A | J31: 9290 | K31: =if(AND($C31<today(),J31>0), "Paid","N/A") -> Paid | L31: =if(AND($C31<today(),J31>0), "N/A","Balance") -> N/A | N31: =if(AND($C31<today(),M31>0), "Paid","N/A") -> N/A | O31: =if(AND($C31<today(),M31>0), "N/A","Balance") -> Balance | Q31: =if(AND($C31<today(),P31>0), "Paid","N/A") -> N/A | R31: =if(AND($C31<today(),P31>0), "N/A","Balance") -> Balance | T31: =if(AND($C31<today(),S31>0), "Paid","N/A") -> N/A | U31: =if(AND($C31<today(),S31>0), "N/A","Balance") -> Balance
B32: =sum(D32:Z32) -> 37637 | C32: 45689 | D32: =D$4 -> 12770 | E32: =if(AND($C32<today(),D32>0), "Paid","N/A") -> Paid | F32: =if(AND($C32<today(),D32>0), "N/A","Balance") -> N/A | G32: 15577 | H32: =if(AND($C32<today(),G32>0), "Paid","N/A") -> Paid | I32: =if(AND($C32<today(),G32>0), "N/A","Balance") -> N/A | J32: 9290 | K32: =if(AND($C32<today(),J32>0), "Paid","N/A") -> Paid | L32: =if(AND($C32<today(),J32>0), "N/A","Balance") -> N/A | N32: =if(AND($C32<today(),M32>0), "Paid","N/A") -> N/A | O32: =if(AND($C32<today(),M32>0), "N/A","Balance") -> Balance | Q32: =if(AND($C32<today(),P32>0), "Paid","N/A") -> N/A | R32: =if(AND($C32<today(),P32>0), "N/A","Balance") -> Balance | T32: =if(AND($C32<today(),S32>0), "Paid","N/A") -> N/A | U32: =if(AND($C32<today(),S32>0), "N/A","Balance") -> Balance
B33: =sum(D33:Z33) -> 37637 | C33: 45717 | D33: =D$4 -> 12770 | E33: =if(AND($C33<today(),D33>0), "Paid","N/A") -> Paid | F33: =if(AND($C33<today(),D33>0), "N/A","Balance") -> N/A | G33: 15577 | H33: =if(AND($C33<today(),G33>0), "Paid","N/A") -> Paid | I33: =if(AND($C33<today(),G33>0), "N/A","Balance") -> N/A | J33: 9290 | K33: =if(AND($C33<today(),J33>0), "Paid","N/A") -> Paid | L33: =if(AND($C33<today(),J33>0), "N/A","Balance") -> N/A | N33: =if(AND($C33<today(),M33>0), "Paid","N/A") -> N/A | O33: =if(AND($C33<today(),M33>0), "N/A","Balance") -> Balance | Q33: =if(AND($C33<today(),P33>0), "Paid","N/A") -> N/A | R33: =if(AND($C33<today(),P33>0), "N/A","Balance") -> Balance | T33: =if(AND($C33<today(),S33>0), "Paid","N/A") -> N/A | U33: =if(AND($C33<today(),S33>0), "N/A","Balance") -> Balance
